Workbook
Name OLE_LINK1: #REF!
Name OLE_LINK1: #REF!
Name rngCeilingAm: #REF!
Name rngCeilingCnt: #REF!
Name rngCeilingVal: #REF!
Name rngFloorAm: #REF!
Name rngFloorCnt: #REF!
Name rngFloorVal: #REF!
Name rngMaximum: #REF!
Name rngMinimum: #REF!
Name rngNegCnt: #REF!
Name rngNegVal: #REF!
Name rngRecInDwnld: #REF!
Name rngRecInDwnldVal: #REF!
Name rngSmpSz1: #REF!
Name rngSmpSz2: #REF!
Name rngSmpSz3: #REF!
Name rngSmpSz4: #REF!
Name rngSmpSz5: #REF!
Name rngSmpSz6: #REF!
Name rngStr1BrkVal: #REF!
Name rngStr2BrkVal: #REF!
Name rngStr3BrkVal: #REF!
Name rngStr4BrkVal: #REF!
Name rngStr5BrkVal: #REF!
Name rngUnitsSmpCnt: #REF!
Name rngUnitsSmpVal: #REF!
Name rngUnSz1: #REF!
Name rngUnSz1Val: #REF!
Name rngUnSz2: #REF!
Name rngUnSz2Val: #REF!
Name rngUnSz3: #REF!
Name rngUnSz3Val: #REF!
Name rngUnSz4: #REF!
Name rngUnSz4Val: #REF!
Name rngUnSz5: #REF!
Name rngUnSz5Val: #REF!
Name rngUnSz6: #REF!
Name rngUnSz6Val: #REF!

Sheet Guidelines
A1: AGENCY | B1: Local | C1: OOS | D1: Agency is the Applicant | E1: No Agency | F1: Local | G1: OOS | H1: Agency is the Applicant | I1: No Agency
A2: PRODCO | B2: Local | C2: Local | D2: Local | E2: Local | F2: OOS | G2: OOS | H2: OOS | I2: OOS
A3: Crew Payroll Tab | B3: Enter all back up | C3: Enter all back up | D3: Enter all back up | E3: Enter all back up | F3: Enter all back up | G3: Enter all back up | H3: Enter all back up | I3: Enter all back up
A4: Crew Expenses Tab | B4: Enter one line & NO-IL | C4: Enter one line & NO-IL | D4: Enter one line & NO-IL | E4: Enter one line & NO-IL | F4: Enter one line & NO-IL, except break out Receipts/Invoices ≥$200.00 paid with CC | G4: Enter all back up | H4: Enter all back up | I4: Enter all back up
A5: Production Tab | B5: Enter Vendor PO #, Name, Amount, Description, link & NO-IL | C5: Enter Vendor PO #, Name, Amount, Description, link & NO-IL | D5: Enter Vendor PO #, Name, Amount, Description, link & NO-IL | E5: Enter Vendor PO #, Name, Amount, Description, link & NO-IL | F5: Enter all back up | G5: Enter all back up | H5: Enter all back up | I5: Enter all back up
A6: Prod CC Tab | B6: Enter one line & NO-IL | C6: Enter one line & NO-IL | D6: Enter one line & NO-IL | E6: Enter one line & NO-IL | F6: Enter one line & NO-IL, except break out Receipts/Invoices ≥$200.00 paid with CC | G6: Enter all back up | H6: Enter all back up | I6: Enter all back up
A7: Petty Cash Tab | B7: Enter one line & NO-IL | C7: Enter one line & NO-IL | D7: Enter one line & NO-IL | E7: Enter one line & NO-IL | F7: Enter one line & NO-IL, except break out Receipts/Invoices ≥$200.00 paid with CC | G7: Enter all back up | H7: Enter all back up | I7: Enter all back up
A8: Client Billings | B8: Request a Summary Invoice (s) | C8: Request a Summary Invoice (s) | D8: Request a Summary Invoice (s) | E8: Request a Summary Invoice (s) | F8: Request a Summary Invoice (s) | G8: Request a Summary Invoice (s) | H8: Request a Summary Invoice (s) | I8: Request a Summary Invoice (s)
A10: Split Receipts | B10: û | C10: x | D10: x | E10: x | F10: Needed if qualified ProdCo exps are less than 50% of ProdCo billings | G10: ü | H10: ü | I10: ü
A11: Alcohol Split Receipts | B11: û | C11: û | D11: û | E11: û | F11: ü | G11: ü | H11: ü | I11: ü
A12: Hotel Charges Summary | B12: û | C12: û | D12: û | E12: û | F12: Needed if qualified ProdCo exps are less than 50% of ProdCo billings; when meals are $300 and above | G12: When meals are $300 and above | H12: When meals are $300 and above | I12: When meals are $300 and above
A14: Local Agency - will qualify client billings less deductions
A15: Local ProdCo - will qualify ProdCo billings
A16: Local Agency - OOS ProdCo - can still qualify entire ProdCo billings, regardless of qualified ProdCo Vendors (at least 50%)
A18: WHAT'S INCLUDED IN THE CPA WORKBOOK?
A19: AGENCY
A20: Client Billings - Agency | B20: Include, deduct OOS agency exps if detailed billings | C20: Exclude, submit billings in the State Sub Folder | D20: Exclude | E20: N/A | F20: Include, deduct OOS agency exps if detailed billings | G20: Exclude, submit billings in the State Sub Folder | H20: Exclude | I20: N/A
A21: Agency IL Vendors | B21: Include | C21: Include | D21: Include | E21: N/A | F21: Include | G21: Include | H21: Include | I21: N/A
A22: Agency Hours Letter | B22: Include, will increase qualified amount if with retainer fee | C22: N/A | D22: Include, will increase qualified amount if with retainer fee | E22: N/A | F22: Include, will increase qualified amount if with retainer fee | G22: N/A | H22: Include, will increase qualified amount if with retainer fee | I22: N/A
A23: Talent | B23: Include - PTIP amounts in Talent Tab; Qualify entire invoice amount if at least 1 talent qualifies in the Client Billing; will affect total amount if Client Billing is detailed | C23: Include, use PTIP report as reference | D23: Include, use PTIP report as reference | E23: N/A | F23: Include - PTIP amounts in Talent Tab; Qualify entire invoice amount if at least 1 talent qualifies in the Client Billing; will affect total amount if Client Billing is detailed | G23: Include, will increase amount qualified | H23: Include, will increase amount qualified | I23: N/A
A24: Agency Exp Reports | B24: Include if detailed billings; Exclude if summary billings | C24: Include | D24: Include | E24: N/A | F24: Include if detailed billings; Exclude if summary billings | G24: Include | H24: Include | I24: N/A
A25: OOS Crew - paid by Agency | B25: Include if detailed client billings; Exclude if summary billings | C25: Include | D25: Include | E25: Include if detailed client billings; Exclude if summary billings | F25: Exclude | G25: Include | H25: Include | I25: N/A
A27: PRODCO
A28: ProdCo Billings | B28: Include | C28: Include | D28: Include | E28: Include | F28: Exclude, submit billings in the State Submission folder | G28: Exclude, submit billings in the State Sub Folder | H28: Exclude, submit billings in the State Sub Folder | I28: N/A
A29: ProdCo IL Vendors | B29: Exclude | C29: Exclude | D29: Exclude | E29: Exclude | F29: Include | G29: Include | H29: Include | I29: Include
A30: Prod Crew Payroll | B30: Include, will be deducted from Total Vendor Expenses (CPA Presentation) | C30: Include, will be deducted from Total Vendor Expenses (CPA Presentation) | D30: Include, will be deducted from Total Vendor Expenses (CPA Presentation) | E30: Include, will be deducted from Total Vendor Expenses (CPA Presentation) | F30: Include, will be deducted from Total Vendor Expenses (CPA Presentation) | G30: Include, will increase qualified spend | H30: Include, will increase qualified spend | I30: Include, will be deducted from Total Vendor Expenses (CPA Presentation)
A31: Prod CC | B31: Exclude | C31: Exclude | D31: Exclude | E31: Exclude | F31: Needed if qualified ProdCo exps are less than 50% of ProdCo billings | G31: Include | H31: Include | I31: Include
A32: Prod Petty Cash | B32: Exclude | C32: Exclude | D32: Exclude | E32: Exclude | F32: Needed if qualified ProdCo exps are less than 50% of ProdCo billings | G32: Include | H32: Include | I32: Include
A33: Crew Expenses | B33: Exclude | C33: Exclude | D33: Exclude | E33: Exclude | F33: Needed if qualified ProdCo exps are less than 50% of ProdCo billings | G33: Include | H33: Include | I33: Include
A34: Talent | B34: Include (will be deducted from Total Vendor Expenses) | C34: Include (will be deducted from Total Vendor Expenses) | D34: Include | E34: Include (will be deducted from Total Vendor Expenses) | F34: Include | G34: Include | H34: Include | I34: Include
A35: OOS Crew - paid by ProdCo | B35: Exclude | C35: Exclude | D35: Exclude | E35: Exclude | F35: Needed if qualified ProdCo exps are less than 50% of ProdCo billings | G35: Include | H35: Include | I35: Include

Sheet Comm Summary (O-L,N-L)
A1: TPC Commercial Incentives Service
A2: Commercial Project Summary
B4: Project Description | F4: State: | H4: Illinois | X4: ECS Company code: | Y4: Elite CIS
B5: Project Title:
B7: Award Date:
B8: Pre Pro Date: | H8: LIVE ACTION | X8: Rebate Estimate Analysis | AB8: STILL
B9: Shoot Date:
B10: Production Wrap Date | H10: SUBMITTED EXPENSES | N10: QUALIFIED EXPENSES | T10: Pending | V10: DNQ | X10: Amount | Y10: Difference
B11: Post Production Date: | H11: PRODUCTION COMPANY | AB11: To have additional columns here if there's another shoot/ production (to not create another workbook)
B12: ProdCo Job Type(s): | H12: Crew Payroll | K12: ='Crew Payroll'!AE45 -> 0 | N12: Total Crew Payroll | Q12: =P13+P14 -> 0 | T12: ='Crew Payroll'!U53 -> 0 | V12: =K12-(Q12+T12) -> 0 | AB12: Create Crew Payroll, Production, and other applicable tabs and create formulas to get total Submitted and Qualified costs.
B13: ProdCo Job Notes: | O13: IL Crew Payroll | P13: ='Crew Payroll'!S53 -> 0
B14: OOS Shoot Job Type & Location | O14: OOS Crew | P14: ='Crew Payroll'!S54 -> 0
B15: OOS Shoot Date(s): | H15: ProdCo Sub-Vendors | K15: =#REF! -> #REF! | N15: ProdCo Sub-Vendors | Q15: =#REF! -> #REF! | T15: =#REF! -> #REF! | V15: =K15-(Q15+T15) -> #REF!
H16: Prod - Petty Cash | K16: =#REF! -> #REF! | N16: Prod - Petty Cash | Q16: =#REF! -> #REF! | T16: =#REF! -> #REF! | V16: =K16-(Q16+T16) -> #REF!
B17: Client: | H17: Prod - Credit Card | K17: =#REF! -> #REF! | N17: Prod - Credit Card | Q17: =#REF! -> #REF! | T17: =#REF! -> #REF! | V17: =K17-(Q17+T17) -> #REF!
B18: Client Brand & Product: | H18: Prod - Exp Reports | K18: =#REF! -> #REF! | N18: Prod - Exp Reports | Q18: =#REF! -> #REF! | T18: =#REF! -> #REF! | V18: =K18-(Q18+T18) -> #REF!
B19: Agency:
B20: Production Company: | D20: OOS Agency or No Agency | H20: Total Talent | K20: =SUM('Talent & Extras'!T63) -> 0 | N20: Total Talent | Q20: ='Talent & Extras'!N81 -> 0 | T20: ='Talent & Extras'!M69 -> 0 | V20: =K20-(Q20+T20) -> 0
B21: Subcontracted ProdCo: | D21: Local ProdCo (Motion) | I21: Talent Payroll | J21: ='Talent & Extras'!Q69 -> 0 | O21: Talent Payroll | P21: ='Talent & Extras'!D69 -> 0
B22: OOS Shoot Prod Company: | D22: Local ProdCo (Still) | I22: Extras Payroll | J22: ='Talent & Extras'!C71 -> 0 | O22: Extras Payroll | P22: ='Talent & Extras'!D70 -> 0
B23: Crew Payroll Company: | O23: Two (2) OOS Talent | P23: ='Talent & Extras'!R69 -> 0
B24: Celebrity Payroll Company: | O24: Handling Fees | P24: ='Agency Sub-Vendors'!M69 -> 0
B25: Talent Payroll Company: | O25: Agency Fees | P25: ='Agency Sub-Vendors'!M68 -> 0
B26: Production Insurance: | H26: Agency Sub-Vendors | K26: ='Agency Sub-Vendors'!M63 -> 0 | N26: Total Sub-Vendors | Q26: ='Agency Sub-Vendors'!M60 -> 0 | T26: ='Agency Sub-Vendors'!M61 -> 0 | V26: =K26-(Q26+T26) -> 0
B27: Other Payor 2: | H27: Agency Hours | K27: ='Agency Hours'!T43 -> 0 | N27: Normal Agency Hours | Q27: ='Agency Hours'!Q71 -> 0 | T27: ='Agency Hours'!O43 -> 0 | V27: =K27-(Q27+T27) -> 0
B28: Other Payor 3: | O28: IL Crew | P28: ='Agency Hours'!Q58 -> 0
O29: OOS Crew | P29: ='Agency Hours'!R43 -> 0
B30: Celebrity Name(s):
I31: Retainer Billings | J31: ='Agency Hours'!J49 -> 0 | O31: Retainer Billings | P31: ='Agency Hours'!S49 -> 0 | U31: ='Agency Hours'!O49 -> 0 | V31: =J31-(P31+U31) -> 0
B32: Agency Job Description:
B33: Agency Job Name: | H33: Prod Agency Hours | K33: ='Agency Hours'!Q68 -> 0 | N33: Production Agency Hours | Q33: ='Agency Hours'!Q64+'Agency Hours'!Q65 -> 0 | T33: ='Agency Hours'!O55 -> 0 | V33: =K33-(Q33+T33) -> 0
B34: Agency Job Number: | O34: IL Crew | P34: ='Agency Hours'!S55 -> 0
O35: OOS Crew | P35: ='Agency Hours'!R55 -> 0
C36: AICP Bid | D36: 0
C37: Agency Estimate | D37: 0 | H37: Agency Exp. Report | K37: =#REF! -> #REF! | N37: Agency Exp. Report | Q37: =#REF! -> #REF! | T37: =#REF! -> #REF! | V37: =K37-(Q37+T37) -> #REF!
C38: Final Script/Storyboard Date | H38: Client - Crew | K38: 0 | N38: Client | Q38: 0 | T38: 0 | V38: =K38-(Q38+T38) -> 0
C39: Application & Boards | H39: Client - Sub-Vendors | K39: 0 | N39: Client - Sub-Vendors | Q39: 0 | T39: 0 | V39: =K39-(Q39+T39) -> 0
C40: APC | H40: Consultant | K40: 0 | N40: Consultant | Q40: 0 | T40: 0 | V40: =K40-(Q40+T40) -> 0
C41: Pre-Production Book | I41: Consultant Retainer Fee | J41: 0 | O41: Consultant Retainer Fee | P41: 0 | U41: 0 | V41: 0
C42: Call Sheet | H42: CPA Fee | K42: 0 | N42: CPA Fee | Q42: 0 | U42: 0 | V42: =K42-(Q42+T42) -> 0
C43: Diversity Tracking Sheet (Including Agency) | H43: Total Submitted costs: | K43: =SUM(K12:K42) -> #REF! | N43: Total Qualified costs: | Q43: =SUM(Q12:Q42)+P24+P25 -> #REF! | T43: 0 | V43: 0
C44: Vendor Diversity Summary
C45: Shoot Location/s: | O45: All Qualified OOS | P45: =P14+P23+P29+P35 -> 0
B47: Spots:
C49: PO Log
C50: Job Cost Detail | D50: 0 | J50: QUALIFIED AMOUNT FOR CPA
C51: Total ProdCo Billings | D51: =Billings!H49 -> 0
C52: Total Client Billings | D52: =Billings!E41 -> 0 | J52: OOS-Local/ None-Local | O52: CPA Workbook | Q52: Audit Adjustment | R52: Tax Credit
C53: Total Amount Spent on Project | D53: =Billings!E40 -> 0 | L53: Amount
D54: =SUM(Billings!F29:F30) -> 0 | J54: ProdCo Billings | L54: =D52 -> 0 | P54: =O54-L54 -> 0 | R54: =O54+Q54 -> 0
E55: % | J55: IL Agency Expenses
K56: Non-Resident Labor | L56: =P14+P23+P28 -> 0 | P56: =O56-L56 -> 0 | R56: =O56+Q56 -> 0
D57: Difference | E57: =SUM(K12:K18)/D37 -> #REF! | K57: Talent | L57: =P21 -> 0 | P57: =O57-L57 -> 0 | R57: =O57+Q57 -> 0
C58: AICP vs ProdCo Submitted | E58: =SUM(K12:K19)/D50 -> #REF! | K58: Extras | L58: =P22 -> 0 | P58: =O58-L58 -> 0 | R58: =O58+Q58 -> 0
C59: PO Log vs ProdCo Amount Entered | D59: =SUM(K12:K19)-D37 -> #REF! | E59: {=SUM(K12:K18/D52)} -> #DIV/0! | K59: Agency Sub-Vendors | L59: =Q24 -> 0 | P59: =O59-L59 -> 0 | R59: =O59+Q59 -> 0
C60: ProdCo Submitted vs ProdCo Billings | D60: =SUM(K12:K18)-D50 -> #REF! | E60: =SUM(Q11:Q19)/D52 -> #REF! | K60: Agency Exps | L60: =Q29 -> 0 | P60: =O60-L60 -> 0 | R60: =O60+Q60 -> 0
C61: ProdCo Qualified vs ProdCo Billings | D61: =SUM(K12:K18)-D52 -> #REF! | J61: Consultant Hours | P61: =O61-L61 -> 0 | R61: =O61+Q61 -> 0
D62: =SUM(Q12:Q18)-D52 -> #REF! | E62: =SUM(K23:K28)/D51 -> #DIV/0! | J62: CPA Fee | L62: =Q42 -> 0 | P62: =O62-L62 -> 0 | R62: =O62+Q62 -> 0
C63: JCD vs Agency Amount Entered | E63: =D53/D38 -> #DIV/0! | J63: QUALIFIED SPEND | L63: =SUM(L54:L62) -> 0 | M63: =L63/J79 -> #DIV/0! | N63: of rebate estimate | P63: =O63-L63 -> 0
C64: Agency Estimate vs Client Billings | D64: =SUM(Q20:Q24)-D51 -> 0 | O64: =O63-SUM(O54:O62) -> 0 | Q64: =Q63-SUM(Q54:Q62) -> 0 | R64: =R63-SUM(R54:R62) -> 0
D65: =D53-D38 -> 0 | J65: Tax Incentive Amount | L65: =L63*0.3 -> 0 | P65: =O65-L65 -> 0 | R65: =O65+Q65 -> 0
J66: Add'l 15% | L66: =(0)*0.15 -> 0 | P66: =O66-L66 -> 0 | R66: =O66+Q66 -> 0
C67: UPLIFTS | J67: Total Tax Credit Amount | L67: =SUM(L65:L66) -> 0 | P67: =O67-L67 -> 0 | R67: =O67+Q67 -> 0
C68: Green Sustainability Uplift
C69: Rural Area Uplift | D69: FALSE
D70: FALSE
J71: REBATE ESTIMATE | K71: CPA QUALIFIED
B72: ProdCo Materials Entered by:
B73: Reviewed by: | I73: ProdCo | J73: 0 | K73: =L54 -> 0 | L73: =K73-J73 -> 0 | M73: {=_xlfn.IFS(L73>0,"Over Budget",L73<0,"Under Budget",L73=0,"-")} -> -
I74: Agency Exps | J74: 0 | K74: =SUM(L56:L60) -> 0 | L74: =K74-J74 -> 0 | M74: {=_xlfn.IFS(L74>0,"Over Budget",L74<0,"Under Budget",L74=0,"-")} -> -
I75: Agency Hours | J75: 0 | K75: 0 | L75: =K75-J75 -> 0 | M75: {=_xlfn.IFS(L75>0,"Over Budget",L75<0,"Under Budget",L75=0,"-")} -> -
B76: Agency Materials Entered by: | I76: Project Fee | J76: 0 | K76: 0 | L76: =K76-J76 -> 0 | M76: {=_xlfn.IFS(L76>0,"Over Budget",L76<0,"Under Budget",L76=0,"-")} -> -
B77: Reviewed by: | I77: Consultant | J77: 0 | K77: =L60 -> 0 | L77: =K77-J77 -> 0 | M77: {=_xlfn.IFS(L77>0,"Over Budget",L77<0,"Under Budget",L77=0,"-")} -> -
I78: CPA | J78: 0 | K78: =L62 -> 0 | L78: =K78-J78 -> 0 | M78: {=_xlfn.IFS(L78>0,"Over Budget",L78<0,"Under Budget",L78=0,"-")} -> -
I79: TOTAL QUALIFIED SPEND | K79: =SUM(K73:K78) -> 0 | L79: =K79-J79 -> 0 | M79: {=_xlfn.IFS(L79>0,"Over Budget",L79<0,"Under Budget",L79=0,"-")} -> -
B80: CPA Prepped by: | J80: =J79-SUM(J73:J78) -> 0 | K80: =O63-K79 -> 0 | Q80: IL Transfer Fee | U80: ((((Qualified Spend - Non Resident Labor) * 0.3) + Bonus Incentive Amount ) * 0.0025) + ((Non Resident Labor * 0.3) * 0.025)
B81: CPA Review by:
I82: Tax Credit (30%) | Q82: Qualified Spend No OOS | R82: =L63-P45 -> 0
I83: Gross Rebate | J83: =J79*0.3 -> 0 | K83: =L67 -> 0 | Q83: State Rebate % | R83: 0.3
I84: Est. Transfer Costs (11.00%) | J84: =-(J83*0.11) -> 0 | K84: =-K83*0.11 -> 0 | N84: {=_xlfn.IFS(M84>0,"Over Budget",M84<0,"Under Budget",M84=0,"-")} -> - | R84: =R82*R83 -> 0
I85: Net Proceeds | J85: =SUM(J83:J84) -> 0 | K85: =SUM(K83:K84) -> 0 | Q85: Bonus Incentive | R85: =L66 -> 0
I86: Reimbursable Expenses | R86: =R84+R85 -> 0
I87: Admin Fee | J87: 0 | K87: =J87 -> 0 | R87: 0.0025
I88: IL Transfer Fee | J88: 0 | K88: =-R96 -> 0 | R88: =R87*R86 -> 0
I89: CPA Fee | J89: 0 | K89: =J89 -> 0
I90: Net Rebate | J90: =SUM(J85:J89) -> 0 | K90: =SUM(K85:K89) -> 0 | Q90: Qualified Spend OOS | R90: =P45 -> 0
I91: TPC Fee (22.50%) | J91: =-(J90*0.225) -> 0 | K91: =-K90*0.225 -> 0 | Q91: State Rebate % | R91: 0.3
I92: Net to Brand | J92: =SUM(J90:J91) -> 0 | K92: =SUM(K90:K91) -> 0 | L92: =K92-J92 -> 0 | M92: {=_xlfn.IFS(L92>0,"Over Budget",L92<0,"Under Budget",L92=0,"-")} -> - | R92: =R90*R91 -> 0
I93: Reported range | R93: 0.025
R94: =R92*R93 -> 0 | S94: =(R90+R82)-L62 -> 0
Q96: IL Transfer Fee Total | R96: =R88+R94 -> 0

Sheet Comm Summary (A-L)
A1: TPC Commercial Incentives Service
A2: Commercial Project Summary
B4: Project Description | C4: =CONCATENATE(C17, " ",C18, " ",C5) -> Digitas "2022 Q3 Eggo Liege TV" | F4: State: | H4: Illinois | V4: ECS Company code: | W4: Elite CIS
B5: Project Title: | C5: "2022 Q3 Eggo Liege TV"
B7: Award Date:
B8: Pre Pro Date: | H8: LIVE ACTION | X8: Rebate Estimate Analysis | AB8: STILL
B9: Shoot Date:
B10: Production Wrap Date | H10: SUBMITTED EXPENSES | N10: QUALIFIED EXPENSES | T10: Pending | V10: DNQ | X10: Amount | Y10: Difference
B11: Post Production Date: | H11: PRODUCTION COMPANY | AB11: To have additional columns here if there's another shoot/ production (to not create another workbook)
B12: ProdCo Job Type(s): | H12: Crew Payroll | K12: ='Crew Payroll'!AE45 -> 0 | N12: Total Crew Payroll | Q12: =P13+P14 -> 0 | T12: ='Crew Payroll'!U53 -> 0 | V12: =K12-(Q12+T12) -> 0 | AB12: Create Crew Payroll, Production, and other applicable tabs and create formulas to get total Submitted and Qualified costs.
B13: ProdCo Job Notes: | O13: IL Crew Payroll | P13: ='Crew Payroll'!S53 -> 0
B14: OOS Shoot Job Type & Location | O14: OOS Crew | P14: ='Crew Payroll'!S54 -> 0
B15: OOS Shoot Date(s): | H15: ProdCo Sub-Vendors | K15: =#REF! -> #REF! | N15: ProdCo Sub-Vendors | Q15: =#REF! -> #REF! | T15: =#REF! -> #REF! | V15: =K15-(Q15+T15) -> #REF!
H16: Prod - Petty Cash | K16: =#REF! -> #REF! | N16: Prod - Petty Cash | Q16: =#REF! -> #REF! | T16: =#REF! -> #REF! | V16: =K16-(Q16+T16) -> #REF!
B17: Client: | C17: Digitas | H17: Prod - Credit Card | K17: =#REF! -> #REF! | N17: Prod - Credit Card | Q17: =#REF! -> #REF! | T17: =#REF! -> #REF! | V17: =K17-(Q17+T17) -> #REF!
B18: Client Brand & Product: | H18: Prod - Exp Reports | K18: =#REF! -> #REF! | N18: Prod - Exp Reports | Q18: =#REF! -> #REF! | T18: =#REF! -> #REF! | V18: =K18-(Q18+T18) -> #REF!
B19: Agency: | C19: Digitas | D19: Local Agency or Agency is Applicant | Z19: AICP less identified OOS
B20: Production Company: | C20: Picrow, Inc | D20: Local ProdCo (Motion) | H20: Total Talent | K20: =SUM('Talent & Extras'!T63) -> 0 | N20: Total Talent | Q20: ='Talent & Extras'!N81 -> 0 | T20: ='Talent & Extras'!M69 -> 0 | V20: =K20-(Q20+T20) -> 0
B21: Subcontracted ProdCo: | C21: Gabe Sanchez | D21: Local ProdCo (Still) | I21: Talent Payroll | J21: ='Talent & Extras'!Q69 -> 0 | O21: Talent Payroll | P21: ='Talent & Extras'!D69 -> 0
B22: OOS Shoot Prod Company: | I22: Extras Payroll | J22: ='Talent & Extras'!C71 -> 0 | O22: Extras Payroll | P22: ='Talent & Extras'!D70 -> 0
B23: Crew Payroll Company: | C23: Greenslate | O23: Two (2) OOS Talent | P23: ='Talent & Extras'!R69 -> 0
B24: Celebrity Payroll Company: | O24: Handling Fees | P24: ='Agency Sub-Vendors'!M69 -> 0
B25: Talent Payroll Company: | C25: Extreme Reach Talent, Inc | O25: Agency Fees | P25: ='Agency Sub-Vendors'!M68 -> 0
B26: Production Insurance: | H26: Agency Sub-Vendors | K26: ='Agency Sub-Vendors'!M63 -> 0 | N26: Total Sub-Vendors | Q26: ='Agency Sub-Vendors'!M60 -> 0 | T26: ='Agency Sub-Vendors'!M61 -> 0 | V26: =K26-(Q26+T26) -> 0
B27: Other Payor 2: | H27: Agency Hours | K27: ='Agency Hours'!T43 -> 0 | N27: Normal Agency Hours | Q27: ='Agency Hours'!Q71 -> 0 | T27: ='Agency Hours'!O43 -> 0 | V27: =K27-(Q27+T27) -> 0
B28: Other Payor 3: | O28: IL Crew | P28: ='Agency Hours'!Q58 -> 0
O29: OOS Crew | P29: ='Agency Hours'!R43 -> 0
B30: Celebrity Name(s):
I31: Retainer Billings | J31: ='Agency Hours'!J49 -> 0 | O31: Retainer Billings | P31: ='Agency Hours'!S49 -> 0 | U31: ='Agency Hours'!O49 -> 0 | V31: =J31-(P31+U31) -> 0
B32: Agency Job Description:
B33: Agency Job Name: | H33: Prod Agency Hours | K33: ='Agency Hours'!Q68 -> 0 | N33: Production Agency Hours | Q33: ='Agency Hours'!Q64+'Agency Hours'!Q65 -> 0 | T33: ='Agency Hours'!O55 -> 0 | V33: =K33-(Q33+T33) -> 0
B34: Agency Job Number: | O34: IL Crew | P34: ='Agency Hours'!S55 -> 0
O35: OOS Crew | P35: ='Agency Hours'!R55 -> 0
C36: AICP Bid | D36: 300358
C37: Agency Estimate | H37: Agency Exp. Report | K37: =#REF! -> #REF! | N37: Agency Exp. Report | Q37: =#REF! -> #REF! | T37: =#REF! -> #REF! | V37: =K37-(Q37+T37) -> #REF!
C38: Final Script/Storyboard Date | H38: Client - Crew | K38: =#REF! -> #REF! | N38: Client | Q38: =#REF!+#REF! -> #REF! | T38: =#REF! -> #REF! | V38: =K38-(Q38+T38) -> #REF!
C39: Application & Boards | H39: Client - Sub-Vendors | K39: =#REF! -> #REF! | N39: Client - Sub-Vendors | Q39: =#REF! -> #REF! | T39: =#REF! -> #REF! | V39: =K39-(Q39+T39) -> #REF!
C40: APC | H40: Consultant | K40: =#REF! -> #REF! | N40: Consultant | Q40: =#REF! -> #REF! | T40: =SUM(T12,T15:T18,T20,T26:T27,T34:T37) -> #REF! | V40: =K40-(Q40+T40) -> #REF!
C41: Pre-Production Book | I41: Consultant Retainer Fee | J41: =#REF! -> #REF! | O41: Consultant Retainer Fee | P41: =#REF! -> #REF! | U41: =#REF! -> #REF! | V41: =J41-(P41+U41) -> #REF!
C42: Call Sheet | H42: CPA Fee | K42: 0 | N42: CPA Fee | Q42: 0 | V42: =K42-(Q42+T42) -> 0
C43: Diversity Tracking Sheet (Including Agency) | H43: Total Submitted costs: | K43: =SUM(K12:K42) -> #REF! | N43: Total Qualified costs: | Q43: =SUM(Q12:Q42)+P24+P25 -> #REF! | T43: =SUM(T12:T42) -> #REF! | V43: =SUM(V12:V30,V32:V42) -> #REF!
C44: Vendor Diversity Summary
C45: Shoot Location/s: | O45: All Qualified OOS | P45: =P14+P23+P29+P35 -> 0
B47: Spots:
C49: PO Log | D49: 0 | J49: QUALIFIED AMOUNT FOR CPA
C50: Job Cost Detail | D50: =Billings!H49 -> 0
C51: Total ProdCo Billings | D51: =Billings!F27 -> 0 | J51: Agency is the applicant - Local ProdCo | O51: CPA Workbook | Q51: Audit Adjustment | R51: Tax Credit
C52: Total Client Billings | D52: =SUM(Billings!F28:F29) -> 0 | L52: Amount
C53: Total Amount Spent on Project | D53: =SUM(Billings!F29:F30) -> 0 | J53: ProdCo Billings | L53: =D51 -> 0 | P53: =O53-L53 -> 0 | R53: =O53+Q53 -> 0
J54: IL Agency Expenses
K55: Crew Paid by Agency | L55: =Q25+P29 -> 0 | P55: =O55-L55 -> 0 | R55: =O55+Q55 -> 0
D56: Difference | K56: Non-Resident Labor | L56: =P30+P23 -> 0 | P56: =O56-L56 -> 0 | R56: =O56+Q56 -> 0
E57: % | K57: Talent | L57: =P21 -> 0 | P57: =O57-L57 -> 0 | R57: =O57+Q57 -> 0
C58: AICP vs ProdCo Submitted | D58: =SUM(K12:K19)-D36 -> #REF! | K58: Extras | L58: =P22 -> 0 | P58: =O58-L58 -> 0 | R58: =O58+Q58 -> 0
C59: PO Log vs ProdCo Amount Entered | D59: =SUM(K12:K18)-D49 -> #REF! | E59: =SUM(K12:K18)/D36 -> #REF! | K59: Agency Sub-Vendors | L59: =Q24 -> 0 | P59: =O59-L59 -> 0 | R59: =O59+Q59 -> 0
C60: ProdCo Submitted vs ProdCo Billings | D60: =SUM(K12:K18)-D51 -> #REF! | E60: =SUM(K12:K19)/D49 -> #REF! | K60: Agency Exps | L60: =Q31 -> 0 | P60: =O60-L60 -> 0 | R60: =O60+Q60 -> 0
C61: ProdCo Qualified vs ProdCo Billings | D61: =SUM(Q12:Q18)-D51 -> #REF! | E61: {=SUM(K12:K18/D51)} -> #DIV/0! | J61: Consultant Hours | L61: =Q33 -> 0 | P61: =O61-L61 -> 0 | R61: =O61+Q61 -> 0
E62: =SUM(Q11:Q19)/D51 -> #REF! | J62: CPA Fee | L62: =Q42 -> 0 | P62: =O62-L62 -> 0 | R62: =O62+Q62 -> 0
C63: JCD vs Agency Amount Entered | D63: =SUM(Q20:Q24)-D50 -> 0 | J63: QUALIFIED SPEND | L63: =SUM(L53:L62) -> 0 | M63: =L63/J80 -> #DIV/0! | N63: of rebate estimate | P63: =O63-L63 -> 0
C64: Agency Estimate vs Client Billings | D64: =D52-D37 -> 0 | E64: =SUM(K23:K30)/D50 -> #DIV/0! | O64: =O63-SUM(O53:O62) -> 0 | Q64: =Q63-SUM(Q53:Q62) -> 0 | R64: =R63-SUM(R53:R62) -> 0
E65: =D52/D37 -> #DIV/0! | J65: Tax Incentive Amount | L65: =L63*0.3 -> 0 | P65: =O65-L65 -> 0 | R65: =O65+Q65 -> 0
C66: UPLIFTS | J66: Add'l 15% | L66: =(0)*0.15 -> 0 | P66: =O66-L66 -> 0 | R66: =O66+Q66 -> 0
C67: Green Sustainability Uplift | D67: FALSE | J67: Total Tax Credit Amount | L67: =SUM(L65:L66) -> 0 | P67: =O67-L67 -> 0 | R67: =O67+Q67 -> 0
C68: Rural Area Uplift | D68: FALSE
J72: REBATE ESTIMATE | K72: CPA QUALIFIED
I74: ProdCo | J74: 0 | K74: =SUM(L53) -> 0 | L74: =K74-J74 -> 0 | M74: {=_xlfn.IFS(L74>0,"Over Budget",L74<0,"Under Budget",L74=0,"-")} -> -
I75: Agency Exps | J75: 0 | K75: =SUM(L55:L60) -> 0 | L75: =K75-J75 -> 0 | M75: {=_xlfn.IFS(L75>0,"Over Budget",L75<0,"Under Budget",L75=0,"-")} -> -
I76: Agency Hours | J76: 0 | K76: 0 | L76: =K76-J76 -> 0 | M76: {=_xlfn.IFS(L76>0,"Over Budget",L76<0,"Under Budget",L76=0,"-")} -> -
I77: Project Fee | J77: 0 | K77: 0 | L77: =K77-J77 -> 0 | M77: {=_xlfn.IFS(L77>0,"Over Budget",L77<0,"Under Budget",L77=0,"-")} -> -
I78: Consultant | J78: 0 | K78: =L61 -> 0 | L78: =K78-J78 -> 0 | M78: {=_xlfn.IFS(L78>0,"Over Budget",L78<0,"Under Budget",L78=0,"-")} -> -
I79: CPA | J79: 3000 | K79: =L62 -> 0 | L79: =K79-J79 -> -3000 | M79: {=_xlfn.IFS(L79>0,"Over Budget",L79<0,"Under Budget",L79=0,"-")} -> Under Budget
B80: ProdCo Materials Entered by: | I80: TOTAL QUALIFIED SPEND | K80: =SUM(K74:K79) -> 0 | L80: =K80-J80 -> 0 | M80: {=_xlfn.IFS(L80>0,"Over Budget",L80<0,"Under Budget",L80=0,"-")} -> -
B81: Reviewed by: | J81: =J80-SUM(J74:J79) -> -3000 | K81: =O63-K80 -> 0 | Q81: IL Transfer Fee
I83: Tax Credit (30%) | Q83: Qualified Spend No OOS | R83: =L63-P45 -> 0
B84: Agency Materials Entered by: | I84: Gross Rebate | J84: =J80*0.3 -> 0 | K84: =L67 -> 0 | Q84: State Rebate % | R84: 0.3
B85: Reviewed by: | I85: Transfer Costs (11.00%) | J85: =-(J84*0.11) -> 0 | K85: =-K84*0.11 -> 0 | N85: {=_xlfn.IFS(M85>0,"Over Budget",M85<0,"Under Budget",M85=0,"-")} -> - | R85: =R83*R84 -> 0
I86: Net Proceeds | J86: =SUM(J84:J85) -> 0 | K86: =SUM(K84:K85) -> 0 | Q86: Bonus Incentive | R86: =L66 -> 0
I87: Reimbursable Expenses | R87: =R85+R86 -> 0
B88: CPA Prepped by: | I88: Admin Fee | J88: 0 | K88: =J88 -> 0 | R88: 0.0025 | U88: ((((Qualified Spend - Non Resident Labor) * 0.3) + Bonus Incentive Amount ) * 0.0025) + ((Non Resident Labor * 0.3) * 0.025)
B89: CPA Review by: | I89: IL Transfer Fee | J89: 0 | K89: =-R97 -> 0 | R89: =R88*R87 -> 0
I90: CPA Fee | J90: 0 | K90: =J90 -> 0
I91: Net Rebate | J91: =SUM(J86:J90) -> 0 | K91: =SUM(K86:K90) -> 0 | Q91: Qualified Spend OOS | R91: =P45 -> 0
I92: TPC Fee (22.50%) | J92: =-(J91*0.225) -> 0 | K92: =-K91*0.225 -> 0 | Q92: State Rebate % | R92: 0.3
I93: Net to Brand | J93: =SUM(J91:J92) -> 0 | K93: =SUM(K91:K92) -> 0 | L93: =K93-J93 -> 0 | M93: {=_xlfn.IFS(L93>0,"Over Budget",L93<0,"Under Budget",L93=0,"-")} -> - | R93: =R91*R92 -> 0
I94: Reported range | R94: 0.025
R95: =R93*R94 -> 0 | S95: =(R91+R83)-L63 -> 0
N97: {=_xlfn.IFS(M97>0,"Over Budget",M97<0,"Under Budget",M97=0,"-")} -> - | Q97: IL Transfer Fee Total | R97: =R89+R95 -> 0

Sheet Comm Summary (L-L, L-O)
A1: TPC Commercial Incentives Service
A2: Commercial Project Summary
B4: Project Description | C4: =CONCATENATE(C17, " ",C18, " ",C5) -> "2022 Q3 Eggo Liege TV" | F4: State: | H4: Illinois | X4: ECS Company code: | Y4: Elite CIS
B5: Project Title: | C5: "2022 Q3 Eggo Liege TV"
B7: Award Date:
B8: Pre Pro Date: | H8: LIVE ACTION | X8: Rebate Estimate Analysis | AB8: STILL
B9: Shoot Date:
B10: Production Wrap Date | H10: SUBMITTED EXPENSES | N10: QUALIFIED EXPENSES | T10: Pending | V10: DNQ | X10: Amount | Y10: Difference
B11: Post Production Date: | H11: PRODUCTION COMPANY | AB11: To have additional columns here if there's another shoot/ production (to not create another workbook)
B12: ProdCo Job Type(s): | H12: Crew Payroll | K12: ='Crew Payroll'!AE45 -> 0 | N12: Total Crew Payroll | Q12: =P13+P14 -> 0 | T12: ='Crew Payroll'!U53 -> 0 | V12: =K12-(Q12+T12) -> 0 | AB12: Create Crew Payroll, Production, and other applicable tabs and create formulas to get total Submitted and Qualified costs.
B13: ProdCo Job Notes: | O13: IL Crew Payroll | P13: ='Crew Payroll'!S53 -> 0
B14: OOS Shoot Job Type & Location | O14: OOS Crew | P14: ='Crew Payroll'!S54 -> 0
B15: OOS Shoot Date(s): | H15: ProdCo Sub-Vendors | K15: =#REF! -> #REF! | N15: ProdCo Sub-Vendors | Q15: =#REF! -> #REF! | T15: =#REF! -> #REF! | V15: =K15-(Q15+T15) -> #REF!
H16: Prod - Petty Cash | K16: =#REF! -> #REF! | N16: Prod - Petty Cash | Q16: =#REF! -> #REF! | T16: =#REF! -> #REF! | V16: =K16-(Q16+T16) -> #REF!
B17: Client: | H17: Prod - Credit Card | K17: =#REF! -> #REF! | N17: Prod - Credit Card | Q17: =#REF! -> #REF! | T17: =#REF! -> #REF! | V17: =K17-(Q17+T17) -> #REF!
B18: Client Brand & Product: | H18: Prod - Exp Reports | K18: =#REF! -> #REF! | N18: Prod - Exp Reports | Q18: =#REF! -> #REF! | T18: =#REF! -> #REF! | V18: =K18-(Q18+T18) -> #REF!
B19: Agency: | D19: Local Agency | Z19: AICP less identified OOS
B20: Production Company: | D20: Local or OOS (State) - Motion or Still | H20: Total Talent | K20: =SUM('Talent & Extras'!T63) -> 0 | N20: Total Talent | Q20: ='Talent & Extras'!N81 -> 0 | T20: ='Talent & Extras'!M69 -> 0 | V20: =K20-(Q20+T20) -> 0
B21: Subcontracted ProdCo: | D21: Local or OOS (State) - Motion or Still | I21: Talent Payroll | J21: ='Talent & Extras'!Q69 -> 0 | O21: Talent Payroll | P21: ='Talent & Extras'!D69 -> 0
B22: OOS Shoot Prod Company: | I22: Extras Payroll | J22: ='Talent & Extras'!C71 -> 0 | O22: Extras Payroll | P22: ='Talent & Extras'!D70 -> 0
B23: Crew Payroll Company: | O23: Two (2) OOS Talent | P23: ='Talent & Extras'!R69 -> 0
B24: Celebrity Payroll Company: | O24: Handling Fees | P24: ='Agency Sub-Vendors'!M69 -> 0
B25: Talent Payroll Company: | O25: Agency Fees | P25: ='Agency Sub-Vendors'!M68 -> 0
B26: Production Insurance: | H26: Agency Sub-Vendors | K26: ='Agency Sub-Vendors'!M63 -> 0 | N26: Total Sub-Vendors | Q26: ='Agency Sub-Vendors'!M60 -> 0 | T26: ='Agency Sub-Vendors'!M61 -> 0 | V26: =K26-(Q26+T26) -> 0
B27: Other Payor 2: | H27: Agency Hours | K27: ='Agency Hours'!T43 -> 0 | N27: Normal Agency Hours | Q27: ='Agency Hours'!Q71 -> 0 | T27: ='Agency Hours'!O43 -> 0 | V27: =K27-(Q27+T27) -> 0
B28: Other Payor 3: | O28: IL Crew | P28: ='Agency Hours'!Q58 -> 0
O29: OOS Crew | P29: ='Agency Hours'!R43 -> 0
B30: Celebrity Name(s):
I31: Retainer Billings | J31: ='Agency Hours'!J49 -> 0 | O31: Retainer Billings | P31: ='Agency Hours'!S49 -> 0 | U31: ='Agency Hours'!O49 -> 0 | V31: =J31-(P31+U31) -> 0
B32: Agency Job Description:
B33: Agency Job Name: | H33: Prod Agency Hours | K33: ='Agency Hours'!Q68 -> 0 | N33: Production Agency Hours | Q33: ='Agency Hours'!Q64+'Agency Hours'!Q65 -> 0 | T33: ='Agency Hours'!O55 -> 0 | V33: =K33-(Q33+T33) -> 0
B34: Agency Job Number: | O34: IL Crew | P34: ='Agency Hours'!S55 -> 0
O35: OOS Crew | P35: ='Agency Hours'!R55 -> 0
C36: AICP Bid
C37: Agency Estimate | H37: Agency Exp. Report | K37: =#REF! -> #REF! | N37: Agency Exp. Report | Q37: =#REF! -> #REF! | T37: =#REF! -> #REF! | V37: =K37-(Q37+T37) -> #REF!
C38: Final Script/Storyboard Date | H38: Client - Crew | K38: =#REF! -> #REF! | N38: Client | Q38: =#REF!+#REF! -> #REF! | T38: =#REF! -> #REF! | V38: =K38-(Q38+T38) -> #REF!
C39: Application & Boards | H39: Client - Sub-Vendors | K39: =#REF! -> #REF! | N39: Client - Sub-Vendors | Q39: =#REF! -> #REF! | T39: =#REF! -> #REF! | V39: =K39-(Q39+T39) -> #REF!
C40: APC | H40: Consultant | K40: =#REF! -> #REF! | N40: Consultant | Q40: =#REF! -> #REF! | T40: =SUM(T12,T15:T18,T20,T26:T27,T34:T37) -> #REF! | V40: =K40-(Q40+T40) -> #REF!
C41: Pre-Production Book | I41: Consultant Retainer Fee | J41: =#REF! -> #REF! | O41: Consultant Retainer Fee | P41: =#REF! -> #REF! | U41: =#REF! -> #REF! | V41: =J41-(P41+U41) -> #REF!
C42: Call Sheet | H42: CPA Fee | K42: 0 | N42: CPA Fee | Q42: 0 | V42: =K42-(Q42+T42) -> 0
C43: Diversity Tracking Sheet (Including Agency) | H43: Total Submitted costs: | K43: =SUM(K12:K42) -> #REF! | N43: Total Qualified costs: | Q43: =SUM(Q12:Q42)+P24+P25 -> #REF! | T43: =SUM(T12:T42) -> #REF! | V43: =SUM(V12:V30,V32:V42) -> #REF!
C44: Vendor Diversity Summary
C45: Shoot Location/s: | O45: All Qualified OOS | P45: =P14+P23+P29+P35 -> 0
B47: Spots:
C49: PO Log | D49: 0
C50: Job Cost Detail | D50: =Billings!H49 -> 0 | J50: QUALIFIED AMOUNT FOR CPA
C51: Total ProdCo Billings | D51: =Billings!F27 -> 0
C52: Total Client Billings | D52: =SUM(Billings!F28:F29) -> 0 | J52: Local-Local/ Local-OOS | O52: CPA Workbook | Q52: Audit Adjustment | R52: Tax Credit
C53: Total Amount Spent on Project | D53: =SUM(Billings!F29:F30) -> 0 | L53: Amount
J54: Client Billings | L54: =D52 -> 0 | P54: =O54-L54 -> 0 | R54: =O54+Q54 -> 0
J55: Less: OOS Exp on Client Billings | P55: =O55-L55 -> 0 | R55: =O55+Q55 -> 0
D56: Difference | J56: Agency Hours | L56: =Q27 -> 0 | P56: =O56-L56 -> 0 | R56: =O56+Q56 -> 0
E57: % | J57: Consultant Hours | L57: =#REF! -> #REF! | P57: =O57-L57 -> #REF! | R57: =O57+Q57 -> 0
C58: AICP vs ProdCo Submitted | D58: =SUM(K12:K19)-D36 -> #REF! | J58: CPA Fee | L58: =Q42 -> 0 | P58: =O58-L58 -> 0 | R58: =O58+Q58 -> 0
C59: PO Log vs ProdCo Amount Entered | D59: =SUM(K12:K18)-D49 -> #REF! | E59: =SUM(K12:K18)/D36 -> #REF! | J59: QUALIFIED SPEND | L59: =SUM(L54:L58) -> #REF! | M59: =L59/J74 -> #REF! | N59: of rebate estimate | P59: =O59-L59 -> #REF!
C60: ProdCo Submitted vs ProdCo Billings | D60: =SUM(K12:K18)-D51 -> #REF! | E60: =SUM(K12:K19)/D49 -> #REF! | O60: =O59-SUM(O54:O58) -> 0 | Q60: =Q59-SUM(Q54:Q58) -> 0 | R60: =R59-SUM(R54:R58) -> 0
C61: ProdCo Qualified vs ProdCo Billings | D61: =SUM(Q12:Q18)-D51 -> #REF! | E61: {=SUM(K12:K18/D51)} -> #DIV/0! | J61: Tax Incentive Amount | L61: =L59*0.3 -> #REF! | P61: =O61-L61 -> #REF! | R61: =O61+Q61 -> 0
E62: =SUM(Q11:Q19)/D51 -> #REF! | J62: Add'l 15% | L62: =(0)*0.15 -> 0 | P62: =O62-L62 -> 0 | R62: =O62+Q62 -> 0
C63: JCD vs Agency Amount Entered | D63: =SUM(K20:K26)-D50 -> 0 | J63: Total Tax Credit Amount | L63: =SUM(L61:L62) -> #REF! | P63: =O63-L63 -> #REF! | R63: =O63+Q63 -> 0
C64: Agency Estimate vs Client Billings | D64: =D52-D37 -> 0 | E64: =SUM(K26:K40)/D50 -> #REF!
C65: Client Billings vs Agency Amount Entered | D65: =SUM(K20:K33)/D52 -> #DIV/0! | E65: =D52/D37 -> #DIV/0!
J66: REBATE ESTIMATE | K66: CPA QUALIFIED
C67: UPLIFTS
C68: Green Sustainability Uplift | D68: FALSE | I68: ProdCo | J68: 0 | K68: =D51 -> 0 | L68: =K68-J68 -> 0 | M68: {=_xlfn.IFS(L68>0,"Over Budget",L68<0,"Under Budget",L68=0,"-")} -> -
C69: Rural Area Uplift | D69: FALSE | I69: Agency Exps | J69: 0 | K69: =SUM(L54:L55)-D51 -> 0 | L69: =K69-J69 -> 0 | M69: {=_xlfn.IFS(L69>0,"Over Budget",L69<0,"Under Budget",L69=0,"-")} -> -
I70: Agency Hours | J70: 0 | K70: =L56 -> 0 | L70: =K70-J70 -> 0 | M70: {=_xlfn.IFS(L70>0,"Over Budget",L70<0,"Under Budget",L70=0,"-")} -> -
B71: ProdCo Materials Entered by: | I71: Project Fee | J71: 0 | K71: 0 | L71: =K71-J71 -> 0 | M71: {=_xlfn.IFS(L71>0,"Over Budget",L71<0,"Under Budget",L71=0,"-")} -> -
B72: Reviewed by: | I72: Consultant | J72: 0 | K72: =L55 -> 0 | L72: =K72-J72 -> 0 | M72: {=_xlfn.IFS(L72>0,"Over Budget",L72<0,"Under Budget",L72=0,"-")} -> -
I73: CPA | J73: 3000 | K73: =L58 -> 0 | L73: =K73-J73 -> -3000 | M73: {=_xlfn.IFS(L73>0,"Over Budget",L73<0,"Under Budget",L73=0,"-")} -> Under Budget
I74: TOTAL QUALIFIED SPEND | K74: =SUM(K68:K73) -> 0 | L74: =K74-J74 -> 0 | M74: {=_xlfn.IFS(L74>0,"Over Budget",L74<0,"Under Budget",L74=0,"-")} -> -
B75: Agency Materials Entered by: | J75: =J74-SUM(J68:J73) -> -3000 | K75: =O59-K74 -> 0 | Q75: IL Transfer Fee
B76: Reviewed by:
I77: Tax Credit (30%) | Q77: Qualified Spend No OOS | R77: =L59-P45 -> #REF!
I78: Gross Rebate | J78: =J74*0.3 -> 0 | K78: =L64 -> 0 | Q78: State Rebate % | R78: 0.3
B79: CPA Prepped by: | I79: Est. Transfer Costs (11.00%) | J79: =-(J78*0.11) -> 0 | K79: =-K78*0.11 -> 0 | R79: =R77*R78 -> #REF!
B80: CPA Review by: | I80: Net Proceeds | J80: =SUM(J78:J79) -> 0 | K80: =SUM(K78:K79) -> 0 | Q80: Bonus Incentive | R80: =L60 -> 0
I81: Reimbursable Expenses | R81: =R79+R80 -> #REF!
I82: Admin Fee | J82: 0 | K82: =J82 -> 0 | R82: 0.0025 | U82: ((((Qualified Spend - Non Resident Labor) * 0.3) + Bonus Incentive Amount ) * 0.0025) + ((Non Resident Labor * 0.3) * 0.025)
I83: IL Transfer Fee | J83: 0 | K83: =-R91 -> #REF! | R83: =R82*R81 -> #REF!
I84: CPA Fee | J84: 0 | K84: =J84 -> 0
I85: Net Rebate | J85: =SUM(J80:J84) -> 0 | K85: =SUM(K80:K84) -> #REF! | Q85: Qualified Spend OOS | R85: =P45 -> 0
I86: TPC Fee (22.50%) | J86: =-(J85*0.225) -> 0 | K86: =-K85*0.225 -> #REF! | Q86: State Rebate % | R86: 0.3
I87: Net to Brand | J87: =SUM(J85:J86) -> 0 | K87: =SUM(K85:K86) -> #REF! | L87: =K87-J87 -> #REF! | M87: {=_xlfn.IFS(L87>0,"Over Budget",L87<0,"Under Budget",L87=0,"-")} -> #REF! | R87: =R85*R86 -> 0
I88: Reported range | R88: 0.025
R89: =R87*R88 -> 0 | S89: =(R85+R77)-L57 -> #REF!
Q91: IL Transfer Fee Total | R91: =R83+R89 -> #REF!

Sheet Billings
A1: TPC Commercial Incentives Service
A2: Commercial Project Billings Summary
B7: ITEM | C7: Qualify | D7: Vendor Name | E7: Vendor Type | F7: Job Type | G7: State | H7: Description | I7: Details | J7: Invoice Date | K7: Invoice # | L7: Eligible Total | M7: Project Fee | N7: Address | O7: City | P7: State | Q7: Zip | R7: Received Invoice | S7: POP | T7: Payment Date | U7: Payment Method | V7: W-9 | W7: Job Number | X7: Notes | Z7: VENDOR NAME | AA7: DESCRIPTION | AB7: ADDRESS | AC7: CITY | AD7: ZIP | AE7: INVOICE DATE | AF7: INVOICE NUMBER | AG7: AMOUNT | AI7: PAYMENT DATE | AJ7: PAYMENT METHOD
B8: 1 | L8: 0 | Z8: =D8 -> 0 | AA8: =H8 -> 0 | AB8: =N8 -> 0 | AC8: =O7 -> City | AD8: =Q8 -> 0 | AE8: =J8 -> 0 | AF8: =K8 -> 0 | AG8: =L8 -> 0 | AI8: =T8 -> 0 | AJ8: =U8 -> 0
B9: 2 | L9: 0 | Z9: =D9 -> 0 | AA9: =H9 -> 0 | AB9: =N9 -> 0 | AC9: =O8 -> 0 | AD9: =Q9 -> 0 | AE9: =J9 -> 0 | AF9: =K9 -> 0 | AG9: =L9 -> 0 | AI9: =T9 -> 0 | AJ9: =U9 -> 0
B10: 3 | L10: 0 | Z10: =D10 -> 0 | AA10: =H10 -> 0 | AB10: =N10 -> 0 | AC10: =O9 -> 0 | AD10: =Q10 -> 0 | AE10: =J10 -> 0 | AF10: =K10 -> 0 | AG10: =L10 -> 0 | AI10: =T10 -> 0 | AJ10: =U10 -> 0
B11: 4 | L11: 0 | Z11: =D11 -> 0 | AA11: =H11 -> 0 | AB11: =N11 -> 0 | AC11: =O10 -> 0 | AD11: =Q11 -> 0 | AE11: =J11 -> 0 | AF11: =K11 -> 0 | AG11: =L11 -> 0 | AI11: =T11 -> 0 | AJ11: =U11 -> 0
B12: 5 | L12: 0 | Z12: =D12 -> 0 | AA12: =H12 -> 0 | AB12: =N12 -> 0 | AC12: =O11 -> 0 | AD12: =Q12 -> 0 | AE12: =J12 -> 0 | AF12: =K12 -> 0 | AG12: =L12 -> 0 | AI12: =T12 -> 0 | AJ12: =U12 -> 0
B13: 6 | L13: 0 | Z13: =D13 -> 0 | AA13: =H13 -> 0 | AB13: =N13 -> 0 | AC13: =O12 -> 0 | AD13: =Q13 -> 0 | AE13: =J13 -> 0 | AF13: =K13 -> 0 | AG13: =L13 -> 0 | AI13: =T13 -> 0 | AJ13: =U13 -> 0
B14: 7 | L14: 0 | Z14: =D14 -> 0 | AA14: =H14 -> 0 | AB14: =N14 -> 0 | AC14: =O13 -> 0 | AD14: =Q14 -> 0 | AE14: =J14 -> 0 | AF14: =K14 -> 0 | AG14: =L14 -> 0 | AI14: =T14 -> 0 | AJ14: =U14 -> 0
B15: 8 | L15: 0 | Z15: =D15 -> 0 | AA15: =H15 -> 0 | AB15: =N15 -> 0 | AC15: =O14 -> 0 | AD15: =Q15 -> 0 | AE15: =J15 -> 0 | AF15: =K15 -> 0 | AG15: =L15 -> 0 | AI15: =T15 -> 0 | AJ15: =U15 -> 0
B16: 9 | L16: 0 | Z16: =D16 -> 0 | AA16: =H16 -> 0 | AB16: =N16 -> 0 | AC16: =O11 -> 0 | AD16: =Q16 -> 0 | AE16: =J16 -> 0 | AF16: =K16 -> 0 | AG16: =L16 -> 0 | AI16: =T16 -> 0 | AJ16: =U16 -> 0
B17: 10 | L17: 0 | Z17: =D17 -> 0 | AA17: =H17 -> 0 | AB17: =N17 -> 0 | AC17: =O16 -> 0 | AD17: =Q17 -> 0 | AE17: =J17 -> 0 | AF17: =K17 -> 0 | AG17: =L17 -> 0 | AI17: =T17 -> 0 | AJ17: =U17 -> 0
B18: 11 | L18: 0 | Z18: =D18 -> 0 | AA18: =H18 -> 0 | AB18: =N18 -> 0 | AC18: =O17 -> 0 | AD18: =Q18 -> 0 | AE18: =J18 -> 0 | AF18: =K18 -> 0 | AG18: =L18 -> 0 | AI18: =T18 -> 0 | AJ18: =U18 -> 0
B19: 12 | L19: 0 | Z19: =D19 -> 0 | AA19: =H19 -> 0 | AB19: =N19 -> 0 | AC19: =O18 -> 0 | AD19: =Q19 -> 0 | AE19: =J19 -> 0 | AF19: =K19 -> 0 | AG19: =L19 -> 0 | AI19: =T19 -> 0 | AJ19: =U19 -> 0
B20: 9 | L20: 0 | Z20: =D20 -> 0 | AA20: =H20 -> 0 | AB20: =N20 -> 0 | AC20: =O15 -> 0 | AD20: =Q20 -> 0 | AE20: =J20 -> 0 | AF20: =K20 -> 0 | AG20: =L20 -> 0 | AI20: =T20 -> 0 | AJ20: =U20 -> 0
B21: 10 | L21: 0 | Z21: =D21 -> 0 | AA21: =H21 -> 0 | AB21: =N21 -> 0 | AC21: =O20 -> 0 | AD21: =Q21 -> 0 | AE21: =J21 -> 0 | AF21: =K21 -> 0 | AG21: =L21 -> 0 | AI21: =T21 -> 0 | AJ21: =U21 -> 0
B22: 11 | L22: 0 | Z22: =D22 -> 0 | AA22: =H22 -> 0 | AB22: =N22 -> 0 | AC22: =O21 -> 0 | AD22: =Q22 -> 0 | AE22: =J22 -> 0 | AF22: =K22 -> 0 | AG22: =L22 -> 0 | AI22: =T22 -> 0 | AJ22: =U22 -> 0
B23: 12 | L23: 0 | Z23: =D23 -> 0 | AA23: =H23 -> 0 | AB23: =N23 -> 0 | AC23: =O22 -> 0 | AD23: =Q23 -> 0 | AE23: =J23 -> 0 | AF23: =K23 -> 0 | AG23: =L23 -> 0 | AI23: =T23 -> 0 | AJ23: =U23 -> 0
L25: =SUBTOTAL(9,$L$8:$L$23) -> 0 | M25: =SUBTOTAL(9,$M$8:$M$23) -> 0
D26: Vendor Name | E26: Job Type | F26: Total Billings | G26: Job Name | H26: Vendor Type
F27: =SUMIFS($L$8:$L$23,$D$8:$D$23,$D27,$F$8:$F$23,$E27) -> 0 | G27: =_xlfn.XLOOKUP($D27,$D$8:$D$23,$W$8:$W$23) -> 0 | H27: =_xlfn.XLOOKUP($D27,$D$8:$D$23,$E$8:$E$23) -> 0
F28: =SUMIFS($L$8:$L$23,$D$8:$D$23,$D28,$F$8:$F$23,$E28) -> 0 | G28: =_xlfn.XLOOKUP($D28,$D$8:$D$23,$W$8:$W$23) -> 0 | H28: =_xlfn.XLOOKUP($D28,$D$8:$D$23,$E$8:$E$23) -> 0
F29: =SUMIFS($L$8:$L$23,$D$8:$D$23,$D29,$F$8:$F$23,$E29) -> 0 | G29: =_xlfn.XLOOKUP($D29,$D$8:$D$23,$W$8:$W$23) -> 0 | H29: =_xlfn.XLOOKUP($D29,$D$8:$D$23,$E$8:$E$23) -> 0
F30: =SUMIFS($L$8:$L$23,$D$8:$D$23,$D30,$F$8:$F$23,$E30) -> 0 | G30: =_xlfn.XLOOKUP($D30,$D$8:$D$23,$W$8:$W$23) -> 0 | H30: =_xlfn.XLOOKUP($D30,$D$8:$D$23,$E$8:$E$23) -> 0
F31: =SUMIFS($L$8:$L$23,$D$8:$D$23,$D31,$F$8:$F$23,$E31) -> 0 | G31: =_xlfn.XLOOKUP($D31,$D$8:$D$23,$W$8:$W$23) -> 0 | H31: =_xlfn.XLOOKUP($D31,$D$8:$D$23,$E$8:$E$23) -> 0
F32: =SUMIFS($L$8:$L$23,$D$8:$D$23,$D32,$F$8:$F$23,$E32) -> 0 | G32: =_xlfn.XLOOKUP($D32,$D$8:$D$23,$W$8:$W$23) -> 0 | H32: =_xlfn.XLOOKUP($D32,$D$8:$D$23,$E$8:$E$23) -> 0
F33: =SUMIFS($L$8:$L$23,$D$8:$D$23,$D33,$F$8:$F$23,$E33) -> 0 | G33: =_xlfn.XLOOKUP($D33,$D$8:$D$23,$W$8:$W$23) -> 0 | H33: =_xlfn.XLOOKUP($D33,$D$8:$D$23,$E$8:$E$23) -> 0
F34: =SUM(F27:F33) -> 0
E39: Eligible Total | F39: Qualified Total | G39: Pending Total | H39: DNQ
D40: Agency | E40: =SUMIFS($L$8:$L$23,$E$8:$E$23,$D40) -> 0 | F40: =SUMIFS($L$8:$L$23,$E$8:$E$23,$D40,$C$8:$C$23,"YES") -> 0 | G40: =SUMIFS($L$8:$L$23,$C$8:$C$23,"PENDING",$E$8:$E$23,$D40) -> 0 | H40: =E40-(F40+G40) -> 0
D41: ProdCo | E41: =SUMIFS($L$8:$L$23,$E$8:$E$23,$D41) -> 0 | F41: =SUMIFS($L$8:$L$23,$E$8:$E$23,$D41,$C$8:$C$23,"YES") -> 0 | G41: =SUMIFS($L$8:$L$23,$C$8:$C$23,"PENDING",$E$8:$E$23,$D41) -> 0 | H41: =E41-(F41+G41) -> 0
D42: Sub-ProdCo | E42: =SUMIFS($L$8:$L$23,$E$8:$E$23,$D42) -> 0 | F42: =SUMIFS($L$8:$L$23,$E$8:$E$23,$D42,$C$8:$C$23,"YES") -> 0 | G42: =SUMIFS($L$8:$L$23,$C$8:$C$23,"PENDING",$E$8:$E$23,$D42) -> 0 | H42: =E42-(F42+G42) -> 0
E43: =SUM(E40:E42) -> 0 | F43: =SUM(F40:F42) -> 0 | G43: =SUM(G40:G42) -> 0 | H43: =E43-(F43+G43) -> 0
E47: Agency - Job Number
D49: Production | E49: Job Cost Detail | G49: Amount | H49: 0
G50: Amount Entered | H50: =SUM('Comm Summary (L-L, L-O)'!K20:K40) -> #REF!
G51: Difference | H51: =SUM(H49:H50) -> #REF!
E54: Agency - Job Number
D56: Talent Residuals | E56: Job Cost Detail | G56: Amount | H56: =G40 -> 0
G57: Amount Entered | H57: 0
G58: Difference | H58: =SUM(H56:H57) -> 0
G61: Total Amount | H61: =H49+H56 -> 0
G62: Total Amount Entered | H62: =SUM(H50,H57) -> #REF!
G63: Difference | H63: =SUM(H61:H62) -> #REF!

Sheet Residency - Callsheet
A1: TPC Commercial Incentives Service
A2: Residency - Callsheet
B7: ITEM_No | C7: XLookUP Name | D7: Document Name | E7: Document Type | F7: Issue_Date | G7: Expiration_Date | H7: Home_Address | I7: City | J7: Zip | K7: State | L7: Diversity | M7: Sex | N7: Notes | O7: Call Sheet Name | P7: Call Sheet Postion

Sheet AICP Bid

Sheet PO Log

Sheet Crew Payroll
B1: Production Tax Incentives PRODUCTION COMPANY CREW PAYROLL
AV2: 1st Shoot Day | AW2: 44831
C3: Project Title: | D3: Kellogg Company "2022 Q3 Eggo Liege TV" | AV3: Last Shoot Day | AW3: 44834
C4: Shoot Date: | D4: 44741 | AL4: FILL-OUT TABLES BELOW THE DATA AFTER ENCODING (TIE-OUTS) | AV4: Covid End Date | AW4: 44896
C5: Work State: | D5: Illinois | U5: 0.062 | V5: 0.0145
BB6: Automated: in case data is not reflected add it to this masterfile | BG6: Don't edit this part; with formulas | BO6: Vac/Hol with | BP6: ER BENEFITS / PH&W
E7: Exclude (Loan Out names) | F7: Use acronym, as will be used in CPA | Y7: DNQ | AC7: DNQ | AL7: INVOICE/ W9 | AP7: PROOF OF PAYMENT | AT7: RESIDENCY | BB7: DIVERSITY
B8: ITEM_No | C8: Qualify | D8: Work_State | E8: Crew_Name | F8: Crew_Position | G8: Position_Category | H8: No_of_Days_Worked | I8: Work Dates | J8: W_Dates_Worked_on_Invoice | K8: Gap_1 | L8: Invoice_Date | M8: PO_No | N8: Invoice_No | O8: Taxable_Wages | P8: Kit Rental | Q8: Mileage Fee | R8: Reimbursement | S8: Rental | T8: Corporate | U8: FICA | V8: Medi | W8: FUI | X8: SUI | Y8: W_C | Z8: PH_W | AA8: Vac_Hol | AB8: Other | AC8: Hand | AD8: Signatory Fee | AE8: Sub_Total | AF8: Non_Eligible | AG8: Total_Eligible | AH8: Automation_Total | AI8: Automation_Check | AJ8: Withholdings Amount | AK8: Withholdings Needed | AL8: Received_Invoice | AM8: Loan Out / 1099 | AN8: Loan_Out_Name | AO8: W9_and_Valid_Date | AP8: Pymt_Method | AQ8: Pymt_No | AR8: Proof_of_Payment | AS8: Payment_Entity | AT8: Document_Type | AU8: Issue_Date | AV8: Expiration_Date | AW8: Residency | AX8: Home_Address | AY8: City | AZ8: Zip | BA8: State | BB8: Diversity | BC8: Sex | BD8: Notes | BF8: Invoice No. | BG8: CPA_Crew_Name | BH8: CPA_Crew_Position | BI8: CPA_Position_Category | BJ8: CPA_Home_Address | BK8: CPA_City | BL8: CPA_Zip | BM8: CPA_No_of_Days_Worked | BN8: CPA_GROSS_WAGES | BO8: CPA_ER_TAXES | BP8: CPA_ER_BENEFITS_PH_W | BQ8: CPA_CPA_TOTAL | BR8: Ineligible1 | BS8: Ineligible2
G9: =_xlfn.XLOOKUP(F9,#REF!,#REF!) -> #REF! | AW9: =IF(C9="NO-OOS","N/A",IF(AT9="Driver's License",IF(AU9>$AW$3,"SOS",IF(AV9>=$AW$3,"Valid",IF(AND(AU9<$AW$3,$AW$4>$AW$3,AU9>AW2),"Covid","Expired"))),IF(AT9="I9",IF(AV9>=$AW$2,"Valid",IF(AND(AT9<$AW$3,$AW$4>$AW$3,AV9>AW2),"Covid","Expired")),IF(AT9="Work Permit",IF(AND(AU9<=$AW$2,(AV9+365)>=$AW$3),"Valid","Expired"),IF(AT9="Missing Residency","Missing",IF(AT9="","","Other")))))) | BN9: =IF($BP$6="GROSS WAGES",(Q9+R9+S9+T9+AA9)-AF9,(Q9+R9+S9+T9)-AF9) -> 0 | BO9: =U9+V9+W9+X9 -> 0 | BP9: =IF($BP$6="ER BENEFITS / PH&W",(Z9+AA9),(Z9)) -> 0 | BQ9: =SUM(BN9:BP9) -> 0 | BR9: =AE9-BQ9 -> 0 | BS9: =BQ9-AE9+Y9+AC9+AF9 -> 0
B10: 1 | G10: =_xlfn.XLOOKUP(F10,#REF!,#REF!) -> #REF! | O10: 0 | P10: 0 | Q10: 0 | R10: 0 | S10: 0 | T10: 0 | U10: 0 | V10: 0 | W10: 0 | X10: 0 | Y10: 0 | Z10: 0 | AA10: 0 | AB10: 0 | AC10: 0 | AD10: 0 | AE10: =SUM(O10:AC10) -> 0 | AF10: 0 | AG10: =AE10-AF10 -> 0 | AH10: 0 | AI10: =AE10-AG10 -> 0 | AW10: =IF(C10="NO-OOS","N/A",IF(AT10="Driver's License",IF(AU10>$AW$3,"SOS",IF(AV10>=$AW$3,"Valid",IF(AND(AU10<$AW$3,$AW$4>$AW$3,AU10>AW3),"Covid","Expired"))),IF(AT10="I9",IF(AV10>=$AW$2,"Valid",IF(AND(AT10<$AW$3,$AW$4>$AW$3,AV10>AW3),"Covid","Expired")),IF(AT10="Work Permit",IF(AND(AU10<=$AW$2,(AV10+365)>=$AW$3),"Valid","Expired"),IF(AT10="Missing Residency","Missing",IF(AT10="","","Other")))))) | BF10: =N10 -> 0 | BG10: =E10 -> 0 | BH10: =F10 -> 0 | BI10: =G10 -> #REF! | BJ10: =AX10 -> 0 | BK10: =AY10 -> 0 | BL10: =AZ10 -> 0 | BM10: =H10 -> 0 | BN10: =IF($BP$6="GROSS WAGES",(O10+P10+Q10+R10+S10+T10+AA10)-AF10,(O10+P10+Q10+R10+S10+T10)-AF10) -> 0 | BO10: =U10+V10+W10+X10 -> 0 | BP10: =IF($BP$6="ER BENEFITS / PH&W",(Z10+AA10),(Z10)) -> 0 | BQ10: =SUM(BN10:BP10) -> 0 | BR10: =AE10-BQ10 -> 0 | BS10: =BQ10-AE10+Y10+AC10+AF10 -> 0
B11: 2 | G11: =_xlfn.XLOOKUP(F11,#REF!,#REF!) -> #REF! | O11: 0 | P11: 0 | Q11: 0 | R11: 0 | S11: 0 | T11: 0 | U11: 0 | V11: 0 | W11: 0 | X11: 0 | Y11: 0 | Z11: 0 | AA11: 0 | AB11: 0 | AC11: 0 | AD11: 0 | AE11: =SUM(Q11:AC11) -> 0 | AF11: 0 | AG11: =AE11-AF11 -> 0 | AH11: 0 | AI11: =AE11-AG11 -> 0 | AW11: =IF(C11="NO-OOS","N/A",IF(AT11="Driver's License",IF(AU11>$AW$3,"SOS",IF(AV11>=$AW$3,"Valid",IF(AND(AU11<$AW$3,$AW$4>$AW$3,AU11>AW4),"Covid","Expired"))),IF(AT11="I9",IF(AV11>=$AW$2,"Valid",IF(AND(AT11<$AW$3,$AW$4>$AW$3,AV11>AW4),"Covid","Expired")),IF(AT11="Work Permit",IF(AND(AU11<=$AW$2,(AV11+365)>=$AW$3),"Valid","Expired"),IF(AT11="Missing Residency","Missing",IF(AT11="","","Other")))))) | BF11: =N11 -> 0 | BG11: =E11 -> 0 | BH11: =F11 -> 0 | BI11: =G11 -> #REF! | BJ11: =AX11 -> 0 | BK11: =AY11 -> 0 | BL11: =AZ11 -> 0 | BM11: =H11 -> 0 | BN11: =IF($BP$6="GROSS WAGES",(O11+P11+Q11+R11+S11+T11+AA11)-AF11,(O11+P11+Q11+R11+S11+T11)-AF11) -> 0 | BO11: =U11+V11+W11+X11 -> 0 | BP11: =IF($BP$6="ER BENEFITS / PH&W",(Z11+AA11),(Z11)) -> 0 | BQ11: =SUM(BN11:BP11) -> 0 | BR11: =AE11-BQ11 -> 0 | BS11: =BQ11-AE11+Y11+AC11+AF11 -> 0
B12: 3 | G12: =_xlfn.XLOOKUP(F12,#REF!,#REF!) -> #REF! | O12: 0 | P12: 0 | Q12: 0 | R12: 0 | S12: 0 | T12: 0 | U12: 0 | V12: 0 | W12: 0 | X12: 0 | Y12: 0 | Z12: 0 | AA12: 0 | AB12: 0 | AC12: 0 | AD12: 0 | AE12: =SUM(Q12:AC12) -> 0 | AF12: 0 | AG12: =AE12-AF12 -> 0 | AH12: 0 | AI12: =AE12-AG12 -> 0 | AW12: =IF(C12="NO-OOS","N/A",IF(AT12="Driver's License",IF(AU12>$AW$3,"SOS",IF(AV12>=$AW$3,"Valid",IF(AND(AU12<$AW$3,$AW$4>$AW$3,AU12>AW5),"Covid","Expired"))),IF(AT12="I9",IF(AV12>=$AW$2,"Valid",IF(AND(AT12<$AW$3,$AW$4>$AW$3,AV12>AW5),"Covid","Expired")),IF(AT12="Work Permit",IF(AND(AU12<=$AW$2,(AV12+365)>=$AW$3),"Valid","Expired"),IF(AT12="Missing Residency","Missing",IF(AT12="","","Other")))))) | BF12: =N12 -> 0 | BG12: =E12 -> 0 | BH12: =F12 -> 0 | BI12: =G12 -> #REF! | BJ12: =AX12 -> 0 | BK12: =AY12 -> 0 | BL12: =AZ12 -> 0 | BM12: =H12 -> 0 | BN12: =IF($BP$6="GROSS WAGES",(O12+P12+Q12+R12+S12+T12+AA12)-AF12,(O12+P12+Q12+R12+S12+T12)-AF12) -> 0 | BO12: =U12+V12+W12+X12 -> 0 | BP12: =IF($BP$6="ER BENEFITS / PH&W",(Z12+AA12),(Z12)) -> 0 | BQ12: =SUM(BN12:BP12) -> 0 | BR12: =AE12-BQ12 -> 0 | BS12: =BQ12-AE12+Y12+AC12+AF12 -> 0
B13: 4 | G13: =_xlfn.XLOOKUP(F13,#REF!,#REF!) -> #REF! | O13: 0 | P13: 0 | Q13: 0 | R13: 0 | S13: 0 | T13: 0 | U13: 0 | V13: 0 | W13: 0 | X13: 0 | Y13: 0 | Z13: 0 | AA13: 0 | AB13: 0 | AC13: 0 | AD13: 0 | AE13: =SUM(Q13:AC13) -> 0 | AF13: 0 | AG13: =AE13-AF13 -> 0 | AH13: 0 | AI13: =AE13-AG13 -> 0 | AW13: =IF(C13="NO-OOS","N/A",IF(AT13="Driver's License",IF(AU13>$AW$3,"SOS",IF(AV13>=$AW$3,"Valid",IF(AND(AU13<$AW$3,$AW$4>$AW$3,AU13>AW6),"Covid","Expired"))),IF(AT13="I9",IF(AV13>=$AW$2,"Valid",IF(AND(AT13<$AW$3,$AW$4>$AW$3,AV13>AW6),"Covid","Expired")),IF(AT13="Work Permit",IF(AND(AU13<=$AW$2,(AV13+365)>=$AW$3),"Valid","Expired"),IF(AT13="Missing Residency","Missing",IF(AT13="","","Other")))))) | BF13: =N13 -> 0 | BG13: =E13 -> 0 | BH13: =F13 -> 0 | BI13: =G13 -> #REF! | BJ13: =AX13 -> 0 | BK13: =AY13 -> 0 | BL13: =AZ13 -> 0 | BM13: =H13 -> 0 | BN13: =IF($BP$6="GROSS WAGES",(O13+P13+Q13+R13+S13+T13+AA13)-AF13,(O13+P13+Q13+R13+S13+T13)-AF13) -> 0 | BO13: =U13+V13+W13+X13 -> 0 | BP13: =IF($BP$6="ER BENEFITS / PH&W",(Z13+AA13),(Z13)) -> 0 | BQ13: =SUM(BN13:BP13) -> 0 | BR13: =AE13-BQ13 -> 0 | BS13: =BQ13-AE13+Y13+AC13+AF13 -> 0
B14: 5 | G14: =_xlfn.XLOOKUP(F14,#REF!,#REF!) -> #REF! | O14: 0 | P14: 0 | Q14: 0 | R14: 0 | S14: 0 | T14: 0 | U14: 0 | V14: 0 | W14: 0 | X14: 0 | Y14: 0 | Z14: 0 | AA14: 0 | AB14: 0 | AC14: 0 | AD14: 0 | AE14: =SUM(Q14:AC14) -> 0 | AF14: 0 | AG14: =AE14-AF14 -> 0 | AH14: 0 | AI14: =AE14-AG14 -> 0 | AW14: =IF(C14="NO-OOS","N/A",IF(AT14="Driver's License",IF(AU14>$AW$3,"SOS",IF(AV14>=$AW$3,"Valid",IF(AND(AU14<$AW$3,$AW$4>$AW$3,AU14>AW7),"Covid","Expired"))),IF(AT14="I9",IF(AV14>=$AW$2,"Valid",IF(AND(AT14<$AW$3,$AW$4>$AW$3,AV14>AW7),"Covid","Expired")),IF(AT14="Work Permit",IF(AND(AU14<=$AW$2,(AV14+365)>=$AW$3),"Valid","Expired"),IF(AT14="Missing Residency","Missing",IF(AT14="","","Other")))))) | BF14: =N14 -> 0 | BG14: =E14 -> 0 | BH14: =F14 -> 0 | BI14: =G14 -> #REF! | BJ14: =AX14 -> 0 | BK14: =AY14 -> 0 | BL14: =AZ14 -> 0 | BM14: =H14 -> 0 | BN14: =IF($BP$6="GROSS WAGES",(O14+P14+Q14+R14+S14+T14+AA14)-AF14,(O14+P14+Q14+R14+S14+T14)-AF14) -> 0 | BO14: =U14+V14+W14+X14 -> 0 | BP14: =IF($BP$6="ER BENEFITS / PH&W",(Z14+AA14),(Z14)) -> 0 | BQ14: =SUM(BN14:BP14) -> 0 | BR14: =AE14-BQ14 -> 0 | BS14: =BQ14-AE14+Y14+AC14+AF14 -> 0
B15: 6 | G15: =_xlfn.XLOOKUP(F15,#REF!,#REF!) -> #REF! | O15: 0 | P15: 0 | Q15: 0 | R15: 0 | S15: 0 | T15: 0 | U15: 0 | V15: 0 | W15: 0 | X15: 0 | Y15: 0 | Z15: 0 | AA15: 0 | AB15: 0 | AC15: 0 | AD15: 0 | AE15: =SUM(Q15:AC15) -> 0 | AF15: 0 | AG15: =AE15-AF15 -> 0 | AH15: 0 | AI15: =AE15-AG15 -> 0 | AW15: =IF(C15="NO-OOS","N/A",IF(AT15="Driver's License",IF(AU15>$AW$3,"SOS",IF(AV15>=$AW$3,"Valid",IF(AND(AU15<$AW$3,$AW$4>$AW$3,AU15>AW8),"Covid","Expired"))),IF(AT15="I9",IF(AV15>=$AW$2,"Valid",IF(AND(AT15<$AW$3,$AW$4>$AW$3,AV15>AW8),"Covid","Expired")),IF(AT15="Work Permit",IF(AND(AU15<=$AW$2,(AV15+365)>=$AW$3),"Valid","Expired"),IF(AT15="Missing Residency","Missing",IF(AT15="","","Other")))))) | BF15: =N15 -> 0 | BG15: =E15 -> 0 | BH15: =F15 -> 0 | BI15: =G15 -> #REF! | BJ15: =AX15 -> 0 | BK15: =AY15 -> 0 | BL15: =AZ15 -> 0 | BM15: =H15 -> 0 | BN15: =IF($BP$6="GROSS WAGES",(O15+P15+Q15+R15+S15+T15+AA15)-AF15,(O15+P15+Q15+R15+S15+T15)-AF15) -> 0 | BO15: =U15+V15+W15+X15 -> 0 | BP15: =IF($BP$6="ER BENEFITS / PH&W",(Z15+AA15),(Z15)) -> 0 | BQ15: =SUM(BN15:BP15) -> 0 | BR15: =AE15-BQ15 -> 0 | BS15: =BQ15-AE15+Y15+AC15+AF15 -> 0
B16: 7 | G16: =_xlfn.XLOOKUP(F16,#REF!,#REF!) -> #REF! | O16: 0 | P16: 0 | Q16: 0 | R16: 0 | S16: 0 | T16: 0 | U16: 0 | V16: 0 | W16: 0 | X16: 0 | Y16: 0 | Z16: 0 | AA16: 0 | AB16: 0 | AC16: 0 | AD16: 0 | AE16: =SUM(Q16:AC16) -> 0 | AF16: 0 | AG16: =AE16-AF16 -> 0 | AH16: 0 | AI16: =AE16-AG16 -> 0 | AW16: =IF(C16="NO-OOS","N/A",IF(AT16="Driver's License",IF(AU16>$AW$3,"SOS",IF(AV16>=$AW$3,"Valid",IF(AND(AU16<$AW$3,$AW$4>$AW$3,AU16>AW9),"Covid","Expired"))),IF(AT16="I9",IF(AV16>=$AW$2,"Valid",IF(AND(AT16<$AW$3,$AW$4>$AW$3,AV16>AW9),"Covid","Expired")),IF(AT16="Work Permit",IF(AND(AU16<=$AW$2,(AV16+365)>=$AW$3),"Valid","Expired"),IF(AT16="Missing Residency","Missing",IF(AT16="","","Other")))))) | BF16: =N16 -> 0 | BG16: =E16 -> 0 | BH16: =F16 -> 0 | BI16: =G16 -> #REF! | BJ16: =AX16 -> 0 | BK16: =AY16 -> 0 | BL16: =AZ16 -> 0 | BM16: =H16 -> 0 | BN16: =IF($BP$6="GROSS WAGES",(O16+P16+Q16+R16+S16+T16+AA16)-AF16,(O16+P16+Q16+R16+S16+T16)-AF16) -> 0 | BO16: =U16+V16+W16+X16 -> 0 | BP16: =IF($BP$6="ER BENEFITS / PH&W",(Z16+AA16),(Z16)) -> 0 | BQ16: =SUM(BN16:BP16) -> 0 | BR16: =AE16-BQ16 -> 0 | BS16: =BQ16-AE16+Y16+AC16+AF16 -> 0
B17: 8 | G17: =_xlfn.XLOOKUP(F17,#REF!,#REF!) -> #REF! | O17: 0 | P17: 0 | Q17: 0 | R17: 0 | S17: 0 | T17: 0 | U17: 0 | V17: 0 | W17: 0 | X17: 0 | Y17: 0 | Z17: 0 | AA17: 0 | AB17: 0 | AC17: 0 | AD17: 0 | AE17: =SUM(Q17:AC17) -> 0 | AF17: 0 | AG17: =AE17-AF17 -> 0 | AH17: 0 | AI17: =AE17-AG17 -> 0 | AW17: =IF(C17="NO-OOS","N/A",IF(AT17="Driver's License",IF(AU17>$AW$3,"SOS",IF(AV17>=$AW$3,"Valid",IF(AND(AU17<$AW$3,$AW$4>$AW$3,AU17>AW10),"Covid","Expired"))),IF(AT17="I9",IF(AV17>=$AW$2,"Valid",IF(AND(AT17<$AW$3,$AW$4>$AW$3,AV17>AW10),"Covid","Expired")),IF(AT17="Work Permit",IF(AND(AU17<=$AW$2,(AV17+365)>=$AW$3),"Valid","Expired"),IF(AT17="Missing Residency","Missing",IF(AT17="","","Other")))))) | BF17: =N17 -> 0 | BG17: =E17 -> 0 | BH17: =F17 -> 0 | BI17: =G17 -> #REF! | BJ17: =AX17 -> 0 | BK17: =AY17 -> 0 | BL17: =AZ17 -> 0 | BM17: =H17 -> 0 | BN17: =IF($BP$6="GROSS WAGES",(O17+P17+Q17+R17+S17+T17+AA17)-AF17,(O17+P17+Q17+R17+S17+T17)-AF17) -> 0 | BO17: =U17+V17+W17+X17 -> 0 | BP17: =IF($BP$6="ER BENEFITS / PH&W",(Z17+AA17),(Z17)) -> 0 | BQ17: =SUM(BN17:BP17) -> 0 | BR17: =AE17-BQ17 -> 0 | BS17: =BQ17-AE17+Y17+AC17+AF17 -> 0
B18: 9 | G18: =_xlfn.XLOOKUP(F18,#REF!,#REF!) -> #REF! | O18: 0 | P18: 0 | Q18: 0 | R18: 0 | S18: 0 | T18: 0 | U18: 0 | V18: 0 | W18: 0 | X18: 0 | Y18: 0 | Z18: 0 | AA18: 0 | AB18: 0 | AC18: 0 | AD18: 0 | AE18: =SUM(Q18:AC18) -> 0 | AF18: 0 | AG18: =AE18-AF18 -> 0 | AH18: 0 | AI18: =AE18-AG18 -> 0 | AW18: =IF(C18="NO-OOS","N/A",IF(AT18="Driver's License",IF(AU18>$AW$3,"SOS",IF(AV18>=$AW$3,"Valid",IF(AND(AU18<$AW$3,$AW$4>$AW$3,AU18>AW11),"Covid","Expired"))),IF(AT18="I9",IF(AV18>=$AW$2,"Valid",IF(AND(AT18<$AW$3,$AW$4>$AW$3,AV18>AW11),"Covid","Expired")),IF(AT18="Work Permit",IF(AND(AU18<=$AW$2,(AV18+365)>=$AW$3),"Valid","Expired"),IF(AT18="Missing Residency","Missing",IF(AT18="","","Other")))))) | BF18: =N18 -> 0 | BG18: =E18 -> 0 | BH18: =F18 -> 0 | BI18: =G18 -> #REF! | BJ18: =AX18 -> 0 | BK18: =AY18 -> 0 | BL18: =AZ18 -> 0 | BM18: =H18 -> 0 | BN18: =IF($BP$6="GROSS WAGES",(O18+P18+Q18+R18+S18+T18+AA18)-AF18,(O18+P18+Q18+R18+S18+T18)-AF18) -> 0 | BO18: =U18+V18+W18+X18 -> 0 | BP18: =IF($BP$6="ER BENEFITS / PH&W",(Z18+AA18),(Z18)) -> 0 | BQ18: =SUM(BN18:BP18) -> 0 | BR18: =AE18-BQ18 -> 0 | BS18: =BQ18-AE18+Y18+AC18+AF18 -> 0
B19: 10 | G19: =_xlfn.XLOOKUP(F19,#REF!,#REF!) -> #REF! | O19: 0 | P19: 0 | Q19: 0 | R19: 0 | S19: 0 | T19: 0 | U19: 0 | V19: 0 | W19: 0 | X19: 0 | Y19: 0 | Z19: 0 | AA19: 0 | AB19: 0 | AC19: 0 | AD19: 0 | AE19: =SUM(Q19:AC19) -> 0 | AF19: 0 | AG19: =AE19-AF19 -> 0 | AH19: 0 | AI19: =AE19-AG19 -> 0 | AW19: =IF(C19="NO-OOS","N/A",IF(AT19="Driver's License",IF(AU19>$AW$3,"SOS",IF(AV19>=$AW$3,"Valid",IF(AND(AU19<$AW$3,$AW$4>$AW$3,AU19>AW12),"Covid","Expired"))),IF(AT19="I9",IF(AV19>=$AW$2,"Valid",IF(AND(AT19<$AW$3,$AW$4>$AW$3,AV19>AW12),"Covid","Expired")),IF(AT19="Work Permit",IF(AND(AU19<=$AW$2,(AV19+365)>=$AW$3),"Valid","Expired"),IF(AT19="Missing Residency","Missing",IF(AT19="","","Other")))))) | BF19: =N19 -> 0 | BG19: =E19 -> 0 | BH19: =F19 -> 0 | BI19: =G19 -> #REF! | BJ19: =AX19 -> 0 | BK19: =AY19 -> 0 | BL19: =AZ19 -> 0 | BM19: =H19 -> 0 | BN19: =IF($BP$6="GROSS WAGES",(O19+P19+Q19+R19+S19+T19+AA19)-AF19,(O19+P19+Q19+R19+S19+T19)-AF19) -> 0 | BO19: =U19+V19+W19+X19 -> 0 | BP19: =IF($BP$6="ER BENEFITS / PH&W",(Z19+AA19),(Z19)) -> 0 | BQ19: =SUM(BN19:BP19) -> 0 | BR19: =AE19-BQ19 -> 0 | BS19: =BQ19-AE19+Y19+AC19+AF19 -> 0
B20: 11 | G20: =_xlfn.XLOOKUP(F20,#REF!,#REF!) -> #REF! | O20: 0 | P20: 0 | Q20: 0 | R20: 0 | S20: 0 | T20: 0 | U20: 0 | V20: 0 | W20: 0 | X20: 0 | Y20: 0 | Z20: 0 | AA20: 0 | AB20: 0 | AC20: 0 | AD20: 0 | AE20: =SUM(Q20:AC20) -> 0 | AF20: 0 | AG20: =AE20-AF20 -> 0 | AH20: 0 | AI20: =AE20-AG20 -> 0 | AW20: =IF(C20="NO-OOS","N/A",IF(AT20="Driver's License",IF(AU20>$AW$3,"SOS",IF(AV20>=$AW$3,"Valid",IF(AND(AU20<$AW$3,$AW$4>$AW$3,AU20>AW13),"Covid","Expired"))),IF(AT20="I9",IF(AV20>=$AW$2,"Valid",IF(AND(AT20<$AW$3,$AW$4>$AW$3,AV20>AW13),"Covid","Expired")),IF(AT20="Work Permit",IF(AND(AU20<=$AW$2,(AV20+365)>=$AW$3),"Valid","Expired"),IF(AT20="Missing Residency","Missing",IF(AT20="","","Other")))))) | BF20: =N20 -> 0 | BG20: =E20 -> 0 | BH20: =F20 -> 0 | BI20: =G20 -> #REF! | BJ20: =AX20 -> 0 | BK20: =AY20 -> 0 | BL20: =AZ20 -> 0 | BM20: =H20 -> 0 | BN20: =IF($BP$6="GROSS WAGES",(O20+P20+Q20+R20+S20+T20+AA20)-AF20,(O20+P20+Q20+R20+S20+T20)-AF20) -> 0 | BO20: =U20+V20+W20+X20 -> 0 | BP20: =IF($BP$6="ER BENEFITS / PH&W",(Z20+AA20),(Z20)) -> 0 | BQ20: =SUM(BN20:BP20) -> 0 | BR20: =AE20-BQ20 -> 0 | BS20: =BQ20-AE20+Y20+AC20+AF20 -> 0
B21: 12 | G21: =_xlfn.XLOOKUP(F21,#REF!,#REF!) -> #REF! | O21: 0 | P21: 0 | Q21: 0 | R21: 0 | S21: 0 | T21: 0 | U21: 0 | V21: 0 | W21: 0 | X21: 0 | Y21: 0 | Z21: 0 | AA21: 0 | AB21: 0 | AC21: 0 | AD21: 0 | AE21: =SUM(Q21:AC21) -> 0 | AF21: 0 | AG21: =AE21-AF21 -> 0 | AH21: 0 | AI21: =AE21-AG21 -> 0 | AW21: =IF(C21="NO-OOS","N/A",IF(AT21="Driver's License",IF(AU21>$AW$3,"SOS",IF(AV21>=$AW$3,"Valid",IF(AND(AU21<$AW$3,$AW$4>$AW$3,AU21>AW14),"Covid","Expired"))),IF(AT21="I9",IF(AV21>=$AW$2,"Valid",IF(AND(AT21<$AW$3,$AW$4>$AW$3,AV21>AW14),"Covid","Expired")),IF(AT21="Work Permit",IF(AND(AU21<=$AW$2,(AV21+365)>=$AW$3),"Valid","Expired"),IF(AT21="Missing Residency","Missing",IF(AT21="","","Other")))))) | BF21: =N21 -> 0 | BG21: =E21 -> 0 | BH21: =F21 -> 0 | BI21: =G21 -> #REF! | BJ21: =AX21 -> 0 | BK21: =AY21 -> 0 | BL21: =AZ21 -> 0 | BM21: =H21 -> 0 | BN21: =IF($BP$6="GROSS WAGES",(O21+P21+Q21+R21+S21+T21+AA21)-AF21,(O21+P21+Q21+R21+S21+T21)-AF21) -> 0 | BO21: =U21+V21+W21+X21 -> 0 | BP21: =IF($BP$6="ER BENEFITS / PH&W",(Z21+AA21),(Z21)) -> 0 | BQ21: =SUM(BN21:BP21) -> 0 | BR21: =AE21-BQ21 -> 0 | BS21: =BQ21-AE21+Y21+AC21+AF21 -> 0
B22: 13 | G22: =_xlfn.XLOOKUP(F22,#REF!,#REF!) -> #REF! | O22: 0 | P22: 0 | Q22: 0 | R22: 0 | S22: 0 | T22: 0 | U22: 0 | V22: 0 | W22: 0 | X22: 0 | Y22: 0 | Z22: 0 | AA22: 0 | AB22: 0 | AC22: 0 | AD22: 0 | AE22: =SUM(Q22:AC22) -> 0 | AF22: 0 | AG22: =AE22-AF22 -> 0 | AH22: 0 | AI22: =AE22-AG22 -> 0 | AW22: =IF(C22="NO-OOS","N/A",IF(AT22="Driver's License",IF(AU22>$AW$3,"SOS",IF(AV22>=$AW$3,"Valid",IF(AND(AU22<$AW$3,$AW$4>$AW$3,AU22>AW15),"Covid","Expired"))),IF(AT22="I9",IF(AV22>=$AW$2,"Valid",IF(AND(AT22<$AW$3,$AW$4>$AW$3,AV22>AW15),"Covid","Expired")),IF(AT22="Work Permit",IF(AND(AU22<=$AW$2,(AV22+365)>=$AW$3),"Valid","Expired"),IF(AT22="Missing Residency","Missing",IF(AT22="","","Other")))))) | BF22: =N22 -> 0 | BG22: =E22 -> 0 | BH22: =F22 -> 0 | BI22: =G22 -> #REF! | BJ22: =AX22 -> 0 | BK22: =AY22 -> 0 | BL22: =AZ22 -> 0 | BM22: =H22 -> 0 | BN22: =IF($BP$6="GROSS WAGES",(O22+P22+Q22+R22+S22+T22+AA22)-AF22,(O22+P22+Q22+R22+S22+T22)-AF22) -> 0 | BO22: =U22+V22+W22+X22 -> 0 | BP22: =IF($BP$6="ER BENEFITS / PH&W",(Z22+AA22),(Z22)) -> 0 | BQ22: =SUM(BN22:BP22) -> 0 | BR22: =AE22-BQ22 -> 0 | BS22: =BQ22-AE22+Y22+AC22+AF22 -> 0
... B39: 30 | G39: =_xlfn.XLOOKUP(F39,#REF!,#REF!) -> #REF! | O39: 0 | P39: 0 | Q39: 0 | R39: 0 | S39: 0 | T39: 0 | U39: 0 | V39: 0 | W39: 0 | X39: 0 | Y39: 0 | Z39: 0 | AA39: 0 | AB39: 0 | AC39: 0 | AD39: 0 | AE39: =SUM(Q39:AC39) -> 0 | AF39: 0 | AG39: =AE39-AF39 -> 0 | AH39: 0 | AI39: =AE39-AG39 -> 0 | AW39: =IF(C39="NO-OOS","N/A",IF(AT39="Driver's License",IF(AU39>$AW$3,"SOS",IF(AV39>=$AW$3,"Valid",IF(AND(AU39<$AW$3,$AW$4>$AW$3,AU39>AW32),"Covid","Expired"))),IF(AT39="I9",IF(AV39>=$AW$2,"Valid",IF(AND(AT39<$AW$3,$AW$4>$AW$3,AV39>AW32),"Covid","Expired")),IF(AT39="Work Permit",IF(AND(AU39<=$AW$2,(AV39+365)>=$AW$3),"Valid","Expired"),IF(AT39="Missing Residency","Missing",IF(AT39="","","Other")))))) | BF39: =N39 -> 0 | BG39: =E39 -> 0 | BH39: =F39 -> 0 | BI39: =G39 -> #REF! | BJ39: =AX39 -> 0 | BK39: =AY39 -> 0 | BL39: =AZ39 -> 0 | BM39: =H39 -> 0 | BN39: =IF($BP$6="GROSS WAGES",(O39+P39+Q39+R39+S39+T39+AA39)-AF39,(O39+P39+Q39+R39+S39+T39)-AF39) -> 0 | BO39: =U39+V39+W39+X39 -> 0 | BP39: =IF($BP$6="ER BENEFITS / PH&W",(Z39+AA39),(Z39)) -> 0 | BQ39: =SUM(BN39:BP39) -> 0 | BR39: =AE39-BQ39 -> 0 | BS39: =BQ39-AE39+Y39+AC39+AF39 -> 0
O40: 0 | P40: 0 | Q40: 0 | R40: 0 | S40: 0 | T40: 0 | U40: 0 | V40: 0 | W40: 0 | X40: 0 | Y40: 0 | AI40: =AE40-AG40 -> 0 | AW40: =IF(C40="NO-OOS","N/A",IF(AT40="Driver's License",IF(AU40>$AW$3,"SOS",IF(AV40>=$AW$3,"Valid",IF(AND(AU40<$AW$3,$AW$4>$AW$3,AU40>43831),"Covid","Expired"))),IF(AT40="I9",IF(AU40>=$AW$3,"Valid",IF(AND(AT40<$AW$3,$AW$4>$AW$3,AU40>43831),"Covid","Expired")),IF(AT40="Work Permit",IF(AND(AU40<=$AW$2,(AV40+365)>=$AW$3),"Valid","Expired"),IF(AT40="Missing Residency","Missing",IF(AT40="","","Other")))))) | BF40: =N40 -> 0 | BG40: =E40 -> 0 | BH40: =F40 -> 0 | BI40: =G40 -> 0 | BJ40: =AX40 -> 0 | BK40: =AY40 -> 0 | BL40: =AZ40 -> 0 | BM40: =H40 -> 0 | BN40: =IF($BP$6="GROSS WAGES",(O40+P40+Q40+R40+S40+T40+AA40)-AF40,(O40+P40+Q40+R40+S40+T40)-AF40) -> 0 | BO40: =U40+V40+W40+X40 -> 0 | BP40: =IF($BP$6="ER BENEFITS / PH&W",(Z40+AA40),(Z40)) -> 0 | BQ40: =SUM(BN40:BP40) -> 0 | BR40: =AE40-BQ40 -> 0 | BS40: =BQ40-AE40+Y40+AC40+AF40 -> 0
O41: 0 | P41: 0 | Q41: 0 | R41: 0 | S41: 0 | T41: 0 | U41: 0 | V41: 0 | W41: 0 | X41: 0 | AI41: =AE41-AG41 -> 0 | AW41: =IF(C41="NO-OOS","N/A",IF(AT41="Driver's License",IF(AU41>$AW$3,"SOS",IF(AV41>=$AW$4,"Valid",IF(AND(AV41<$AW$4,$AW$5>$AW$4,AV41>43831),"Covid","Expired"))),IF(AT41="I9",IF(AV41>=$AW$4,"Valid",IF(AND(AV41<$AW$4,$AW$5>$AW$4,AV41>43831),"Covid","Expired")),IF(AT41="Work Permit",IF(AND(AU41<=$AW$3,(AU41+365)>=$AW$4),"Valid","Expired"),IF(AT41="Missing Residency","Missing",IF(AT41="","","Other")))))) | BF41: =N41 -> 0 | BG41: =E41 -> 0 | BH41: =F41 -> 0 | BI41: =G41 -> 0 | BJ41: =AX41 -> 0 | BK41: =AY41 -> 0 | BL41: =AZ41 -> 0 | BM41: =H41 -> 0 | BN41: =IF($BP$6="GROSS WAGES",(O41+P41+Q41+R41+S41+T41+AA41)-AF41,(O41+P41+Q41+R41+S41+T41)-AF41) -> 0 | BO41: =U41+V41+W41+X41 -> 0 | BP41: =IF($BP$6="ER BENEFITS / PH&W",(Z41+AA41),(Z41)) -> 0 | BQ41: =SUM(BN41:BP41) -> 0 | BR41: =AE41-BQ41 -> 0 | BS41: =BQ41-AE41+Y41+AC41+AF41 -> 0
O42: =SUBTOTAL(9,O9:O41) -> 0 | P42: =SUBTOTAL(9,P9:P41) -> 0 | Q42: =SUBTOTAL(9,Q9:Q41) -> 0 | R42: =SUBTOTAL(9,R9:R41) -> 0 | S42: =SUBTOTAL(9,S9:S41) -> 0 | T42: =SUBTOTAL(9,T9:T41) -> 0 | U42: =SUBTOTAL(9,U9:U41) -> 0 | V42: =SUBTOTAL(9,V9:V41) -> 0 | ... AG42: =SUBTOTAL(9,AG9:AG41) -> 0 | BN42: =SUBTOTAL(9,BN9:BN41) -> 0 | BO42: =SUBTOTAL(9,BO9:BO41) -> 0 | BP42: =SUBTOTAL(9,BP9:BP41) -> 0 | BQ42: =SUBTOTAL(9,BQ9:BQ41) -> 0 | BR42: =SUM(BR9:BR41) -> 0 | BS42: =BQ42-AE42+Y42+AC42+AF42 -> 0
O45: =SUM(O9:O41) -> 0 | P45: =SUM(P9:P41) -> 0 | Q45: =SUM(Q9:Q41) -> 0 | R45: =SUM(R9:R41) -> 0 | S45: =SUM(S9:S41) -> 0 | T45: =SUM(T9:T41) -> 0 | U45: =SUM(U9:U41) -> 0 | V45: =SUM(V9:V41) -> 0 | ... AG45: =SUM(AG9:AG41) -> 0 | BN45: =SUM(BN9:BN41) -> 0 | BO45: =SUM(BO9:BO41) -> 0 | BP45: =SUM(BP9:BP41) -> 0 | BQ45: =SUM(BQ9:BQ41) -> 0 | BR45: =SUM(BR9:BR41) -> 0
R51: Number of YES-OOS | S51: =COUNTIFS($C$9:$C$41,"YES-OOS") -> 0 | W51: ELIGIBLE TOTAL
U52: PENDING | V52: NO-OOS | W52: NO-IL | X52: YES-OOS | Y52: YES
R53: Total Eligible | S53: =(Y53)-S57 -> 0 | U53: =SUMIF($C$9:$C$41,U52,$BQ$9:$BQ$41) -> 0 | V53: =SUMIF($C$9:$C$41,V52,$BQ$9:$BQ$41) -> 0 | W53: =SUMIF($C$9:$C$41,W52,$BQ$9:$BQ$41) -> 0 | X53: =SUMIF($C$9:$C$41,X52,$BQ$9:$BQ$41) -> 0 | Y53: =SUMIF($C$9:$C$41,Y52,$BQ$9:$BQ$41) -> 0 | Z53: =SUM(U53:Y53) -> 0
R54: Two OOS Crew | S54: =X53 -> 0 | Z54: =Z53-BQ45 -> 0
R55: Pending | S55: =U53 -> 0
R56: Total Ineligible | S56: =V53+W53+V58+W58+Y58+X58+U58 -> 0 | W56: INELIGIBLE TOTAL
R57: PAs | S57: =SUMIF(AS9:AS41,"Elite CIS",AE9:AE41) -> 0 | U57: PENDING | V57: NO-OOS | W57: NO-IL | X57: YES-OOS | Y57: YES
R58: Total Expenses | S58: =SUM(S53:S57) -> 0 | U58: =SUMIF($C$9:$C$41,U57,$BR$9:$BR$41) -> 0 | V58: =SUMIF($C$9:$C$41,V57,$BR$9:$BR$41) -> 0 | W58: =SUMIF($C$9:$C$41,W57,$BR$9:$BR$41) -> 0 | X58: =SUMIF($C$9:$C$41,X57,$BR$9:$BR$41) -> 0 | Y58: =SUMIF($C$9:$C$41,Y57,$BR$9:$BR$41) -> 0 | Z58: =SUM(U58:Y58) -> 0
S59: =S58-AE45 -> 0 | Z59: =Z58-BR45 -> 0
R62: Payroll & Crew Invoice No. | S62: Invoice Amount | T62: Qualified Amount | U62: Pending | V62: Ineligible Amount | W62: Gross | X62: ER Taxes | Y62: Benefits (P, H & W) | Z62: Total Qualified
R63: 1 | S63: =SUMIF($N$9:$N$41,R63,$AE$9:$AE$41) -> 0 | T63: =SUMIFS($BQ$9:$BQ$41,$N$9:$N$41,R63,$C$9:$C$41,"YES")+SUMIFS($BQ$9:$BQ$41,$N$9:$N$41,R63,$C$9:$C$41,"YES-OOS") -> 0 | U63: =SUMIFS($BQ$9:$BQ$41,$N$9:$N$41,R63,$C$9:$C$41,"PENDING") -> 0 | V63: =S63-(T63+U63) -> 0 | W63: =SUMIFS($BN$9:$BN$41,$N$9:$N$41,R63,$C$9:$C$41,"YES")+SUMIFS($BN$9:$BN$41,$N$9:$N$41,R63,$C$9:$C$41,"YES-OOS") -> 0 | X63: =SUMIFS($BO$9:$BO$41,$N$9:$N$41,R63,$C$9:$C$41,"YES")+SUMIFS($BO$9:$BO$41,$N$9:$N$41,R63,$C$9:$C$41,"YES-OOS") -> 0 | Y63: =SUMIFS($BP$9:$BP$41,$N$9:$N$41,R63,$C$9:$C$41,"YES")+SUMIFS($BP$9:$BP$41,$N$9:$N$41,R63,$C$9:$C$41,"YES-OOS") -> 0 | Z63: =SUM(W63:Y63) -> 0 | AQ63: =Z63-T63 -> 0
R64: 2 | S64: =SUMIF($N$9:$N$41,R64,$AE$9:$AE$41) -> 0 | T64: =SUMIFS($BQ$9:$BQ$41,$N$9:$N$41,R64,$C$9:$C$41,"YES")+SUMIFS($BQ$9:$BQ$41,$N$9:$N$41,R64,$C$9:$C$41,"YES-OOS") -> 0 | U64: =SUMIFS($BQ$9:$BQ$41,$N$9:$N$41,R64,$C$9:$C$41,"PENDING") -> 0 | V64: =S64-(T64+U64) -> 0 | W64: =SUMIFS($BN$9:$BN$41,$N$9:$N$41,R64,$C$9:$C$41,"YES")+SUMIFS($BN$9:$BN$41,$N$9:$N$41,R64,$C$9:$C$41,"YES-OOS") -> 0 | X64: =SUMIFS($BO$9:$BO$41,$N$9:$N$41,R64,$C$9:$C$41,"YES")+SUMIFS($BO$9:$BO$41,$N$9:$N$41,R64,$C$9:$C$41,"YES-OOS") -> 0 | Y64: =SUMIFS($BP$9:$BP$41,$N$9:$N$41,R64,$C$9:$C$41,"YES")+SUMIFS($BP$9:$BP$41,$N$9:$N$41,R64,$C$9:$C$41,"YES-OOS") -> 0 | Z64: =SUM(W64:Y64) -> 0 | AQ64: =Z64-T64 -> 0
R65: 3 | S65: =SUMIF($N$9:$N$41,R65,$AE$9:$AE$41) -> 0 | T65: =SUMIFS($BQ$9:$BQ$41,$N$9:$N$41,R65,$C$9:$C$41,"YES")+SUMIFS($BQ$9:$BQ$41,$N$9:$N$41,R65,$C$9:$C$41,"YES-OOS") -> 0 | U65: =SUMIFS($BQ$9:$BQ$41,$N$9:$N$41,R65,$C$9:$C$41,"PENDING") -> 0 | V65: =S65-(T65+U65) -> 0 | W65: =SUMIFS($BN$9:$BN$41,$N$9:$N$41,R65,$C$9:$C$41,"YES")+SUMIFS($BN$9:$BN$41,$N$9:$N$41,R65,$C$9:$C$41,"YES-OOS") -> 0 | X65: =SUMIFS($BO$9:$BO$41,$N$9:$N$41,R65,$C$9:$C$41,"YES")+SUMIFS($BO$9:$BO$41,$N$9:$N$41,R65,$C$9:$C$41,"YES-OOS") -> 0 | Y65: =SUMIFS($BP$9:$BP$41,$N$9:$N$41,R65,$C$9:$C$41,"YES")+SUMIFS($BP$9:$BP$41,$N$9:$N$41,R65,$C$9:$C$41,"YES-OOS") -> 0 | Z65: =SUM(W65:Y65) -> 0 | AQ65: =Z65-T65 -> 0
R66: 4 | S66: =SUMIF($N$9:$N$41,R66,$AE$9:$AE$41) -> 0 | T66: =SUMIFS($BQ$9:$BQ$41,$N$9:$N$41,R66,$C$9:$C$41,"YES")+SUMIFS($BQ$9:$BQ$41,$N$9:$N$41,R66,$C$9:$C$41,"YES-OOS") -> 0 | U66: =SUMIFS($BQ$9:$BQ$41,$N$9:$N$41,R66,$C$9:$C$41,"PENDING") -> 0 | V66: =S66-(T66+U66) -> 0 | W66: =SUMIFS($BN$9:$BN$41,$N$9:$N$41,R66,$C$9:$C$41,"YES")+SUMIFS($BN$9:$BN$41,$N$9:$N$41,R66,$C$9:$C$41,"YES-OOS") -> 0 | X66: =SUMIFS($BO$9:$BO$41,$N$9:$N$41,R66,$C$9:$C$41,"YES")+SUMIFS($BO$9:$BO$41,$N$9:$N$41,R66,$C$9:$C$41,"YES-OOS") -> 0 | Y66: =SUMIFS($BP$9:$BP$41,$N$9:$N$41,R66,$C$9:$C$41,"YES")+SUMIFS($BP$9:$BP$41,$N$9:$N$41,R66,$C$9:$C$41,"YES-OOS") -> 0 | Z66: =SUM(W66:Y66) -> 0 | AQ66: =Z66-T66 -> 0
R67: 5 | S67: =SUMIF($N$9:$N$41,R67,$AE$9:$AE$41) -> 0 | T67: =SUMIFS($BQ$9:$BQ$41,$N$9:$N$41,R67,$C$9:$C$41,"YES")+SUMIFS($BQ$9:$BQ$41,$N$9:$N$41,R67,$C$9:$C$41,"YES-OOS") -> 0 | U67: =SUMIFS($BQ$9:$BQ$41,$N$9:$N$41,R67,$C$9:$C$41,"PENDING") -> 0 | V67: =S67-(T67+U67) -> 0 | W67: =SUMIFS($BN$9:$BN$41,$N$9:$N$41,R67,$C$9:$C$41,"YES")+SUMIFS($BN$9:$BN$41,$N$9:$N$41,R67,$C$9:$C$41,"YES-OOS") -> 0 | X67: =SUMIFS($BO$9:$BO$41,$N$9:$N$41,R67,$C$9:$C$41,"YES")+SUMIFS($BO$9:$BO$41,$N$9:$N$41,R67,$C$9:$C$41,"YES-OOS") -> 0 | Y67: =SUMIFS($BP$9:$BP$41,$N$9:$N$41,R67,$C$9:$C$41,"YES")+SUMIFS($BP$9:$BP$41,$N$9:$N$41,R67,$C$9:$C$41,"YES-OOS") -> 0 | Z67: =SUM(W67:Y67) -> 0 | AQ67: =Z67-T67 -> 0
S68: =SUMIF($N$9:$N$41,R68,$AE$9:$AE$41) -> 0 | T68: =SUMIFS($BQ$9:$BQ$41,$N$9:$N$41,R68,$C$9:$C$41,"YES")+SUMIFS($BQ$9:$BQ$41,$N$9:$N$41,R68,$C$9:$C$41,"YES-OOS") -> 0 | U68: =SUMIFS($BQ$9:$BQ$41,$N$9:$N$41,R68,$C$9:$C$41,"PENDING") -> 0 | V68: =S68-(T68+U68) -> 0 | W68: =SUMIFS($BN$9:$BN$41,$N$9:$N$41,R68,$C$9:$C$41,"YES")+SUMIFS($BN$9:$BN$41,$N$9:$N$41,R68,$C$9:$C$41,"YES-OOS") -> 0 | X68: =SUMIFS($BO$9:$BO$41,$N$9:$N$41,R68,$C$9:$C$41,"YES")+SUMIFS($BO$9:$BO$41,$N$9:$N$41,R68,$C$9:$C$41,"YES-OOS") -> 0 | Y68: =SUMIFS($BP$9:$BP$41,$N$9:$N$41,R68,$C$9:$C$41,"YES")+SUMIFS($BP$9:$BP$41,$N$9:$N$41,R68,$C$9:$C$41,"YES-OOS") -> 0 | Z68: =SUM(W68:Y68) -> 0 | AQ68: =Z68-T68 -> 0
S69: =SUMIF($N$9:$N$41,R69,$AE$9:$AE$41) -> 0 | T69: =SUMIFS($BQ$9:$BQ$41,$N$9:$N$41,R69,$C$9:$C$41,"YES")+SUMIFS($BQ$9:$BQ$41,$N$9:$N$41,R69,$C$9:$C$41,"YES-OOS") -> 0 | U69: =SUMIFS($BQ$9:$BQ$41,$N$9:$N$41,R69,$C$9:$C$41,"PENDING") -> 0 | V69: =S69-(T69+U69) -> 0 | W69: =SUMIFS($BN$9:$BN$41,$N$9:$N$41,R69,$C$9:$C$41,"YES")+SUMIFS($BN$9:$BN$41,$N$9:$N$41,R69,$C$9:$C$41,"YES-OOS") -> 0 | X69: =SUMIFS($BO$9:$BO$41,$N$9:$N$41,R69,$C$9:$C$41,"YES")+SUMIFS($BO$9:$BO$41,$N$9:$N$41,R69,$C$9:$C$41,"YES-OOS") -> 0 | Y69: =SUMIFS($BP$9:$BP$41,$N$9:$N$41,R69,$C$9:$C$41,"YES")+SUMIFS($BP$9:$BP$41,$N$9:$N$41,R69,$C$9:$C$41,"YES-OOS") -> 0 | Z69: =SUM(W69:Y69) -> 0 | AQ69: =Z69-T69 -> 0
S70: =SUMIF($N$9:$N$41,R70,$AE$9:$AE$41) -> 0 | T70: =SUMIFS($BQ$9:$BQ$41,$N$9:$N$41,R70,$C$9:$C$41,"YES")+SUMIFS($BQ$9:$BQ$41,$N$9:$N$41,R70,$C$9:$C$41,"YES-OOS") -> 0 | U70: =SUMIFS($BQ$9:$BQ$41,$N$9:$N$41,R70,$C$9:$C$41,"PENDING") -> 0 | V70: =S70-(T70+U70) -> 0 | W70: =SUMIFS($BN$9:$BN$41,$N$9:$N$41,R70,$C$9:$C$41,"YES")+SUMIFS($BN$9:$BN$41,$N$9:$N$41,R70,$C$9:$C$41,"YES-OOS") -> 0 | X70: =SUMIFS($BO$9:$BO$41,$N$9:$N$41,R70,$C$9:$C$41,"YES")+SUMIFS($BO$9:$BO$41,$N$9:$N$41,R70,$C$9:$C$41,"YES-OOS") -> 0 | Y70: =SUMIFS($BP$9:$BP$41,$N$9:$N$41,R70,$C$9:$C$41,"YES")+SUMIFS($BP$9:$BP$41,$N$9:$N$41,R70,$C$9:$C$41,"YES-OOS") -> 0 | Z70: =SUM(W70:Y70) -> 0 | AQ70: =Z70-T70 -> 0
S71: =SUMIF($N$9:$N$41,R71,$AE$9:$AE$41) -> 0 | T71: =SUMIFS($BQ$9:$BQ$41,$N$9:$N$41,R71,$C$9:$C$41,"YES")+SUMIFS($BQ$9:$BQ$41,$N$9:$N$41,R71,$C$9:$C$41,"YES-OOS") -> 0 | U71: =SUMIFS($BQ$9:$BQ$41,$N$9:$N$41,R71,$C$9:$C$41,"PENDING") -> 0 | V71: =S71-(T71+U71) -> 0 | W71: =SUMIFS($BN$9:$BN$41,$N$9:$N$41,R71,$C$9:$C$41,"YES")+SUMIFS($BN$9:$BN$41,$N$9:$N$41,R71,$C$9:$C$41,"YES-OOS") -> 0 | X71: =SUMIFS($BO$9:$BO$41,$N$9:$N$41,R71,$C$9:$C$41,"YES")+SUMIFS($BO$9:$BO$41,$N$9:$N$41,R71,$C$9:$C$41,"YES-OOS") -> 0 | Y71: =SUMIFS($BP$9:$BP$41,$N$9:$N$41,R71,$C$9:$C$41,"YES")+SUMIFS($BP$9:$BP$41,$N$9:$N$41,R71,$C$9:$C$41,"YES-OOS") -> 0 | Z71: =SUM(W71:Y71) -> 0 | AQ71: =Z71-T71 -> 0
S72: =SUMIF($N$9:$N$41,R72,$AE$9:$AE$41) -> 0 | T72: =SUMIFS($BQ$9:$BQ$41,$N$9:$N$41,R72,$C$9:$C$41,"YES")+SUMIFS($BQ$9:$BQ$41,$N$9:$N$41,R72,$C$9:$C$41,"YES-OOS") -> 0 | U72: =SUMIFS($BQ$9:$BQ$41,$N$9:$N$41,R72,$C$9:$C$41,"PENDING") -> 0 | V72: =S72-(T72+U72) -> 0 | W72: =SUMIFS($BN$9:$BN$41,$N$9:$N$41,R72,$C$9:$C$41,"YES")+SUMIFS($BN$9:$BN$41,$N$9:$N$41,R72,$C$9:$C$41,"YES-OOS") -> 0 | X72: =SUMIFS($BO$9:$BO$41,$N$9:$N$41,R72,$C$9:$C$41,"YES")+SUMIFS($BO$9:$BO$41,$N$9:$N$41,R72,$C$9:$C$41,"YES-OOS") -> 0 | Y72: =SUMIFS($BP$9:$BP$41,$N$9:$N$41,R72,$C$9:$C$41,"YES")+SUMIFS($BP$9:$BP$41,$N$9:$N$41,R72,$C$9:$C$41,"YES-OOS") -> 0 | Z72: =SUM(W72:Y72) -> 0 | AQ72: =Z72-T72 -> 0
S73: =SUMIF($N$9:$N$41,R73,$AE$9:$AE$41) -> 0 | T73: =SUMIFS($BQ$9:$BQ$41,$N$9:$N$41,R73,$C$9:$C$41,"YES")+SUMIFS($BQ$9:$BQ$41,$N$9:$N$41,R73,$C$9:$C$41,"YES-OOS") -> 0 | U73: =SUMIFS($BQ$9:$BQ$41,$N$9:$N$41,R73,$C$9:$C$41,"PENDING") -> 0 | V73: =S73-(T73+U73) -> 0 | W73: =SUMIFS($BN$9:$BN$41,$N$9:$N$41,R73,$C$9:$C$41,"YES")+SUMIFS($BN$9:$BN$41,$N$9:$N$41,R73,$C$9:$C$41,"YES-OOS") -> 0 | X73: =SUMIFS($BO$9:$BO$41,$N$9:$N$41,R73,$C$9:$C$41,"YES")+SUMIFS($BO$9:$BO$41,$N$9:$N$41,R73,$C$9:$C$41,"YES-OOS") -> 0 | Y73: =SUMIFS($BP$9:$BP$41,$N$9:$N$41,R73,$C$9:$C$41,"YES")+SUMIFS($BP$9:$BP$41,$N$9:$N$41,R73,$C$9:$C$41,"YES-OOS") -> 0 | Z73: =SUM(W73:Y73) -> 0 | AQ73: =Z73-T73 -> 0
S74: =SUMIF($N$9:$N$41,R74,$AE$9:$AE$41) -> 0 | T74: =SUMIFS($BQ$9:$BQ$41,$N$9:$N$41,R74,$C$9:$C$41,"YES")+SUMIFS($BQ$9:$BQ$41,$N$9:$N$41,R74,$C$9:$C$41,"YES-OOS") -> 0 | U74: =SUMIFS($BQ$9:$BQ$41,$N$9:$N$41,R74,$C$9:$C$41,"PENDING") -> 0 | V74: =S74-(T74+U74) -> 0 | W74: =SUMIFS($BN$9:$BN$41,$N$9:$N$41,#REF!,$C$9:$C$41,"YES")+SUMIFS($BN$9:$BN$41,$N$9:$N$41,#REF!,$C$9:$C$41,"YES-OOS") -> 0 | X74: =SUMIFS($BO$9:$BO$41,$N$9:$N$41,#REF!,$C$9:$C$41,"YES")+SUMIFS($BO$9:$BO$41,$N$9:$N$41,#REF!,$C$9:$C$41,"YES-OOS") -> 0 | Y74: =SUMIFS($BP$9:$BP$41,$N$9:$N$41,R74,$C$9:$C$41,"YES")+SUMIFS($BP$9:$BP$41,$N$9:$N$41,R74,$C$9:$C$41,"YES-OOS") -> 0 | Z74: =SUM(W74:Y74) -> 0 | AQ74: =Z74-T74 -> 0
S75: =SUMIF($N$9:$N$41,R75,$AE$9:$AE$41) -> 0 | T75: =SUMIFS($BQ$9:$BQ$41,$N$9:$N$41,R75,$C$9:$C$41,"YES")+SUMIFS($BQ$9:$BQ$41,$N$9:$N$41,R75,$C$9:$C$41,"YES-OOS") -> 0 | U75: =SUMIFS($BQ$9:$BQ$41,$N$9:$N$41,R75,$C$9:$C$41,"PENDING") -> 0 | V75: =S75-(T75+U75) -> 0 | W75: =SUMIFS($BN$9:$BN$41,$N$9:$N$41,#REF!,$C$9:$C$41,"YES")+SUMIFS($BN$9:$BN$41,$N$9:$N$41,#REF!,$C$9:$C$41,"YES-OOS") -> 0 | X75: =SUMIFS($BO$9:$BO$41,$N$9:$N$41,#REF!,$C$9:$C$41,"YES")+SUMIFS($BO$9:$BO$41,$N$9:$N$41,#REF!,$C$9:$C$41,"YES-OOS") -> 0 | Y75: =SUMIFS($BP$9:$BP$41,$N$9:$N$41,R75,$C$9:$C$41,"YES")+SUMIFS($BP$9:$BP$41,$N$9:$N$41,R75,$C$9:$C$41,"YES-OOS") -> 0 | Z75: =SUM(W75:Y75) -> 0 | AQ75: =Z75-T75 -> 0
R76: Hours Letter | S76: =SUMIF($N$9:$N$41,R76,$AE$9:$AE$41) -> 0 | T76: =SUMIFS($BQ$9:$BQ$41,$N$9:$N$41,R76,$C$9:$C$41,"YES")+SUMIFS($BQ$9:$BQ$41,$N$9:$N$41,R76,$C$9:$C$41,"YES-OOS") -> 0 | U76: =SUMIFS($BQ$9:$BQ$41,$N$9:$N$41,R76,$C$9:$C$41,"PENDING") -> 0 | V76: =S76-(T76+U76) -> 0 | W76: =SUMIFS($BN$9:$BN$41,$N$9:$N$41,R76,$C$9:$C$41,"YES")+SUMIFS($BN$9:$BN$41,$N$9:$N$41,R76,$C$9:$C$41,"YES-OOS") -> 0 | X76: =SUMIFS($BO$9:$BO$41,$N$9:$N$41,R76,$C$9:$C$41,"YES")+SUMIFS($BO$9:$BO$41,$N$9:$N$41,R76,$C$9:$C$41,"YES-OOS") -> 0 | Y76: =SUMIFS($BP$9:$BP$41,$N$9:$N$41,R76,$C$9:$C$41,"YES")+SUMIFS($BP$9:$BP$41,$N$9:$N$41,R76,$C$9:$C$41,"YES-OOS") -> 0 | Z76: =SUM(W76:Y76) -> 0 | AQ76: =Z76-T76 -> 0
R77: Total | S77: =SUM(S63:S76) -> 0 | T77: =SUM(T63:T76) -> 0 | U77: =SUM(U63:U76) -> 0 | V77: =SUM(V63:V76) -> 0 | W77: =SUM(W63:W76) -> 0 | X77: =SUM(X63:X76) -> 0 | Y77: =SUM(Y63:Y76) -> 0 | Z77: =SUM(Z63:Z76) -> 0 | AQ77: =Z77-T77 -> 0
S78: =S77-AE45 -> 0 | T78: =T77-(S53+S54) -> 0 | U78: =U77-U53 -> 0 | V78: =V77-S56 -> 0
R80: All Freelance | S80: 0 | T80: 0 | U80: 0

Sheet Talent & Extras
B1: Production Tax Incentives Talent & Extras
AA3: 1st Shoot Day | AB3: 44597
B4: Project Title: | C4: =#REF! -> #REF! | AA4: Last Shoot Day | AB4: 44600
B5: Shoot Date: | C5: =#REF! -> #REF! | G5: DELETE SAMPLE DATA FOR ACTUAL PROJECTS | AA5: Covid End Date | AB5: 44896
B6: Work State: | C6: =#REF! -> #REF! | AR6: Don't edit this part; with formulas | BG6: (Handling Fees & W/C)
V7: INVOICE/ PROOF OF PAYMENT | Z7: RESIDENCY | BG7: Ineligible
B8: ITEM # | C8: Qualify? | D8: Included on PTIP Report? | E8: Amount Included on PTIP Report | F8: Work State | G8: Talent Name | H8: Title | I8: No. of Work Days | J8: Work Dates | K8: Invoice # | L8: Invoice Date | M8: Wages $ | N8: Misc Pymt/ Agent Fee | O8: ER Payroll Tax | P8: Worker's Comp | Q8: Handling | R8: SAG (P&H) $ | S8: Signatory Fee | T8: Total | U8: PTIP_Check | V8: Received_Invoice | W8: Pymt Method | X8: Payment Entity | Y8: Type | Z8: Document Type | AA8: Issue Date | AB8: Expiration Date | AC8: Home Address | AD8: City | AE8: State | AF8: Zip | AG8: NO-IL Residency Status | AH8: W-9 | AK8: Notes: | AL8: Job No. | AM8: Client Billing No. | AN8: Commercial Id | AO8: Commercial Title | AP8: CPA Tab | AR8: Talent Name | AS8: Title | AT8: Home Address | AU8: City | AV8: Zip | AW8: No. of Work Days | AX8: GROSS | AY8: PAYROLL TAXES | AZ8: BENEFITS (P, H & W) | BA8: CPA TOTAL | BC8: Invoice # | BD8: Work Dates
AX9: =M9+N9 -> 0 | AY9: =O9 -> 0 | AZ9: =R9 -> 0 | BA9: =SUM(AX9:AZ9) -> 0 | BG9: =T9-BA9 -> 0 | BH9: =BG9-Q9-P9 -> 0
B10: 1 | M10: 0 | N10: 0 | O10: 0 | P10: 0 | Q10: 0 | R10: 0 | S10: 0 | T10: =SUM(M10:S10) -> 0 | U10: =E10-T10 -> 0 | AR10: =G10 -> 0 | AS10: =H10 -> 0 | AT10: =I10 -> 0 | AU10: =AD10 -> 0 | AV10: =AF10 -> 0 | AW10: =I10 -> 0 | AX10: =M10+N10 -> 0 | AY10: =O10 -> 0 | AZ10: =R10 -> 0 | BA10: =SUM(AX10:AZ10) -> 0 | BC10: =K10 -> 0 | BD10: =J10 -> 0 | BE10: =BA10-T10+Q10+P10 -> 0 | BG10: =T10-BA10 -> 0 | BH10: =BG10-Q10-P10 -> 0
B11: 2 | M11: 0 | N11: 0 | O11: 0 | P11: 0 | Q11: 0 | R11: 0 | S11: 0 | T11: =SUM(M11:S11) -> 0 | U11: =E11-T11 -> 0 | AR11: =G11 -> 0 | AS11: =H11 -> 0 | AT11: =I11 -> 0 | AU11: =AD11 -> 0 | AV11: =AF11 -> 0 | AW11: =I11 -> 0 | AX11: =M11+N11 -> 0 | AY11: =O11 -> 0 | AZ11: =R11 -> 0 | BA11: =SUM(AX11:AZ11) -> 0 | BC11: =K11 -> 0 | BD11: =J11 -> 0 | BE11: =BA11-T11+Q11+P11 -> 0 | BG11: =T11-BA11 -> 0 | BH11: =BG11-Q11-P11 -> 0
B12: 3 | M12: 0 | N12: 0 | O12: 0 | P12: 0 | Q12: 0 | R12: 0 | S12: 0 | T12: =SUM(M12:S12) -> 0 | U12: =E12-T12 -> 0 | AR12: =G12 -> 0 | AS12: =H12 -> 0 | AT12: =I12 -> 0 | AU12: =AD12 -> 0 | AV12: =AF12 -> 0 | AW12: =I12 -> 0 | AX12: =M12+N12 -> 0 | AY12: =O12 -> 0 | AZ12: =R12 -> 0 | BA12: =SUM(AX12:AZ12) -> 0 | BC12: =K12 -> 0 | BD12: =J12 -> 0 | BE12: =BA12-T12+Q12+P12 -> 0 | BG12: =T12-BA12 -> 0 | BH12: =BG12-Q12-P12 -> 0
B13: 4 | M13: 0 | N13: 0 | O13: 0 | P13: 0 | Q13: 0 | R13: 0 | S13: 0 | T13: =SUM(M13:S13) -> 0 | U13: =E13-T13 -> 0 | AR13: =G13 -> 0 | AS13: =H13 -> 0 | AT13: =I13 -> 0 | AU13: =AD13 -> 0 | AV13: =AF13 -> 0 | AW13: =I13 -> 0 | AX13: =M13+N13 -> 0 | AY13: =O13 -> 0 | AZ13: =R13 -> 0 | BA13: =SUM(AX13:AZ13) -> 0 | BC13: =K13 -> 0 | BD13: =J13 -> 0 | BE13: =BA13-T13+Q13+P13 -> 0 | BG13: =T13-BA13 -> 0 | BH13: =BG13-Q13-P13 -> 0
B14: 5 | M14: 0 | N14: 0 | O14: 0 | P14: 0 | Q14: 0 | R14: 0 | S14: 0 | T14: =SUM(M14:S14) -> 0 | U14: =E14-T14 -> 0 | AR14: =G14 -> 0 | AS14: =H14 -> 0 | AT14: =I14 -> 0 | AU14: =AD14 -> 0 | AV14: =AF14 -> 0 | AW14: =I14 -> 0 | AX14: =M14+N14 -> 0 | AY14: =O14 -> 0 | AZ14: =R14 -> 0 | BA14: =SUM(AX14:AZ14) -> 0 | BC14: =K14 -> 0 | BD14: =J14 -> 0 | BE14: =BA14-T14+Q14+P14 -> 0 | BG14: =T14-BA14 -> 0 | BH14: =BG14-Q14-P14 -> 0
B15: 6 | M15: 0 | N15: 0 | O15: 0 | P15: 0 | Q15: 0 | R15: 0 | S15: 0 | T15: =SUM(M15:S15) -> 0 | U15: =E15-T15 -> 0 | AR15: =G15 -> 0 | AS15: =H15 -> 0 | AT15: =I15 -> 0 | AU15: =AD15 -> 0 | AV15: =AF15 -> 0 | AW15: =I15 -> 0 | AX15: =M15+N15 -> 0 | AY15: =O15 -> 0 | AZ15: =R15 -> 0 | BA15: =SUM(AX15:AZ15) -> 0 | BC15: =K15 -> 0 | BD15: =J15 -> 0 | BE15: =BA15-T15+Q15+P15 -> 0 | BG15: =T15-BA15 -> 0 | BH15: =BG15-Q15-P15 -> 0
B16: 7 | M16: 0 | N16: 0 | O16: 0 | P16: 0 | Q16: 0 | R16: 0 | S16: 0 | T16: =SUM(M16:S16) -> 0 | U16: =E16-T16 -> 0 | AR16: =G16 -> 0 | AS16: =H16 -> 0 | AT16: =I16 -> 0 | AU16: =AD16 -> 0 | AV16: =AF16 -> 0 | AW16: =I16 -> 0 | AX16: =M16+N16 -> 0 | AY16: =O16 -> 0 | AZ16: =R16 -> 0 | BA16: =SUM(AX16:AZ16) -> 0 | BC16: =K16 -> 0 | BD16: =J16 -> 0 | BE16: =BA16-T16+Q16+P16 -> 0 | BG16: =T16-BA16 -> 0 | BH16: =BG16-Q16-P16 -> 0
B17: 8 | M17: 0 | N17: 0 | O17: 0 | P17: 0 | Q17: 0 | R17: 0 | S17: 0 | T17: =SUM(M17:S17) -> 0 | U17: =E17-T17 -> 0 | AR17: =G17 -> 0 | AS17: =H17 -> 0 | AT17: =I17 -> 0 | AU17: =AD17 -> 0 | AV17: =AF17 -> 0 | AW17: =I17 -> 0 | AX17: =M17+N17 -> 0 | AY17: =O17 -> 0 | AZ17: =R17 -> 0 | BA17: =SUM(AX17:AZ17) -> 0 | BC17: =K17 -> 0 | BD17: =J17 -> 0 | BE17: =BA17-T17+Q17+P17 -> 0 | BG17: =T17-BA17 -> 0 | BH17: =BG17-Q17-P17 -> 0
B18: 9 | M18: 0 | N18: 0 | O18: 0 | P18: 0 | Q18: 0 | R18: 0 | S18: 0 | T18: =SUM(M18:S18) -> 0 | U18: =E18-T18 -> 0 | AR18: =G18 -> 0 | AS18: =H18 -> 0 | AT18: =I18 -> 0 | AU18: =AD18 -> 0 | AV18: =AF18 -> 0 | AW18: =I18 -> 0 | AX18: =M18+N18 -> 0 | AY18: =O18 -> 0 | AZ18: =R18 -> 0 | BA18: =SUM(AX18:AZ18) -> 0 | BC18: =K18 -> 0 | BD18: =J18 -> 0 | BE18: =BA18-T18+Q18+P18 -> 0 | BG18: =T18-BA18 -> 0 | BH18: =BG18-Q18-P18 -> 0
B19: 10 | M19: 0 | N19: 0 | O19: 0 | P19: 0 | Q19: 0 | R19: 0 | S19: 0 | T19: =SUM(M19:S19) -> 0 | U19: =E19-T19 -> 0 | AR19: =G19 -> 0 | AS19: =H19 -> 0 | AT19: =I19 -> 0 | AU19: =AD19 -> 0 | AV19: =AF19 -> 0 | AW19: =I19 -> 0 | AX19: =M19+N19 -> 0 | AY19: =O19 -> 0 | AZ19: =R19 -> 0 | BA19: =SUM(AX19:AZ19) -> 0 | BC19: =K19 -> 0 | BD19: =J19 -> 0 | BE19: =BA19-T19+Q19+P19 -> 0 | BG19: =T19-BA19 -> 0 | BH19: =BG19-Q19-P19 -> 0
B20: 11 | M20: 0 | N20: 0 | O20: 0 | P20: 0 | Q20: 0 | R20: 0 | S20: 0 | T20: =SUM(M20:S20) -> 0 | U20: =E20-T20 -> 0 | AR20: =G20 -> 0 | AS20: =H20 -> 0 | AT20: =I20 -> 0 | AU20: =AD20 -> 0 | AV20: =AF20 -> 0 | AW20: =I20 -> 0 | AX20: =M20+N20 -> 0 | AY20: =O20 -> 0 | AZ20: =R20 -> 0 | BA20: =SUM(AX20:AZ20) -> 0 | BC20: =K20 -> 0 | BD20: =J20 -> 0 | BE20: =BA20-T20+Q20+P20 -> 0 | BG20: =T20-BA20 -> 0 | BH20: =BG20-Q20-P20 -> 0
B21: 12 | M21: 0 | N21: 0 | O21: 0 | P21: 0 | Q21: 0 | R21: 0 | S21: 0 | T21: =SUM(M21:S21) -> 0 | U21: =E21-T21 -> 0 | AR21: =G21 -> 0 | AS21: =H21 -> 0 | AT21: =I21 -> 0 | AU21: =AD21 -> 0 | AV21: =AF21 -> 0 | AW21: =I21 -> 0 | AX21: =M21+N21 -> 0 | AY21: =O21 -> 0 | AZ21: =R21 -> 0 | BA21: =SUM(AX21:AZ21) -> 0 | BC21: =K21 -> 0 | BD21: =J21 -> 0 | BE21: =BA21-T21+Q21+P21 -> 0 | BG21: =T21-BA21 -> 0 | BH21: =BG21-Q21-P21 -> 0
... B58: 49 | M58: 0 | N58: 0 | O58: 0 | P58: 0 | Q58: 0 | R58: 0 | S58: 0 | T58: =SUM(M58:S58) -> 0 | U58: =E58-T58 -> 0 | AR58: =G58 -> 0 | AS58: =H58 -> 0 | AT58: =I58 -> 0 | AU58: =AD58 -> 0 | AV58: =AF58 -> 0 | AW58: =I58 -> 0 | AX58: =M58+N58 -> 0 | AY58: =O58 -> 0 | AZ58: =R58 -> 0 | BA58: =SUM(AX58:AZ58) -> 0 | BC58: =K58 -> 0 | BD58: =J58 -> 0 | BE58: =BA58-T58+Q58+P58 -> 0 | BG58: =T58-BA58 -> 0 | BH58: =BG58-Q58-P58 -> 0
AR59: =G59 -> 0 | AS59: =H59 -> 0 | AT59: =I59 -> 0 | AU59: =AD59 -> 0 | AV59: =AF59 -> 0 | AW59: =I59 -> 0 | AX59: =M59+N59 -> 0 | AY59: =O59 -> 0 | AZ59: =R59 -> 0 | BA59: =SUM(AX59:AZ59) -> 0 | BE59: =BA59-T59+Q59+P59 -> 0 | BG59: =T59-BA59 -> 0 | BH59: =BG59-Q59-P59 -> 0
C60: x | D60: x | E60: x | M60: =SUBTOTAL(9,M9:M59) -> 0 | N60: =SUBTOTAL(9,N9:N59) -> 0 | O60: =SUBTOTAL(9,O9:O59) -> 0 | P60: =SUBTOTAL(9,P9:P59) -> 0 | Q60: =SUBTOTAL(9,Q9:Q59) -> 0 | R60: =SUBTOTAL(9,R9:R59) -> 0 | S60: =SUBTOTAL(9,S9:S59) -> 0 | T60: =SUBTOTAL(9,T9:T59) -> 0 | V60: x | W60: x | X60: x | Y60: x | Z60: x | AA60: x | AB60: x | AC60: x | AD60: x | AE60: x | AF60: x | AG60: x | AK60: x | AL60: x | AM60: x | AN60: x | AO60: x | AX60: =SUBTOTAL(9,AX9:AX59) -> 0 | AY60: =SUBTOTAL(9,AY9:AY59) -> 0 | AZ60: =SUBTOTAL(9,AZ9:AZ59) -> 0 | BA60: =SUBTOTAL(9,BA9:BA59) -> 0 | BE60: =BA60-T60+Q60+P60 -> 0 | BG60: =SUM(BG9:BG59) -> 0 | BH60: =BG60-Q60-P60 -> 0
M63: =SUM(M9:M59) -> 0 | N63: =SUM(N9:N59) -> 0 | O63: =SUM(O9:O59) -> 0 | P63: =SUM(P9:P59) -> 0 | Q63: =SUM(Q9:Q59) -> 0 | R63: =SUM(R9:R59) -> 0 | S63: =SUM(S9:S59) -> 0 | T63: =SUM(T9:T59) -> 0 | AZ63: =SUM(AX9:AX59) -> 0 | BA63: =SUM(AY9:AY59) -> 0 | BE63: =SUM(AZ9:AZ59) -> 0 | BF63: =SUM(BA9:BA59) -> 0 | BG63: =BF63-T63+Q63+P63 -> 0 | BI63: =SUM(BG9:BG59) -> 0 | BJ63: =BI63-Q63-P63 -> 0
M67: ELIGIBLE TOTAL
B68: CPA Tab | C68: Total | D68: YES | E68: YES-OOS | F68: YES-AGENCY FEE | G68: Pending | H68: DNQ | M68: PENDING | N68: YES-AGENCY FEE | O68: NO-OOS | P68: NO-IL | Q68: YES | R68: YES-OOS
B69: Talent | C69: =SUMIFS($T$9:$T$59,$AP$9:$AP$59,$B69) -> 0 | D69: =SUMIFS($BA$9:$BA$59,$AP$9:$AP$59,$B69,$C$9:$C$59,D$68) -> 0 | E69: =SUMIFS($BA$9:$BA$59,$AP$9:$AP$59,$B69,$C$9:$C$59,E$68) -> 0 | F69: =SUMIFS($BA$9:$BA$59,$AP$9:$AP$59,$B69,$C$9:$C$59,F$68) -> 0 | G69: =SUMIFS($BA$9:$BA$59,$AP$9:$AP$59,$B69,$C$9:$C$59,G$68) -> 0 | H69: =C69-(D69+E69+F69+G69) -> 0 | M69: =SUMIF($C$9:$C$59,M68,$BA$9:$BA$59) -> 0 | N69: =SUMIF($C$9:$C$59,N68,$BA$9:$BA$59) -> 0 | O69: =SUMIF($C$9:$C$59,O68,$BA$9:$BA$59) -> 0 | P69: =SUMIF($C$9:$C$59,P68,$BA$9:$BA$59) -> 0 | Q69: =SUMIF($C$9:$C$59,Q68,$BA$9:$BA$59) -> 0 | R69: =SUMIF($C$9:$C$59,R68,$BA$9:$BA$59) -> 0 | T69: =SUM(M69:R69) -> 0
B70: Extra | C70: =SUMIFS($T$9:$T$59,$AP$9:$AP$59,$B70) -> 0 | D70: =SUMIFS($BA$9:$BA$59,$AP$9:$AP$59,$B70,$C$9:$C$59,D$68) -> 0 | E70: =SUMIFS($BA$9:$BA$59,$AP$9:$AP$59,$B70,$C$9:$C$59,E$68) -> 0 | F70: =SUMIFS($BA$9:$BA$59,$AP$9:$AP$59,$B70,$C$9:$C$59,F$68) -> 0 | G70: =SUMIFS($BA$9:$BA$59,$AP$9:$AP$59,$B70,$C$9:$C$59,G$68) -> 0 | H70: =C70-(D70+E70+F70+G70) -> 0 | T70: =T69-BF63 -> 0
B71: Vendor | C71: =SUMIFS($T$9:$T$59,$AP$9:$AP$59,$B71) -> 0 | D71: =SUMIFS($BA$9:$BA$59,$AP$9:$AP$59,$B71,$C$9:$C$59,D$68) -> 0 | E71: =SUMIFS($BA$9:$BA$59,$AP$9:$AP$59,$B71,$C$9:$C$59,E$68) -> 0 | F71: =SUMIFS($BA$9:$BA$59,$AP$9:$AP$59,$B71,$C$9:$C$59,F$68) -> 0 | G71: =SUMIFS($BA$9:$BA$59,$AP$9:$AP$59,$B71,$C$9:$C$59,G$68) -> 0 | H71: =C71-(D71+E71+F71+G71) -> 0
C72: =SUBTOTAL(9,C69:C71) -> 0 | D72: =SUBTOTAL(9,D69:D71) -> 0 | E72: =SUM(E69:E71) -> 0 | F72: =SUM(F69:F71) -> 0 | G72: =SUM(G69:G71) -> 0 | H72: =C72-(D72+E72+F72+G72) -> 0 | I72: =C72-SUM(D72:H72) -> 0 | M72: INELIGIBLE TOTAL
C73: =C72-T63 -> 0 | D73: =D72-Q69 -> 0 | E73: =E72-R69 -> 0 | F73: =F72-N69 -> 0 | G73: =G72-M69 -> 0 | H73: =H72-(T74+P69+O69) -> 0 | M73: PENDING | N73: YES-AGENCY FEE | O73: NO-OOS | P73: NO-IL | Q73: YES | R73: YES-OOS
M74: =SUMIF($C$9:$C$59,M$73,$BG$9:$BG$59) -> 0 | N74: =SUMIF($C$9:$C$59,N$73,$BG$9:$BG$59) -> 0 | O74: =SUMIF($C$9:$C$59,O$73,$BG$9:$BG$59) -> 0 | P74: =SUMIF($C$9:$C$59,P$73,$BG$9:$BG$59) -> 0 | Q74: =SUMIF($C$9:$C$59,Q$73,$BG$9:$BG$59) -> 0 | R74: =SUMIF($C$9:$C$59,R$73,$BG$9:$BG$59) -> 0 | T74: =SUM(M74:R74) -> 0
M75: =SUMIF($C$9:$C$59,M$73,$Q$9:$Q$59) -> 0 | N75: =SUMIF($C$9:$C$59,N$73,$Q$9:$Q$59) -> 0 | O75: =SUMIF($C$9:$C$59,O$73,$Q$9:$Q$59) -> 0 | P75: =SUMIF($C$9:$C$59,P$73,$Q$9:$Q$59) -> 0 | Q75: =SUMIF($C$9:$C$59,Q$73,$Q$9:$Q$59) -> 0 | R75: =SUMIF($C$9:$C$59,R$73,$Q$9:$Q$59) -> 0 | T75: =SUM(M75:R75) -> 0 | V75: =T75-Q60 -> 0
O78: Handling Fee
N80: Total | O80: Qualifed | P80: Ineligible
M81: Total Eligible | N81: =Q69+R69 -> 0
M82: Total Pending | N82: =M69 -> 0
M83: Total Ineligible | N83: =O69+P69+O74+P74+Q74+R74+N74+M74-N85 -> 0
M84: Total Agency Fees | N84: =N69 -> 0 | O84: =F72 -> 0 | P84: =N84-O84 -> 0 | R84: (For CPA Use only) | Y84: =N86-T63 -> 0
M85: Total Handling Fees | N85: =Q63 -> 0 | O85: =AF108 -> 0 | P85: =AG108 -> 0
M86: Total Expenses | N86: =SUM(N81:N85) -> 0
N87: =N86-T63 -> 0
AK88: Client Billings
N89: Job No. | O89: Client Billing No. | P89: Invoice No. | Q89: Invoice Amount | R89: Qualified Amount | T89: Pending Amount | U89: Ineligible Amount | V89: Handling Fees | X89: Qualified Wages/Misc | Y89: Qualified Taxes | Z89: Qualified Benefits | AD89: CPA Qualified | AE89: CPA DNQ | AF89: CPA Handling | AG89: CPA DNQ Handling | AK89: Invoice | AL89: Talent Sessions | AM89: Artists Taxes | AN89: Handling & Fulfillment | AO89: SAG
N90: =_xlfn.XLOOKUP($P90,$K$9:$K$59,AL$9:AL$59) -> #N/A | O90: =_xlfn.XLOOKUP($P90,$K$9:$K$59,AM$9:AM$59) -> #N/A | P90: 1 | Q90: =SUMIF($K$9:$K$59,P90,$T$9:$T$59) -> 0 | R90: =SUMIFS($BA$9:$BA$59,$K$9:$K$59,P90,$C$9:$C$59,"YES")+SUMIFS($BA$9:$BA$59,$K$9:$K$59,P90,$C$9:$C$59,"YES-OOS") -> 0 | T90: =SUMIFS($BA$9:$BA$59,$K$9:$K$59,P90,$C$9:$C$59,"PENDING") -> 0 | U90: =Q90-(R90+T90) -> 0 | V90: =SUMIF($K$9:$K$59,P90,$Q$9:$Q$59) -> 0 | X90: =SUM(SUMIFS($M$9:$M$59,$K$9:$K$59,$P90,$C$9:$C$59,"YES"), SUMIFS($N$9:$N$59,$K$9:$K$59,$P90,$C$9:$C$59,"YES"))+SUM(SUMIFS($M$9:$M$59,$K$9:$K$59,$P90,$C$9:$C$59,"YES-OOS"), SUMIFS($N$9:$N$59,$K$9:$K$59,$P90,$C$9:$C$59,"YES-OOS")) -> 0 | Y90: =SUMIFS($O$9:$O$59,$K$9:$K$59,$P90,$C$9:$C$59,"YES")+SUMIFS($O$9:$O$59,$K$9:$K$59,$P90,$C$9:$C$59,"YES-OOS") -> 0 | Z90: =SUMIFS($R$9:$R$59,$K$9:$K$59,P90,$C$9:$C$59,"YES")+SUMIFS($R$9:$R$59,$K$9:$K$59,P90,$C$9:$C$59,"YES-OOS") -> 0 | AA90: =R90-(X90+Y90+Z90) -> 0 | AD90: =IF(R90<>0,Q90,0) -> 0 | AE90: =IF(R90<>0,0,Q90) -> 0 | AF90: =IF(R90<>0,V90,0) -> 0 | AG90: =IF(R90<>0,0,V90) -> 0 | AH90: =(Q90+V90)-(AD90+AE90+AF90+AG90) -> 0 | AK90: =P90 -> 1 | AL90: =SUMIFS($M$9:$M$59,$K$9:$K$59,$P90)+SUMIFS($N$9:$N$59,$K$9:$K$59,$P90) -> 0 | AM90: =SUMIFS($O$9:$O$59,$K$9:$K$59,$P90)+SUMIFS($P$9:$P$59,$K$9:$K$59,$P90) -> 0 | AN90: =SUMIFS($Q$9:$Q$59,$K$9:$K$59,$P90) -> 0 | AO90: =SUMIFS($R$9:$R$59,$K$9:$K$59,$P90) -> 0 | AP90: =Q90-SUM(AL90:AO90) -> 0
N91: =_xlfn.XLOOKUP($P91,$K$9:$K$59,AL$9:AL$59) -> #N/A | O91: =_xlfn.XLOOKUP($P91,$K$9:$K$59,AM$9:AM$59) -> #N/A | P91: 2 | Q91: =SUMIF($K$9:$K$59,P91,$T$9:$T$59) -> 0 | R91: =SUMIFS($BA$9:$BA$59,$K$9:$K$59,P91,$C$9:$C$59,"YES")+SUMIFS($BA$9:$BA$59,$K$9:$K$59,P91,$C$9:$C$59,"YES-OOS") -> 0 | T91: =SUMIFS($BA$9:$BA$59,$K$9:$K$59,P91,$C$9:$C$59,"PENDING") -> 0 | U91: =Q91-(R91+T91) -> 0 | V91: =SUMIF($K$9:$K$59,P91,$Q$9:$Q$59) -> 0 | X91: =SUM(SUMIFS($M$9:$M$59,$K$9:$K$59,$P91,$C$9:$C$59,"YES"), SUMIFS($N$9:$N$59,$K$9:$K$59,$P91,$C$9:$C$59,"YES"))+SUM(SUMIFS($M$9:$M$59,$K$9:$K$59,$P91,$C$9:$C$59,"YES-OOS"), SUMIFS($N$9:$N$59,$K$9:$K$59,$P91,$C$9:$C$59,"YES-OOS")) -> 0 | Y91: =SUMIFS($O$9:$O$59,$K$9:$K$59,$P91,$C$9:$C$59,"YES")+SUMIFS($O$9:$O$59,$K$9:$K$59,$P91,$C$9:$C$59,"YES-OOS") -> 0 | Z91: =SUMIFS($R$9:$R$59,$K$9:$K$59,P91,$C$9:$C$59,"YES")+SUMIFS($R$9:$R$59,$K$9:$K$59,P91,$C$9:$C$59,"YES-OOS") -> 0 | AA91: =R91-(X91+Y91+Z91) -> 0 | AD91: =IF(R91<>0,Q91,0) -> 0 | AE91: =IF(R91<>0,0,Q91) -> 0 | AF91: =IF(R91<>0,V91,0) -> 0 | AG91: =IF(R91<>0,0,V91) -> 0 | AH91: =(Q91+V91)-(AD91+AE91+AF91+AG91) -> 0 | AK91: =P91 -> 2 | AL91: =SUMIFS($M$9:$M$59,$K$9:$K$59,$P91)+SUMIFS($N$9:$N$59,$K$9:$K$59,$P91) -> 0 | AM91: =SUMIFS($O$9:$O$59,$K$9:$K$59,$P91)+SUMIFS($P$9:$P$59,$K$9:$K$59,$P91) -> 0 | AN91: =SUMIFS($Q$9:$Q$59,$K$9:$K$59,$P91) -> 0 | AO91: =SUMIFS($R$9:$R$59,$K$9:$K$59,$P91) -> 0 | AP91: =Q91-SUM(AL91:AO91) -> 0
N92: =_xlfn.XLOOKUP($P92,$K$9:$K$59,AL$9:AL$59) -> 0 | O92: =_xlfn.XLOOKUP($P92,$K$9:$K$59,AM$9:AM$59) -> 0 | Q92: =SUMIF($K$9:$K$59,P92,$T$9:$T$59) -> 0 | R92: =SUMIFS($BA$9:$BA$59,$K$9:$K$59,P92,$C$9:$C$59,"YES")+SUMIFS($BA$9:$BA$59,$K$9:$K$59,P92,$C$9:$C$59,"YES-OOS") -> 0 | T92: =SUMIFS($BA$9:$BA$59,$K$9:$K$59,P92,$C$9:$C$59,"PENDING") -> 0 | U92: =Q92-(R92+T92) -> 0 | V92: =SUMIF($K$9:$K$59,P92,$Q$9:$Q$59) -> 0 | X92: =SUM(SUMIFS($M$9:$M$59,$K$9:$K$59,$P92,$C$9:$C$59,"YES"), SUMIFS($N$9:$N$59,$K$9:$K$59,$P92,$C$9:$C$59,"YES"))+SUM(SUMIFS($M$9:$M$59,$K$9:$K$59,$P92,$C$9:$C$59,"YES-OOS"), SUMIFS($N$9:$N$59,$K$9:$K$59,$P92,$C$9:$C$59,"YES-OOS")) -> 0 | Y92: =SUMIFS($O$9:$O$59,$K$9:$K$59,$P92,$C$9:$C$59,"YES")+SUMIFS($O$9:$O$59,$K$9:$K$59,$P92,$C$9:$C$59,"YES-OOS") -> 0 | Z92: =SUMIFS($R$9:$R$59,$K$9:$K$59,P92,$C$9:$C$59,"YES")+SUMIFS($R$9:$R$59,$K$9:$K$59,P92,$C$9:$C$59,"YES-OOS") -> 0 | AA92: =R92-(X92+Y92+Z92) -> 0 | AD92: =IF(R92<>0,Q92,0) -> 0 | AE92: =IF(R92<>0,0,Q92) -> 0 | AF92: =IF(R92<>0,V92,0) -> 0 | AG92: =IF(R92<>0,0,V92) -> 0 | AH92: =(Q92+V92)-(AD92+AE92+AF92+AG92) -> 0 | AK92: =P92 -> 0 | AL92: =SUMIFS($M$9:$M$59,$K$9:$K$59,$P92)+SUMIFS($N$9:$N$59,$K$9:$K$59,$P92) -> 0 | AM92: =SUMIFS($O$9:$O$59,$K$9:$K$59,$P92)+SUMIFS($P$9:$P$59,$K$9:$K$59,$P92) -> 0 | AN92: =SUMIFS($Q$9:$Q$59,$K$9:$K$59,$P92) -> 0 | AO92: =SUMIFS($R$9:$R$59,$K$9:$K$59,$P92) -> 0 | AP92: =Q92-SUM(AL92:AO92) -> 0
N93: =_xlfn.XLOOKUP($P93,$K$9:$K$59,AL$9:AL$59) -> 0 | O93: =_xlfn.XLOOKUP($P93,$K$9:$K$59,AM$9:AM$59) -> 0 | Q93: =SUMIF($K$9:$K$59,P93,$T$9:$T$59) -> 0 | R93: =SUMIFS($BA$9:$BA$59,$K$9:$K$59,P93,$C$9:$C$59,"YES")+SUMIFS($BA$9:$BA$59,$K$9:$K$59,P93,$C$9:$C$59,"YES-OOS") -> 0 | T93: =SUMIFS($BA$9:$BA$59,$K$9:$K$59,P93,$C$9:$C$59,"PENDING") -> 0 | U93: =Q93-(R93+T93) -> 0 | V93: =SUMIF($K$9:$K$59,P93,$Q$9:$Q$59) -> 0 | X93: =SUM(SUMIFS($M$9:$M$59,$K$9:$K$59,$P93,$C$9:$C$59,"YES"), SUMIFS($N$9:$N$59,$K$9:$K$59,$P93,$C$9:$C$59,"YES"))+SUM(SUMIFS($M$9:$M$59,$K$9:$K$59,$P93,$C$9:$C$59,"YES-OOS"), SUMIFS($N$9:$N$59,$K$9:$K$59,$P93,$C$9:$C$59,"YES-OOS")) -> 0 | Y93: =SUMIFS($O$9:$O$59,$K$9:$K$59,$P93,$C$9:$C$59,"YES")+SUMIFS($O$9:$O$59,$K$9:$K$59,$P93,$C$9:$C$59,"YES-OOS") -> 0 | Z93: =SUMIFS($R$9:$R$59,$K$9:$K$59,P93,$C$9:$C$59,"YES")+SUMIFS($R$9:$R$59,$K$9:$K$59,P93,$C$9:$C$59,"YES-OOS") -> 0 | AA93: =R93-(X93+Y93+Z93) -> 0 | AD93: =IF(R93<>0,Q93,0) -> 0 | AE93: =IF(R93<>0,0,Q93) -> 0 | AF93: =IF(R93<>0,V93,0) -> 0 | AG93: =IF(R93<>0,0,V93) -> 0 | AH93: =(Q93+V93)-(AD93+AE93+AF93+AG93) -> 0 | AK93: =P93 -> 0 | AL93: =SUMIFS($M$9:$M$59,$K$9:$K$59,$P93)+SUMIFS($N$9:$N$59,$K$9:$K$59,$P93) -> 0 | AM93: =SUMIFS($O$9:$O$59,$K$9:$K$59,$P93)+SUMIFS($P$9:$P$59,$K$9:$K$59,$P93) -> 0 | AN93: =SUMIFS($Q$9:$Q$59,$K$9:$K$59,$P93) -> 0 | AO93: =SUMIFS($R$9:$R$59,$K$9:$K$59,$P93) -> 0 | AP93: =Q93-SUM(AL93:AO93) -> 0
N94: =_xlfn.XLOOKUP($P94,$K$9:$K$59,AL$9:AL$59) -> 0 | O94: =_xlfn.XLOOKUP($P94,$K$9:$K$59,AM$9:AM$59) -> 0 | Q94: =SUMIF($K$9:$K$59,P94,$T$9:$T$59) -> 0 | R94: =SUMIFS($BA$9:$BA$59,$K$9:$K$59,P94,$C$9:$C$59,"YES")+SUMIFS($BA$9:$BA$59,$K$9:$K$59,P94,$C$9:$C$59,"YES-OOS") -> 0 | T94: =SUMIFS($BA$9:$BA$59,$K$9:$K$59,P94,$C$9:$C$59,"PENDING") -> 0 | U94: =Q94-(R94+T94) -> 0 | V94: =SUMIF($K$9:$K$59,P94,$Q$9:$Q$59) -> 0 | X94: =SUM(SUMIFS($M$9:$M$59,$K$9:$K$59,$P94,$C$9:$C$59,"YES"), SUMIFS($N$9:$N$59,$K$9:$K$59,$P94,$C$9:$C$59,"YES"))+SUM(SUMIFS($M$9:$M$59,$K$9:$K$59,$P94,$C$9:$C$59,"YES-OOS"), SUMIFS($N$9:$N$59,$K$9:$K$59,$P94,$C$9:$C$59,"YES-OOS")) -> 0 | Y94: =SUMIFS($O$9:$O$59,$K$9:$K$59,$P94,$C$9:$C$59,"YES")+SUMIFS($O$9:$O$59,$K$9:$K$59,$P94,$C$9:$C$59,"YES-OOS") -> 0 | Z94: =SUMIFS($R$9:$R$59,$K$9:$K$59,P94,$C$9:$C$59,"YES")+SUMIFS($R$9:$R$59,$K$9:$K$59,P94,$C$9:$C$59,"YES-OOS") -> 0 | AA94: =R94-(X94+Y94+Z94) -> 0 | AD94: =IF(R94<>0,Q94,0) -> 0 | AE94: =IF(R94<>0,0,Q94) -> 0 | AF94: =IF(R94<>0,V94,0) -> 0 | AG94: =IF(R94<>0,0,V94) -> 0 | AH94: =(Q94+V94)-(AD94+AE94+AF94+AG94) -> 0 | AK94: =P94 -> 0 | AL94: =SUMIFS($M$9:$M$59,$K$9:$K$59,$P94)+SUMIFS($N$9:$N$59,$K$9:$K$59,$P94) -> 0 | AM94: =SUMIFS($O$9:$O$59,$K$9:$K$59,$P94)+SUMIFS($P$9:$P$59,$K$9:$K$59,$P94) -> 0 | AN94: =SUMIFS($Q$9:$Q$59,$K$9:$K$59,$P94) -> 0 | AO94: =SUMIFS($R$9:$R$59,$K$9:$K$59,$P94) -> 0 | AP94: =Q94-SUM(AL94:AO94) -> 0
N95: =_xlfn.XLOOKUP($P95,$K$9:$K$59,AL$9:AL$59) -> 0 | O95: =_xlfn.XLOOKUP($P95,$K$9:$K$59,AM$9:AM$59) -> 0 | Q95: =SUMIF($K$9:$K$59,P95,$T$9:$T$59) -> 0 | R95: =SUMIFS($BA$9:$BA$59,$K$9:$K$59,P95,$C$9:$C$59,"YES")+SUMIFS($BA$9:$BA$59,$K$9:$K$59,P95,$C$9:$C$59,"YES-OOS") -> 0 | T95: =SUMIFS($BA$9:$BA$59,$K$9:$K$59,P95,$C$9:$C$59,"PENDING") -> 0 | U95: =Q95-(R95+T95) -> 0 | V95: =SUMIF($K$9:$K$59,P95,$Q$9:$Q$59) -> 0 | X95: =SUM(SUMIFS($M$9:$M$59,$K$9:$K$59,$P95,$C$9:$C$59,"YES"), SUMIFS($N$9:$N$59,$K$9:$K$59,$P95,$C$9:$C$59,"YES"))+SUM(SUMIFS($M$9:$M$59,$K$9:$K$59,$P95,$C$9:$C$59,"YES-OOS"), SUMIFS($N$9:$N$59,$K$9:$K$59,$P95,$C$9:$C$59,"YES-OOS")) -> 0 | Y95: =SUMIFS($O$9:$O$59,$K$9:$K$59,$P95,$C$9:$C$59,"YES")+SUMIFS($O$9:$O$59,$K$9:$K$59,$P95,$C$9:$C$59,"YES-OOS") -> 0 | Z95: =SUMIFS($R$9:$R$59,$K$9:$K$59,P95,$C$9:$C$59,"YES")+SUMIFS($R$9:$R$59,$K$9:$K$59,P95,$C$9:$C$59,"YES-OOS") -> 0 | AA95: =R95-(X95+Y95+Z95) -> 0 | AD95: =IF(R95<>0,Q95,0) -> 0 | AE95: =IF(R95<>0,0,Q95) -> 0 | AF95: =IF(R95<>0,V95,0) -> 0 | AG95: =IF(R95<>0,0,V95) -> 0 | AH95: =(Q95+V95)-(AD95+AE95+AF95+AG95) -> 0 | AK95: =P95 -> 0 | AL95: =SUMIFS($M$9:$M$59,$K$9:$K$59,$P95)+SUMIFS($N$9:$N$59,$K$9:$K$59,$P95) -> 0 | AM95: =SUMIFS($O$9:$O$59,$K$9:$K$59,$P95)+SUMIFS($P$9:$P$59,$K$9:$K$59,$P95) -> 0 | AN95: =SUMIFS($Q$9:$Q$59,$K$9:$K$59,$P95) -> 0 | AO95: =SUMIFS($R$9:$R$59,$K$9:$K$59,$P95) -> 0 | AP95: =Q95-SUM(AL95:AO95) -> 0
N96: =_xlfn.XLOOKUP($P96,$K$9:$K$59,AL$9:AL$59) -> 0 | O96: =_xlfn.XLOOKUP($P96,$K$9:$K$59,AM$9:AM$59) -> 0 | Q96: =SUMIF($K$9:$K$59,P96,$T$9:$T$59) -> 0 | R96: =SUMIFS($BA$9:$BA$59,$K$9:$K$59,P96,$C$9:$C$59,"YES")+SUMIFS($BA$9:$BA$59,$K$9:$K$59,P96,$C$9:$C$59,"YES-OOS") -> 0 | T96: =SUMIFS($BA$9:$BA$59,$K$9:$K$59,P96,$C$9:$C$59,"PENDING") -> 0 | U96: =Q96-(R96+T96) -> 0 | V96: =SUMIF($K$9:$K$59,P96,$Q$9:$Q$59) -> 0 | X96: =SUM(SUMIFS($M$9:$M$59,$K$9:$K$59,$P96,$C$9:$C$59,"YES"), SUMIFS($N$9:$N$59,$K$9:$K$59,$P96,$C$9:$C$59,"YES"))+SUM(SUMIFS($M$9:$M$59,$K$9:$K$59,$P96,$C$9:$C$59,"YES-OOS"), SUMIFS($N$9:$N$59,$K$9:$K$59,$P96,$C$9:$C$59,"YES-OOS")) -> 0 | Y96: =SUMIFS($O$9:$O$59,$K$9:$K$59,$P96,$C$9:$C$59,"YES")+SUMIFS($O$9:$O$59,$K$9:$K$59,$P96,$C$9:$C$59,"YES-OOS") -> 0 | Z96: =SUMIFS($R$9:$R$59,$K$9:$K$59,P96,$C$9:$C$59,"YES")+SUMIFS($R$9:$R$59,$K$9:$K$59,P96,$C$9:$C$59,"YES-OOS") -> 0 | AA96: =R96-(X96+Y96+Z96) -> 0 | AD96: =IF(R96<>0,Q96,0) -> 0 | AE96: =IF(R96<>0,0,Q96) -> 0 | AF96: =IF(R96<>0,V96,0) -> 0 | AG96: =IF(R96<>0,0,V96) -> 0 | AH96: =(Q96+V96)-(AD96+AE96+AF96+AG96) -> 0 | AK96: =P96 -> 0 | AL96: =SUMIFS($M$9:$M$59,$K$9:$K$59,$P96)+SUMIFS($N$9:$N$59,$K$9:$K$59,$P96) -> 0 | AM96: =SUMIFS($O$9:$O$59,$K$9:$K$59,$P96)+SUMIFS($P$9:$P$59,$K$9:$K$59,$P96) -> 0 | AN96: =SUMIFS($Q$9:$Q$59,$K$9:$K$59,$P96) -> 0 | AO96: =SUMIFS($R$9:$R$59,$K$9:$K$59,$P96) -> 0 | AP96: =Q96-SUM(AL96:AO96) -> 0
N97: =_xlfn.XLOOKUP($P97,$K$9:$K$59,AL$9:AL$59) -> 0 | O97: =_xlfn.XLOOKUP($P97,$K$9:$K$59,AM$9:AM$59) -> 0 | Q97: =SUMIF($K$9:$K$59,P97,$T$9:$T$59) -> 0 | R97: =SUMIFS($BA$9:$BA$59,$K$9:$K$59,P97,$C$9:$C$59,"YES")+SUMIFS($BA$9:$BA$59,$K$9:$K$59,P97,$C$9:$C$59,"YES-OOS") -> 0 | T97: =SUMIFS($BA$9:$BA$59,$K$9:$K$59,P97,$C$9:$C$59,"PENDING") -> 0 | U97: =Q97-(R97+T97) -> 0 | V97: =SUMIF($K$9:$K$59,P97,$Q$9:$Q$59) -> 0 | X97: =SUM(SUMIFS($M$9:$M$59,$K$9:$K$59,$P97,$C$9:$C$59,"YES"), SUMIFS($N$9:$N$59,$K$9:$K$59,$P97,$C$9:$C$59,"YES"))+SUM(SUMIFS($M$9:$M$59,$K$9:$K$59,$P97,$C$9:$C$59,"YES-OOS"), SUMIFS($N$9:$N$59,$K$9:$K$59,$P97,$C$9:$C$59,"YES-OOS")) -> 0 | Y97: =SUMIFS($O$9:$O$59,$K$9:$K$59,$P97,$C$9:$C$59,"YES")+SUMIFS($O$9:$O$59,$K$9:$K$59,$P97,$C$9:$C$59,"YES-OOS") -> 0 | Z97: =SUMIFS($R$9:$R$59,$K$9:$K$59,P97,$C$9:$C$59,"YES")+SUMIFS($R$9:$R$59,$K$9:$K$59,P97,$C$9:$C$59,"YES-OOS") -> 0 | AA97: =R97-(X97+Y97+Z97) -> 0 | AD97: =IF(R97<>0,Q97,0) -> 0 | AE97: =IF(R97<>0,0,Q97) -> 0 | AF97: =IF(R97<>0,V97,0) -> 0 | AG97: =IF(R97<>0,0,V97) -> 0 | AH97: =(Q97+V97)-(AD97+AE97+AF97+AG97) -> 0 | AK97: =P97 -> 0 | AL97: =SUMIFS($M$9:$M$59,$K$9:$K$59,$P97)+SUMIFS($N$9:$N$59,$K$9:$K$59,$P97) -> 0 | AM97: =SUMIFS($O$9:$O$59,$K$9:$K$59,$P97)+SUMIFS($P$9:$P$59,$K$9:$K$59,$P97) -> 0 | AN97: =SUMIFS($Q$9:$Q$59,$K$9:$K$59,$P97) -> 0 | AO97: =SUMIFS($R$9:$R$59,$K$9:$K$59,$P97) -> 0 | AP97: =Q97-SUM(AL97:AO97) -> 0
N98: =_xlfn.XLOOKUP($P98,$K$9:$K$59,AL$9:AL$59) -> 0 | O98: =_xlfn.XLOOKUP($P98,$K$9:$K$59,AM$9:AM$59) -> 0 | Q98: =SUMIF($K$9:$K$59,P98,$T$9:$T$59) -> 0 | R98: =SUMIFS($BA$9:$BA$59,$K$9:$K$59,P98,$C$9:$C$59,"YES")+SUMIFS($BA$9:$BA$59,$K$9:$K$59,P98,$C$9:$C$59,"YES-OOS") -> 0 | T98: =SUMIFS($BA$9:$BA$59,$K$9:$K$59,P98,$C$9:$C$59,"PENDING") -> 0 | U98: =Q98-(R98+T98) -> 0 | V98: =SUMIF($K$9:$K$59,P98,$Q$9:$Q$59) -> 0 | X98: =SUM(SUMIFS($M$9:$M$59,$K$9:$K$59,$P98,$C$9:$C$59,"YES"), SUMIFS($N$9:$N$59,$K$9:$K$59,$P98,$C$9:$C$59,"YES"))+SUM(SUMIFS($M$9:$M$59,$K$9:$K$59,$P98,$C$9:$C$59,"YES-OOS"), SUMIFS($N$9:$N$59,$K$9:$K$59,$P98,$C$9:$C$59,"YES-OOS")) -> 0 | Y98: =SUMIFS($O$9:$O$59,$K$9:$K$59,$P98,$C$9:$C$59,"YES")+SUMIFS($O$9:$O$59,$K$9:$K$59,$P98,$C$9:$C$59,"YES-OOS") -> 0 | Z98: =SUMIFS($R$9:$R$59,$K$9:$K$59,P98,$C$9:$C$59,"YES")+SUMIFS($R$9:$R$59,$K$9:$K$59,P98,$C$9:$C$59,"YES-OOS") -> 0 | AA98: =R98-(X98+Y98+Z98) -> 0 | AD98: =IF(R98<>0,Q98,0) -> 0 | AE98: =IF(R98<>0,0,Q98) -> 0 | AF98: =IF(R98<>0,V98,0) -> 0 | AG98: =IF(R98<>0,0,V98) -> 0 | AH98: =(Q98+V98)-(AD98+AE98+AF98+AG98) -> 0 | AK98: =P98 -> 0 | AL98: =SUMIFS($M$9:$M$59,$K$9:$K$59,$P98)+SUMIFS($N$9:$N$59,$K$9:$K$59,$P98) -> 0 | AM98: =SUMIFS($O$9:$O$59,$K$9:$K$59,$P98)+SUMIFS($P$9:$P$59,$K$9:$K$59,$P98) -> 0 | AN98: =SUMIFS($Q$9:$Q$59,$K$9:$K$59,$P98) -> 0 | AO98: =SUMIFS($R$9:$R$59,$K$9:$K$59,$P98) -> 0 | AP98: =Q98-SUM(AL98:AO98) -> 0
N99: =_xlfn.XLOOKUP($P99,$K$9:$K$59,AL$9:AL$59) -> 0 | O99: =_xlfn.XLOOKUP($P99,$K$9:$K$59,AM$9:AM$59) -> 0 | Q99: =SUMIF($K$9:$K$59,P99,$T$9:$T$59) -> 0 | R99: =SUMIFS($BA$9:$BA$59,$K$9:$K$59,P99,$C$9:$C$59,"YES")+SUMIFS($BA$9:$BA$59,$K$9:$K$59,P99,$C$9:$C$59,"YES-OOS") -> 0 | T99: =SUMIFS($BA$9:$BA$59,$K$9:$K$59,P99,$C$9:$C$59,"PENDING") -> 0 | U99: =Q99-(R99+T99) -> 0 | V99: =SUMIF($K$9:$K$59,P99,$Q$9:$Q$59) -> 0 | X99: =SUM(SUMIFS($M$9:$M$59,$K$9:$K$59,$P99,$C$9:$C$59,"YES"), SUMIFS($N$9:$N$59,$K$9:$K$59,$P99,$C$9:$C$59,"YES"))+SUM(SUMIFS($M$9:$M$59,$K$9:$K$59,$P99,$C$9:$C$59,"YES-OOS"), SUMIFS($N$9:$N$59,$K$9:$K$59,$P99,$C$9:$C$59,"YES-OOS")) -> 0 | Y99: =SUMIFS($O$9:$O$59,$K$9:$K$59,$P99,$C$9:$C$59,"YES")+SUMIFS($O$9:$O$59,$K$9:$K$59,$P99,$C$9:$C$59,"YES-OOS") -> 0 | Z99: =SUMIFS($R$9:$R$59,$K$9:$K$59,P99,$C$9:$C$59,"YES")+SUMIFS($R$9:$R$59,$K$9:$K$59,P99,$C$9:$C$59,"YES-OOS") -> 0 | AA99: =R99-(X99+Y99+Z99) -> 0 | AD99: =IF(R99<>0,Q99,0) -> 0 | AE99: =IF(R99<>0,0,Q99) -> 0 | AF99: =IF(R99<>0,V99,0) -> 0 | AG99: =IF(R99<>0,0,V99) -> 0 | AH99: =(Q99+V99)-(AD99+AE99+AF99+AG99) -> 0 | AK99: =P99 -> 0 | AL99: =SUMIFS($M$9:$M$59,$K$9:$K$59,$P99)+SUMIFS($N$9:$N$59,$K$9:$K$59,$P99) -> 0 | AM99: =SUMIFS($O$9:$O$59,$K$9:$K$59,$P99)+SUMIFS($P$9:$P$59,$K$9:$K$59,$P99) -> 0 | AN99: =SUMIFS($Q$9:$Q$59,$K$9:$K$59,$P99) -> 0 | AO99: =SUMIFS($R$9:$R$59,$K$9:$K$59,$P99) -> 0 | AP99: =Q99-SUM(AL99:AO99) -> 0
N100: =_xlfn.XLOOKUP($P100,$K$9:$K$59,AL$9:AL$59) -> 0 | O100: =_xlfn.XLOOKUP($P100,$K$9:$K$59,AM$9:AM$59) -> 0 | Q100: =SUMIF($K$9:$K$59,P100,$T$9:$T$59) -> 0 | R100: =SUMIFS($BA$9:$BA$59,$K$9:$K$59,P100,$C$9:$C$59,"YES")+SUMIFS($BA$9:$BA$59,$K$9:$K$59,P100,$C$9:$C$59,"YES-OOS") -> 0 | T100: =SUMIFS($BA$9:$BA$59,$K$9:$K$59,P100,$C$9:$C$59,"PENDING") -> 0 | U100: =Q100-(R100+T100) -> 0 | V100: =SUMIF($K$9:$K$59,P100,$Q$9:$Q$59) -> 0 | X100: =SUM(SUMIFS($M$9:$M$59,$K$9:$K$59,$P100,$C$9:$C$59,"YES"), SUMIFS($N$9:$N$59,$K$9:$K$59,$P100,$C$9:$C$59,"YES"))+SUM(SUMIFS($M$9:$M$59,$K$9:$K$59,$P100,$C$9:$C$59,"YES-OOS"), SUMIFS($N$9:$N$59,$K$9:$K$59,$P100,$C$9:$C$59,"YES-OOS")) -> 0 | Y100: =SUMIFS($O$9:$O$59,$K$9:$K$59,$P100,$C$9:$C$59,"YES")+SUMIFS($O$9:$O$59,$K$9:$K$59,$P100,$C$9:$C$59,"YES-OOS") -> 0 | Z100: =SUMIFS($R$9:$R$59,$K$9:$K$59,P100,$C$9:$C$59,"YES")+SUMIFS($R$9:$R$59,$K$9:$K$59,P100,$C$9:$C$59,"YES-OOS") -> 0 | AA100: =R100-(X100+Y100+Z100) -> 0 | AD100: =IF(R100<>0,Q100,0) -> 0 | AE100: =IF(R100<>0,0,Q100) -> 0 | AF100: =IF(R100<>0,V100,0) -> 0 | AG100: =IF(R100<>0,0,V100) -> 0 | AH100: =(Q100+V100)-(AD100+AE100+AF100+AG100) -> 0 | AK100: =P100 -> 0 | AL100: =SUMIFS($M$9:$M$59,$K$9:$K$59,$P100)+SUMIFS($N$9:$N$59,$K$9:$K$59,$P100) -> 0 | AM100: =SUMIFS($O$9:$O$59,$K$9:$K$59,$P100)+SUMIFS($P$9:$P$59,$K$9:$K$59,$P100) -> 0 | AN100: =SUMIFS($Q$9:$Q$59,$K$9:$K$59,$P100) -> 0 | AO100: =SUMIFS($R$9:$R$59,$K$9:$K$59,$P100) -> 0 | AP100: =Q100-SUM(AL100:AO100) -> 0
N101: =_xlfn.XLOOKUP($P101,$K$9:$K$59,AL$9:AL$59) -> 0 | O101: =_xlfn.XLOOKUP($P101,$K$9:$K$59,AM$9:AM$59) -> 0 | Q101: =SUMIF($K$9:$K$59,P101,$T$9:$T$59) -> 0 | R101: =SUMIFS($BA$9:$BA$59,$K$9:$K$59,P101,$C$9:$C$59,"YES")+SUMIFS($BA$9:$BA$59,$K$9:$K$59,P101,$C$9:$C$59,"YES-OOS") -> 0 | T101: =SUMIFS($BA$9:$BA$59,$K$9:$K$59,P101,$C$9:$C$59,"PENDING") -> 0 | U101: =Q101-(R101+T101) -> 0 | V101: =SUMIF($K$9:$K$59,P101,$Q$9:$Q$59) -> 0 | X101: =SUM(SUMIFS($M$9:$M$59,$K$9:$K$59,$P101,$C$9:$C$59,"YES"), SUMIFS($N$9:$N$59,$K$9:$K$59,$P101,$C$9:$C$59,"YES"))+SUM(SUMIFS($M$9:$M$59,$K$9:$K$59,$P101,$C$9:$C$59,"YES-OOS"), SUMIFS($N$9:$N$59,$K$9:$K$59,$P101,$C$9:$C$59,"YES-OOS")) -> 0 | Y101: =SUMIFS($O$9:$O$59,$K$9:$K$59,$P101,$C$9:$C$59,"YES")+SUMIFS($O$9:$O$59,$K$9:$K$59,$P101,$C$9:$C$59,"YES-OOS") -> 0 | Z101: =SUMIFS($R$9:$R$59,$K$9:$K$59,P101,$C$9:$C$59,"YES")+SUMIFS($R$9:$R$59,$K$9:$K$59,P101,$C$9:$C$59,"YES-OOS") -> 0 | AA101: =R101-(X101+Y101+Z101) -> 0 | AD101: =IF(R101<>0,Q101,0) -> 0 | AE101: =IF(R101<>0,0,Q101) -> 0 | AF101: =IF(R101<>0,V101,0) -> 0 | AG101: =IF(R101<>0,0,V101) -> 0 | AH101: =(Q101+V101)-(AD101+AE101+AF101+AG101) -> 0 | AK101: =P101 -> 0 | AL101: =SUMIFS($M$9:$M$59,$K$9:$K$59,$P101)+SUMIFS($N$9:$N$59,$K$9:$K$59,$P101) -> 0 | AM101: =SUMIFS($O$9:$O$59,$K$9:$K$59,$P101)+SUMIFS($P$9:$P$59,$K$9:$K$59,$P101) -> 0 | AN101: =SUMIFS($Q$9:$Q$59,$K$9:$K$59,$P101) -> 0 | AO101: =SUMIFS($R$9:$R$59,$K$9:$K$59,$P101) -> 0 | AP101: =Q101-SUM(AL101:AO101) -> 0
N102: =_xlfn.XLOOKUP($P102,$K$9:$K$59,AL$9:AL$59) -> 0 | O102: =_xlfn.XLOOKUP($P102,$K$9:$K$59,AM$9:AM$59) -> 0 | Q102: =SUMIF($K$9:$K$59,P102,$T$9:$T$59) -> 0 | R102: =SUMIFS($BA$9:$BA$59,$K$9:$K$59,P102,$C$9:$C$59,"YES")+SUMIFS($BA$9:$BA$59,$K$9:$K$59,P102,$C$9:$C$59,"YES-OOS") -> 0 | T102: =SUMIFS($BA$9:$BA$59,$K$9:$K$59,P102,$C$9:$C$59,"PENDING") -> 0 | U102: =Q102-(R102+T102) -> 0 | V102: =SUMIF($K$9:$K$59,P102,$Q$9:$Q$59) -> 0 | X102: =SUM(SUMIFS($M$9:$M$59,$K$9:$K$59,$P102,$C$9:$C$59,"YES"), SUMIFS($N$9:$N$59,$K$9:$K$59,$P102,$C$9:$C$59,"YES"))+SUM(SUMIFS($M$9:$M$59,$K$9:$K$59,$P102,$C$9:$C$59,"YES-OOS"), SUMIFS($N$9:$N$59,$K$9:$K$59,$P102,$C$9:$C$59,"YES-OOS")) -> 0 | Y102: =SUMIFS($O$9:$O$59,$K$9:$K$59,$P102,$C$9:$C$59,"YES")+SUMIFS($O$9:$O$59,$K$9:$K$59,$P102,$C$9:$C$59,"YES-OOS") -> 0 | Z102: =SUMIFS($R$9:$R$59,$K$9:$K$59,P102,$C$9:$C$59,"YES")+SUMIFS($R$9:$R$59,$K$9:$K$59,P102,$C$9:$C$59,"YES-OOS") -> 0 | AA102: =R102-(X102+Y102+Z102) -> 0 | AD102: =IF(R102<>0,Q102,0) -> 0 | AE102: =IF(R102<>0,0,Q102) -> 0 | AF102: =IF(R102<>0,V102,0) -> 0 | AG102: =IF(R102<>0,0,V102) -> 0 | AH102: =(Q102+V102)-(AD102+AE102+AF102+AG102) -> 0 | AK102: =P102 -> 0 | AL102: =SUMIFS($M$9:$M$59,$K$9:$K$59,$P102)+SUMIFS($N$9:$N$59,$K$9:$K$59,$P102) -> 0 | AM102: =SUMIFS($O$9:$O$59,$K$9:$K$59,$P102)+SUMIFS($P$9:$P$59,$K$9:$K$59,$P102) -> 0 | AN102: =SUMIFS($Q$9:$Q$59,$K$9:$K$59,$P102) -> 0 | AO102: =SUMIFS($R$9:$R$59,$K$9:$K$59,$P102) -> 0 | AP102: =Q102-SUM(AL102:AO102) -> 0
N103: =_xlfn.XLOOKUP($P103,$K$9:$K$59,AL$9:AL$59) -> 0 | O103: =_xlfn.XLOOKUP($P103,$K$9:$K$59,AM$9:AM$59) -> 0 | Q103: =SUMIF($K$9:$K$59,P103,$T$9:$T$59) -> 0 | R103: =SUMIFS($BA$9:$BA$59,$K$9:$K$59,P103,$C$9:$C$59,"YES")+SUMIFS($BA$9:$BA$59,$K$9:$K$59,P103,$C$9:$C$59,"YES-OOS") -> 0 | T103: =SUMIFS($BA$9:$BA$59,$K$9:$K$59,P103,$C$9:$C$59,"PENDING") -> 0 | U103: =Q103-(R103+T103) -> 0 | V103: =SUMIF($K$9:$K$59,P103,$Q$9:$Q$59) -> 0 | X103: =SUM(SUMIFS($M$9:$M$59,$K$9:$K$59,$P103,$C$9:$C$59,"YES"), SUMIFS($N$9:$N$59,$K$9:$K$59,$P103,$C$9:$C$59,"YES"))+SUM(SUMIFS($M$9:$M$59,$K$9:$K$59,$P103,$C$9:$C$59,"YES-OOS"), SUMIFS($N$9:$N$59,$K$9:$K$59,$P103,$C$9:$C$59,"YES-OOS")) -> 0 | Y103: =SUMIFS($O$9:$O$59,$K$9:$K$59,$P103,$C$9:$C$59,"YES")+SUMIFS($O$9:$O$59,$K$9:$K$59,$P103,$C$9:$C$59,"YES-OOS") -> 0 | Z103: =SUMIFS($R$9:$R$59,$K$9:$K$59,P103,$C$9:$C$59,"YES")+SUMIFS($R$9:$R$59,$K$9:$K$59,P103,$C$9:$C$59,"YES-OOS") -> 0 | AA103: =R103-(X103+Y103+Z103) -> 0 | AD103: =IF(R103<>0,Q103,0) -> 0 | AE103: =IF(R103<>0,0,Q103) -> 0 | AF103: =IF(R103<>0,V103,0) -> 0 | AG103: =IF(R103<>0,0,V103) -> 0 | AH103: =(Q103+V103)-(AD103+AE103+AF103+AG103) -> 0 | AK103: =P103 -> 0 | AL103: =SUMIFS($M$9:$M$59,$K$9:$K$59,$P103)+SUMIFS($N$9:$N$59,$K$9:$K$59,$P103) -> 0 | AM103: =SUMIFS($O$9:$O$59,$K$9:$K$59,$P103)+SUMIFS($P$9:$P$59,$K$9:$K$59,$P103) -> 0 | AN103: =SUMIFS($Q$9:$Q$59,$K$9:$K$59,$P103) -> 0 | AO103: =SUMIFS($R$9:$R$59,$K$9:$K$59,$P103) -> 0 | AP103: =Q103-SUM(AL103:AO103) -> 0
... N107: =_xlfn.XLOOKUP($P107,$K$9:$K$59,AL$9:AL$59) -> 0 | O107: =_xlfn.XLOOKUP($P107,$K$9:$K$59,AM$9:AM$59) -> 0 | Q107: =SUMIF($K$9:$K$59,P107,$T$9:$T$59) -> 0 | R107: =SUMIFS($BA$9:$BA$59,$K$9:$K$59,P107,$C$9:$C$59,"YES")+SUMIFS($BA$9:$BA$59,$K$9:$K$59,P107,$C$9:$C$59,"YES-OOS") -> 0 | T107: =SUMIFS($BA$9:$BA$59,$K$9:$K$59,P107,$C$9:$C$59,"PENDING") -> 0 | U107: =Q107-(R107+T107) -> 0 | V107: =SUMIF($K$9:$K$59,P107,$Q$9:$Q$59) -> 0 | X107: =SUM(SUMIFS($M$9:$M$59,$K$9:$K$59,$P107,$C$9:$C$59,"YES"), SUMIFS($N$9:$N$59,$K$9:$K$59,$P107,$C$9:$C$59,"YES"))+SUM(SUMIFS($M$9:$M$59,$K$9:$K$59,$P107,$C$9:$C$59,"YES-OOS"), SUMIFS($N$9:$N$59,$K$9:$K$59,$P107,$C$9:$C$59,"YES-OOS")) -> 0 | Y107: =SUMIFS($O$9:$O$59,$K$9:$K$59,$P107,$C$9:$C$59,"YES")+SUMIFS($O$9:$O$59,$K$9:$K$59,$P107,$C$9:$C$59,"YES-OOS") -> 0 | Z107: =SUMIFS($R$9:$R$59,$K$9:$K$59,P107,$C$9:$C$59,"YES")+SUMIFS($R$9:$R$59,$K$9:$K$59,P107,$C$9:$C$59,"YES-OOS") -> 0 | AA107: =R107-(X107+Y107+Z107) -> 0 | AD107: =IF(R107<>0,Q107,0) -> 0 | AE107: =IF(R107<>0,0,Q107) -> 0 | AF107: =IF(R107<>0,V107,0) -> 0 | AG107: =IF(R107<>0,0,V107) -> 0 | AH107: =(Q107+V107)-(AD107+AE107+AF107+AG107) -> 0 | AK107: =P107 -> 0 | AL107: =SUMIFS($M$9:$M$59,$K$9:$K$59,$P107)+SUMIFS($N$9:$N$59,$K$9:$K$59,$P107) -> 0 | AM107: =SUMIFS($O$9:$O$59,$K$9:$K$59,$P107)+SUMIFS($P$9:$P$59,$K$9:$K$59,$P107) -> 0 | AN107: =SUMIFS($Q$9:$Q$59,$K$9:$K$59,$P107) -> 0 | AO107: =SUMIFS($R$9:$R$59,$K$9:$K$59,$P107) -> 0 | AP107: =Q107-SUM(AL107:AO107) -> 0
P108: Total | Q108: =SUM(Q90:Q107) -> 0 | R108: =SUM(R90:R107) -> 0 | T108: =SUM(T90:T107) -> 0 | U108: =SUM(U90:U107) -> 0 | V108: =SUM(V90:V107) -> 0 | X108: =SUM(X90:X107) -> 0 | Y108: =SUM(Y90:Y107) -> 0 | Z108: =SUM(Z90:Z107) -> 0 | AA108: =R108-(X108+Y108+Z108) -> 0 | AD108: =SUM(AD90:AD107) -> 0 | AE108: =SUM(AE90:AE107) -> 0 | AF108: =SUM(AF90:AF107) -> 0 | AG108: =SUM(AG90:AG107) -> 0 | AL108: =SUM(AL90:AL107) -> 0 | AM108: =SUM(AM90:AM107) -> 0 | AN108: =SUM(AN90:AN107) -> 0 | AO108: =SUM(AO90:AO107) -> 0 | AP108: =SUM(AP90:AP107) -> 0
Q109: =Q108-T63 -> 0 | R109: =R108-N81 -> 0 | T109: =T108-M69 -> 0 | U109: =U108-N83-N84-N85 -> 0 | V109: =V108-N85 -> 0 | AE109: =(AD108+AE108)-Q108 -> 0 | AG109: =(AF108+AG108)-V108 -> 0
N111: State Submission Table Entry Reconcile
N112: Job Type | O112: Job # | P112: Client Billing | Q112: Total Amount | R112: Qualified Billing Amount | T112: Amount Removed | U112: Ties to CPA workbook
P113: A | Q113: =SUMIF($O$90:$O$107,$P113,$Q$90:$Q$107) -> 0 | R113: =SUMIFS($BA$9:$BA$59,$AM$9:$AM$59,$P113,$C$9:$C$59,"YES")+SUMIFS($BA$9:$BA$59,$AM$9:$AM$59,$P113,$C$9:$C$59,"YES-OOS") -> 0 | U113: =SUMIFS($AD$90:$AD$107,$O$90:$O$107,P113) -> 0
P114: B | Q114: =SUMIF($O$90:$O$107,P114,$Q$90:$Q$107) -> 0 | R114: =SUMIFS($BA$9:$BA$59,$AM$9:$AM$59,$P114,$C$9:$C$59,"YES")+SUMIFS($BA$9:$BA$59,$AM$9:$AM$59,$P114,$C$9:$C$59,"YES-OOS") -> 0 | U114: =SUMIFS($AD$90:$AD$107,$O$90:$O$107,P114) -> 0 | Y114: =SUMIFS($AD$91:$AD$104,$O$91:$O$104,P110) -> 0
P115: C | Q115: =SUMIF($O$90:$O$107,P115,$Q$90:$Q$107) -> 0 | R115: =SUMIFS($BA$9:$BA$59,$AM$9:$AM$59,$P115,$C$9:$C$59,"YES")+SUMIFS($BA$9:$BA$59,$AM$9:$AM$59,$P115,$C$9:$C$59,"YES-OOS") -> 0 | U115: =SUMIFS($AD$90:$AD$107,$O$90:$O$107,P115) -> 0
P116: D | Q116: =SUMIF($O$90:$O$107,P116,$Q$90:$Q$107) -> 0 | R116: =SUMIFS($BA$9:$BA$59,$AM$9:$AM$59,$P116,$C$9:$C$59,"YES")+SUMIFS($BA$9:$BA$59,$AM$9:$AM$59,$P116,$C$9:$C$59,"YES-OOS") -> 0 | U116: =SUMIFS($AD$90:$AD$107,$O$90:$O$107,P116) -> 0
Q117: =SUMIF($O$90:$O$107,P117,$Q$90:$Q$107) -> 0 | R117: =SUMIFS($BA$9:$BA$59,$AM$9:$AM$59,$P117,$C$9:$C$59,"YES")+SUMIFS($BA$9:$BA$59,$AM$9:$AM$59,$P117,$C$9:$C$59,"YES-OOS") -> 0 | U117: =SUMIFS($AD$90:$AD$107,$O$90:$O$107,P117) -> 0
Q118: =SUMIF($O$90:$O$107,P118,$Q$90:$Q$107) -> 0 | R118: =SUMIFS($BA$9:$BA$59,$AM$9:$AM$59,$P118,$C$9:$C$59,"YES")+SUMIFS($BA$9:$BA$59,$AM$9:$AM$59,$P118,$C$9:$C$59,"YES-OOS") -> 0 | U118: =SUMIFS($AD$90:$AD$107,$O$90:$O$107,P118) -> 0
Q119: =SUM(Q113:Q118) -> 0 | R119: =SUM(R113:R118) -> 0 | T119: =SUM(T113:T118) -> 0 | U119: =SUM(U113:U118) -> 0
Q120: =Q119-T63 -> 0 | R120: =R119-N81 -> 0 | U120: =AD108-U119 -> 0
O122: CPA Columns - State Submission Entered Amounts Reconcile
O123: Job Type | P123: Job # | Q123: Total Amount | R123: Qualified Billing Amount | T123: Ties to CPA workbook
P124: A1 | Q124: =SUMIF($AL$9:$AL$59,$P124,$T$9:$T$59) -> 0 | R124: =SUMIFS($BA$9:$BA$59,$AL$9:$AL$59,$P124,$C$9:$C$59,"YES")+SUMIFS($BA$9:$BA$59,$AL$9:$AL$59,$P124,$C$9:$C$59,"YES-OOS") -> 0 | T124: =SUMIFS($AD$90:$AD$107,$N$90:$N$107,P124) -> 0
P125: B1 | Q125: =SUMIF($AL$9:$AL$59,$P125,$T$9:$T$59) -> 0 | R125: =SUMIFS($BA$9:$BA$59,$AL$9:$AL$59,$P125,$C$9:$C$59,"YES")+SUMIFS($BA$9:$BA$59,$AL$9:$AL$59,$P125,$C$9:$C$59,"YES-OOS") -> 0 | T125: =SUMIFS($AD$90:$AD$107,$N$90:$N$107,P125) -> 0
P126: C1 | Q126: =SUMIF($AL$9:$AL$59,$P126,$T$9:$T$59) -> 0 | R126: =SUMIFS($BA$9:$BA$59,$AL$9:$AL$59,$P126,$C$9:$C$59,"YES")+SUMIFS($BA$9:$BA$59,$AL$9:$AL$59,$P126,$C$9:$C$59,"YES-OOS") -> 0 | T126: =SUMIFS($AD$90:$AD$107,$N$90:$N$107,P126) -> 0
P127: D1 | Q127: =SUMIF($AL$9:$AL$59,$P127,$T$9:$T$59) -> 0 | R127: =SUMIFS($BA$9:$BA$59,$AL$9:$AL$59,$P127,$C$9:$C$59,"YES")+SUMIFS($BA$9:$BA$59,$AL$9:$AL$59,$P127,$C$9:$C$59,"YES-OOS") -> 0 | T127: =SUMIFS($AD$90:$AD$107,$N$90:$N$107,P127) -> 0
Q128: =SUM(Q124:Q127) -> 0 | R128: =SUM(R124:R127) -> 0 | T128: =SUM(T124:T127) -> 0
Q129: =Q128-T63 -> 0 | R129: =R128-N81 -> 0 | T129: =T128-AD108 -> 0

Sheet Agency Hours
B1: Production Tax Incentives Hours Letter
X2: 1st Shoot Day | Y2: 44741
B3: Project Title: | D3: =#REF! -> #REF! | X3: Last Shoot Day | Y3: 44741
B4: Shoot Date: | D4: =#REF! -> #REF! | G4: DELETE SAMPLE DATA FOR ACTUAL PROJECTS | X4: Covid End Date | Y4: 44896
B5: Work State: | D5: =#REF! -> #REF!
P6: Follow CPA Diversity Format (WHITE, HISP, AA…) | AF6: Don't edit this part; with formulas
G7: Use acronym, as will be used in CPA | P7: DIVERSITY | T7: Proof of Payment | X7: RESIDENCY
B8: Hours Letter | C8: Invoice Date | D8: ITEM # | E8: Qualify? | F8: Crew Name | G8: Job Description | H8: Position Category | I8: Address | J8: City | K8: Zip | L8: State | M8: Agency Hours | N8: Agency Hours Amount | O8: Agency Retainer Billing Amount | P8: Diversity | Q8: Sex | R8: Hours Letter Type | S8: Description | T8: Pymt Method | U8: Pymt/Check | V8: Proof of Payment | X8: Document Type | Y8: Issue Date | Z8: Expiration Date | AA8: Residency | AB8: NO-IL Residency Status | AC8: Job No. | AD8: Client Billing No. | AF8: Crew Name | AG8: Crew Position | AH8: Position Category | AI8: Home address | AJ8: City | AK8: Zip | AL8: # of Hours Worked | AM8: Dates Worked | AN8: Agency Hours Amount $ | AO8: ER TAXES | AP8: ER BENEFITS / PH&W | AQ8: CPA TOTAL
N9: 0 | AA9: =IF(E9="NO-OOS","N/A",IF(X9="Driver's License",IF(Y9>$Y$2,"SOS",IF(Z9>=$Y$3,"Valid",IF(AND(Z9<$Y$3,$Y$4>$Y$3,Z9>43831),"Covid","Expired"))),IF(X9="I9",IF(Z9>=$Y$3,"Valid",IF(AND(Z9<$Y$3,$Y$4>$Y$3,Z9>43831),"Covid","Expired")),IF(X9="Work Permit",IF(AND(Z9<=$Y$2,(Z9+365)>=$Y$3),"Valid","Expired"),IF(X9="Missing Residency","Missing",IF(X9="","","Other")))))) | AF9: =F9 -> 0 | AG9: =G9 -> 0 | AH9: =H9 -> 0 | AI9: =I9 -> 0 | AJ9: =J9 -> 0 | AK9: =K9 -> 0 | AL9: =M9 -> 0 | AN9: =N9 -> 0 | AO9: 0 | AP9: 0 | AQ9: =AN9 -> 0
N10: 0 | AA10: =IF(E10="NO-OOS","N/A",IF(X10="Driver's License",IF(Y10>$Y$2,"SOS",IF(Z10>=$Y$3,"Valid",IF(AND(Z10<$Y$3,$Y$4>$Y$3,Z10>43831),"Covid","Expired"))),IF(X10="I9",IF(Z10>=$Y$3,"Valid",IF(AND(Z10<$Y$3,$Y$4>$Y$3,Z10>43831),"Covid","Expired")),IF(X10="Work Permit",IF(AND(Z10<=$Y$2,(Z10+365)>=$Y$3),"Valid","Expired"),IF(X10="Missing Residency","Missing",IF(X10="","","Other")))))) | AF10: =F10 -> 0 | AG10: =G10 -> 0 | AH10: =H10 -> 0 | AI10: =I10 -> 0 | AJ10: =J10 -> 0 | AK10: =K10 -> 0 | AL10: =M10 -> 0 | AN10: =N10 -> 0 | AO10: 0 | AP10: 0 | AQ10: =AN10 -> 0
N11: 0 | AA11: =IF(E11="NO-OOS","N/A",IF(X11="Driver's License",IF(Y11>$Y$2,"SOS",IF(Z11>=$Y$3,"Valid",IF(AND(Z11<$Y$3,$Y$4>$Y$3,Z11>43831),"Covid","Expired"))),IF(X11="I9",IF(Z11>=$Y$3,"Valid",IF(AND(Z11<$Y$3,$Y$4>$Y$3,Z11>43831),"Covid","Expired")),IF(X11="Work Permit",IF(AND(Z11<=$Y$2,(Z11+365)>=$Y$3),"Valid","Expired"),IF(X11="Missing Residency","Missing",IF(X11="","","Other")))))) | AF11: =F11 -> 0 | AG11: =G11 -> 0 | AH11: =H11 -> 0 | AI11: =I11 -> 0 | AJ11: =J11 -> 0 | AK11: =K11 -> 0 | AL11: =M11 -> 0 | AN11: =N11 -> 0 | AO11: 0 | AP11: 0 | AQ11: =AN11 -> 0
N12: 0 | AA12: =IF(E12="NO-OOS","N/A",IF(X12="Driver's License",IF(Y12>$Y$2,"SOS",IF(Z12>=$Y$3,"Valid",IF(AND(Z12<$Y$3,$Y$4>$Y$3,Z12>43831),"Covid","Expired"))),IF(X12="I9",IF(Z12>=$Y$3,"Valid",IF(AND(Z12<$Y$3,$Y$4>$Y$3,Z12>43831),"Covid","Expired")),IF(X12="Work Permit",IF(AND(Z12<=$Y$2,(Z12+365)>=$Y$3),"Valid","Expired"),IF(X12="Missing Residency","Missing",IF(X12="","","Other")))))) | AF12: =F12 -> 0 | AG12: =G12 -> 0 | AH12: =H12 -> 0 | AI12: =I12 -> 0 | AJ12: =J12 -> 0 | AK12: =K12 -> 0 | AL12: =M12 -> 0 | AN12: =N12 -> 0 | AO12: 0 | AP12: 0 | AQ12: =AN12 -> 0
N13: 0 | AA13: =IF(E13="NO-OOS","N/A",IF(X13="Driver's License",IF(Y13>$Y$2,"SOS",IF(Z13>=$Y$3,"Valid",IF(AND(Z13<$Y$3,$Y$4>$Y$3,Z13>43831),"Covid","Expired"))),IF(X13="I9",IF(Z13>=$Y$3,"Valid",IF(AND(Z13<$Y$3,$Y$4>$Y$3,Z13>43831),"Covid","Expired")),IF(X13="Work Permit",IF(AND(Z13<=$Y$2,(Z13+365)>=$Y$3),"Valid","Expired"),IF(X13="Missing Residency","Missing",IF(X13="","","Other")))))) | AF13: =F13 -> 0 | AG13: =G13 -> 0 | AH13: =H13 -> 0 | AI13: =I13 -> 0 | AJ13: =J13 -> 0 | AK13: =K13 -> 0 | AL13: =M13 -> 0 | AN13: =N13 -> 0 | AO13: 0 | AP13: 0 | AQ13: =AN13 -> 0
N14: 0 | AA14: =IF(E14="NO-OOS","N/A",IF(X14="Driver's License",IF(Y14>$Y$2,"SOS",IF(Z14>=$Y$3,"Valid",IF(AND(Z14<$Y$3,$Y$4>$Y$3,Z14>43831),"Covid","Expired"))),IF(X14="I9",IF(Z14>=$Y$3,"Valid",IF(AND(Z14<$Y$3,$Y$4>$Y$3,Z14>43831),"Covid","Expired")),IF(X14="Work Permit",IF(AND(Z14<=$Y$2,(Z14+365)>=$Y$3),"Valid","Expired"),IF(X14="Missing Residency","Missing",IF(X14="","","Other")))))) | AF14: =F14 -> 0 | AG14: =G14 -> 0 | AH14: =H14 -> 0 | AI14: =I14 -> 0 | AJ14: =J14 -> 0 | AK14: =K14 -> 0 | AL14: =M14 -> 0 | AN14: =N14 -> 0 | AO14: 0 | AP14: 0 | AQ14: =AN14 -> 0
N15: 0 | AA15: =IF(E15="NO-OOS","N/A",IF(X15="Driver's License",IF(Y15>$Y$2,"SOS",IF(Z15>=$Y$3,"Valid",IF(AND(Z15<$Y$3,$Y$4>$Y$3,Z15>43831),"Covid","Expired"))),IF(X15="I9",IF(Z15>=$Y$3,"Valid",IF(AND(Z15<$Y$3,$Y$4>$Y$3,Z15>43831),"Covid","Expired")),IF(X15="Work Permit",IF(AND(Z15<=$Y$2,(Z15+365)>=$Y$3),"Valid","Expired"),IF(X15="Missing Residency","Missing",IF(X15="","","Other")))))) | AF15: =F15 -> 0 | AG15: =G15 -> 0 | AH15: =H15 -> 0 | AI15: =I15 -> 0 | AJ15: =J15 -> 0 | AK15: =K15 -> 0 | AL15: =M15 -> 0 | AN15: =N15 -> 0 | AO15: 0 | AP15: 0 | AQ15: =AN15 -> 0
N16: 0 | AA16: =IF(E16="NO-OOS","N/A",IF(X16="Driver's License",IF(Y16>$Y$2,"SOS",IF(Z16>=$Y$3,"Valid",IF(AND(Z16<$Y$3,$Y$4>$Y$3,Z16>43831),"Covid","Expired"))),IF(X16="I9",IF(Z16>=$Y$3,"Valid",IF(AND(Z16<$Y$3,$Y$4>$Y$3,Z16>43831),"Covid","Expired")),IF(X16="Work Permit",IF(AND(Z16<=$Y$2,(Z16+365)>=$Y$3),"Valid","Expired"),IF(X16="Missing Residency","Missing",IF(X16="","","Other")))))) | AF16: =F16 -> 0 | AG16: =G16 -> 0 | AH16: =H16 -> 0 | AI16: =I16 -> 0 | AJ16: =J16 -> 0 | AK16: =K16 -> 0 | AL16: =M16 -> 0 | AN16: =N16 -> 0 | AO16: 0 | AP16: 0 | AQ16: =AN16 -> 0
N17: 0 | AA17: =IF(E17="NO-OOS","N/A",IF(X17="Driver's License",IF(Y17>$Y$2,"SOS",IF(Z17>=$Y$3,"Valid",IF(AND(Z17<$Y$3,$Y$4>$Y$3,Z17>43831),"Covid","Expired"))),IF(X17="I9",IF(Z17>=$Y$3,"Valid",IF(AND(Z17<$Y$3,$Y$4>$Y$3,Z17>43831),"Covid","Expired")),IF(X17="Work Permit",IF(AND(Z17<=$Y$2,(Z17+365)>=$Y$3),"Valid","Expired"),IF(X17="Missing Residency","Missing",IF(X17="","","Other")))))) | AF17: =F17 -> 0 | AG17: =G17 -> 0 | AH17: =H17 -> 0 | AI17: =I17 -> 0 | AJ17: =J17 -> 0 | AK17: =K17 -> 0 | AL17: =M17 -> 0 | AN17: =N17 -> 0 | AO17: 0 | AP17: 0 | AQ17: =AN17 -> 0
N18: 0 | AA18: =IF(E18="NO-OOS","N/A",IF(X18="Driver's License",IF(Y18>$Y$2,"SOS",IF(Z18>=$Y$3,"Valid",IF(AND(Z18<$Y$3,$Y$4>$Y$3,Z18>43831),"Covid","Expired"))),IF(X18="I9",IF(Z18>=$Y$3,"Valid",IF(AND(Z18<$Y$3,$Y$4>$Y$3,Z18>43831),"Covid","Expired")),IF(X18="Work Permit",IF(AND(Z18<=$Y$2,(Z18+365)>=$Y$3),"Valid","Expired"),IF(X18="Missing Residency","Missing",IF(X18="","","Other")))))) | AN18: =N18 -> 0 | AQ18: =AN18 -> 0
B19: AGENCY Retainer Fee | AA19: =IF(E19="NO-OOS","N/A",IF(X19="Driver's License",IF(Y19>$Y$2,"SOS",IF(Z19>=$Y$3,"Valid",IF(AND(Z19<$Y$3,$Y$4>$Y$3,Z19>43831),"Covid","Expired"))),IF(X19="I9",IF(Z19>=$Y$3,"Valid",IF(AND(Z19<$Y$3,$Y$4>$Y$3,Z19>43831),"Covid","Expired")),IF(X19="Work Permit",IF(AND(Z19<=$Y$2,(Z19+365)>=$Y$3),"Valid","Expired"),IF(X19="Missing Residency","Missing",IF(X19="","","Other"))))))
O20: 0 | AA20: =IF(E20="NO-OOS","N/A",IF(X20="Driver's License",IF(Y20>$Y$2,"SOS",IF(Z20>=$Y$3,"Valid",IF(AND(Z20<$Y$3,$Y$4>$Y$3,Z20>43831),"Covid","Expired"))),IF(X20="I9",IF(Z20>=$Y$3,"Valid",IF(AND(Z20<$Y$3,$Y$4>$Y$3,Z20>43831),"Covid","Expired")),IF(X20="Work Permit",IF(AND(Z20<=$Y$2,(Z20+365)>=$Y$3),"Valid","Expired"),IF(X20="Missing Residency","Missing",IF(X20="","","Other")))))) | AF20: =F20 -> 0 | AG20: =G20 -> 0 | AH20: =H20 -> 0 | AI20: =I20 -> 0 | AJ20: =J20 -> 0 | AK20: =K20 -> 0 | AL20: =M20 -> 0 | AN20: =N20 -> 0 | AO20: 0 | AP20: 0 | AQ20: =AN20 -> 0
O21: 0 | AA21: =IF(E21="NO-OOS","N/A",IF(X21="Driver's License",IF(Y21>$Y$2,"SOS",IF(Z21>=$Y$3,"Valid",IF(AND(Z21<$Y$3,$Y$4>$Y$3,Z21>43831),"Covid","Expired"))),IF(X21="I9",IF(Z21>=$Y$3,"Valid",IF(AND(Z21<$Y$3,$Y$4>$Y$3,Z21>43831),"Covid","Expired")),IF(X21="Work Permit",IF(AND(Z21<=$Y$2,(Z21+365)>=$Y$3),"Valid","Expired"),IF(X21="Missing Residency","Missing",IF(X21="","","Other")))))) | AF21: =F21 -> 0 | AG21: =G21 -> 0 | AH21: =H21 -> 0 | AI21: =I21 -> 0 | AJ21: =J21 -> 0 | AK21: =K21 -> 0 | AL21: =M21 -> 0 | AN21: =N21 -> 0 | AO21: 0 | AP21: 0 | AQ21: =AN21 -> 0
O22: 0 | AA22: =IF(E22="NO-OOS","N/A",IF(X22="Driver's License",IF(Y22>$Y$2,"SOS",IF(Z22>=$Y$3,"Valid",IF(AND(Z22<$Y$3,$Y$4>$Y$3,Z22>43831),"Covid","Expired"))),IF(X22="I9",IF(Z22>=$Y$3,"Valid",IF(AND(Z22<$Y$3,$Y$4>$Y$3,Z22>43831),"Covid","Expired")),IF(X22="Work Permit",IF(AND(Z22<=$Y$2,(Z22+365)>=$Y$3),"Valid","Expired"),IF(X22="Missing Residency","Missing",IF(X22="","","Other")))))) | AF22: =F22 -> 0 | AG22: =G22 -> 0 | AH22: =H22 -> 0 | AI22: =I22 -> 0 | AJ22: =J22 -> 0 | AK22: =K22 -> 0 | AL22: =M22 -> 0 | AN22: =N22 -> 0 | AO22: 0 | AP22: 0 | AQ22: =AN22 -> 0
O23: 0 | AA23: =IF(E23="NO-OOS","N/A",IF(X23="Driver's License",IF(Y23>$Y$2,"SOS",IF(Z23>=$Y$3,"Valid",IF(AND(Z23<$Y$3,$Y$4>$Y$3,Z23>43831),"Covid","Expired"))),IF(X23="I9",IF(Z23>=$Y$3,"Valid",IF(AND(Z23<$Y$3,$Y$4>$Y$3,Z23>43831),"Covid","Expired")),IF(X23="Work Permit",IF(AND(Z23<=$Y$2,(Z23+365)>=$Y$3),"Valid","Expired"),IF(X23="Missing Residency","Missing",IF(X23="","","Other")))))) | AF23: =F23 -> 0 | AG23: =G23 -> 0 | AH23: =H23 -> 0 | AI23: =I23 -> 0 | AJ23: =J23 -> 0 | AK23: =K23 -> 0 | AL23: =M23 -> 0 | AN23: =N23 -> 0 | AO23: 0 | AP23: 0 | AQ23: =AN23 -> 0
O24: 0 | AA24: =IF(E24="NO-OOS","N/A",IF(X24="Driver's License",IF(Y24>$Y$2,"SOS",IF(Z24>=$Y$3,"Valid",IF(AND(Z24<$Y$3,$Y$4>$Y$3,Z24>43831),"Covid","Expired"))),IF(X24="I9",IF(Z24>=$Y$3,"Valid",IF(AND(Z24<$Y$3,$Y$4>$Y$3,Z24>43831),"Covid","Expired")),IF(X24="Work Permit",IF(AND(Z24<=$Y$2,(Z24+365)>=$Y$3),"Valid","Expired"),IF(X24="Missing Residency","Missing",IF(X24="","","Other")))))) | AF24: =F24 -> 0 | AG24: =G24 -> 0 | AH24: =H24 -> 0 | AI24: =I24 -> 0 | AJ24: =J24 -> 0 | AK24: =K24 -> 0 | AL24: =M24 -> 0 | AN24: =N24 -> 0 | AO24: 0 | AP24: 0 | AQ24: =AN24 -> 0
O25: 0 | AA25: =IF(E25="NO-OOS","N/A",IF(X25="Driver's License",IF(Y25>$Y$2,"SOS",IF(Z25>=$Y$3,"Valid",IF(AND(Z25<$Y$3,$Y$4>$Y$3,Z25>43831),"Covid","Expired"))),IF(X25="I9",IF(Z25>=$Y$3,"Valid",IF(AND(Z25<$Y$3,$Y$4>$Y$3,Z25>43831),"Covid","Expired")),IF(X25="Work Permit",IF(AND(Z25<=$Y$2,(Z25+365)>=$Y$3),"Valid","Expired"),IF(X25="Missing Residency","Missing",IF(X25="","","Other")))))) | AF25: =F25 -> 0 | AG25: =G25 -> 0 | AH25: =H25 -> 0 | AI25: =I25 -> 0 | AJ25: =J25 -> 0 | AK25: =K25 -> 0 | AL25: =M25 -> 0 | AN25: =N25 -> 0 | AO25: 0 | AP25: 0 | AQ25: =AN25 -> 0
O26: 0 | AA26: =IF(E26="NO-OOS","N/A",IF(X26="Driver's License",IF(Y26>$Y$2,"SOS",IF(Z26>=$Y$3,"Valid",IF(AND(Z26<$Y$3,$Y$4>$Y$3,Z26>43831),"Covid","Expired"))),IF(X26="I9",IF(Z26>=$Y$3,"Valid",IF(AND(Z26<$Y$3,$Y$4>$Y$3,Z26>43831),"Covid","Expired")),IF(X26="Work Permit",IF(AND(Z26<=$Y$2,(Z26+365)>=$Y$3),"Valid","Expired"),IF(X26="Missing Residency","Missing",IF(X26="","","Other")))))) | AF26: =F26 -> 0 | AG26: =G26 -> 0 | AH26: =H26 -> 0 | AI26: =I26 -> 0 | AJ26: =J26 -> 0 | AK26: =K26 -> 0 | AL26: =M26 -> 0 | AN26: =N26 -> 0 | AO26: 0 | AP26: 0 | AQ26: =AN26 -> 0
B27: AGENCY PRODUCTION HOURS | AA27: =IF(E27="NO-OOS","N/A",IF(X27="Driver's License",IF(Y27>$Y$2,"SOS",IF(Z27>=$Y$3,"Valid",IF(AND(Z27<$Y$3,$Y$4>$Y$3,Z27>43831),"Covid","Expired"))),IF(X27="I9",IF(Z27>=$Y$3,"Valid",IF(AND(Z27<$Y$3,$Y$4>$Y$3,Z27>43831),"Covid","Expired")),IF(X27="Work Permit",IF(AND(Z27<=$Y$2,(Z27+365)>=$Y$3),"Valid","Expired"),IF(X27="Missing Residency","Missing",IF(X27="","","Other"))))))
N28: 0 | AA28: =IF(E28="NO-OOS","N/A",IF(X28="Driver's License",IF(Y28>$Y$2,"SOS",IF(Z28>=$Y$3,"Valid",IF(AND(Z28<$Y$3,$Y$4>$Y$3,Z28>43831),"Covid","Expired"))),IF(X28="I9",IF(Z28>=$Y$3,"Valid",IF(AND(Z28<$Y$3,$Y$4>$Y$3,Z28>43831),"Covid","Expired")),IF(X28="Work Permit",IF(AND(Z28<=$Y$2,(Z28+365)>=$Y$3),"Valid","Expired"),IF(X28="Missing Residency","Missing",IF(X28="","","Other")))))) | AF28: =F28 -> 0 | AG28: =G28 -> 0 | AH28: =H28 -> 0 | AI28: =I28 -> 0 | AJ28: =J28 -> 0 | AK28: =K28 -> 0 | AL28: =M28 -> 0 | AN28: =N28 -> 0 | AO28: 0 | AP28: 0 | AQ28: =AN28 -> 0
N29: 0 | AA29: =IF(E29="NO-OOS","N/A",IF(X29="Driver's License",IF(Y29>$Y$2,"SOS",IF(Z29>=$Y$3,"Valid",IF(AND(Z29<$Y$3,$Y$4>$Y$3,Z29>43831),"Covid","Expired"))),IF(X29="I9",IF(Z29>=$Y$3,"Valid",IF(AND(Z29<$Y$3,$Y$4>$Y$3,Z29>43831),"Covid","Expired")),IF(X29="Work Permit",IF(AND(Z29<=$Y$2,(Z29+365)>=$Y$3),"Valid","Expired"),IF(X29="Missing Residency","Missing",IF(X29="","","Other")))))) | AF29: =F29 -> 0 | AG29: =G29 -> 0 | AH29: =H29 -> 0 | AI29: =I29 -> 0 | AJ29: =J29 -> 0 | AK29: =K29 -> 0 | AL29: =M29 -> 0 | AN29: =N29 -> 0 | AO29: 0 | AP29: 0 | AQ29: =AN29 -> 0
N30: 0 | AA30: =IF(E30="NO-OOS","N/A",IF(X30="Driver's License",IF(Y30>$Y$2,"SOS",IF(Z30>=$Y$3,"Valid",IF(AND(Z30<$Y$3,$Y$4>$Y$3,Z30>43831),"Covid","Expired"))),IF(X30="I9",IF(Z30>=$Y$3,"Valid",IF(AND(Z30<$Y$3,$Y$4>$Y$3,Z30>43831),"Covid","Expired")),IF(X30="Work Permit",IF(AND(Z30<=$Y$2,(Z30+365)>=$Y$3),"Valid","Expired"),IF(X30="Missing Residency","Missing",IF(X30="","","Other")))))) | AF30: =F30 -> 0 | AG30: =G30 -> 0 | AH30: =H30 -> 0 | AI30: =I30 -> 0 | AJ30: =J30 -> 0 | AK30: =K30 -> 0 | AL30: =M30 -> 0 | AN30: =N30 -> 0 | AO30: 0 | AP30: 0 | AQ30: =AN30 -> 0
N31: 0 | AA31: =IF(E31="NO-OOS","N/A",IF(X31="Driver's License",IF(Y31>$Y$2,"SOS",IF(Z31>=$Y$3,"Valid",IF(AND(Z31<$Y$3,$Y$4>$Y$3,Z31>43831),"Covid","Expired"))),IF(X31="I9",IF(Z31>=$Y$3,"Valid",IF(AND(Z31<$Y$3,$Y$4>$Y$3,Z31>43831),"Covid","Expired")),IF(X31="Work Permit",IF(AND(Z31<=$Y$2,(Z31+365)>=$Y$3),"Valid","Expired"),IF(X31="Missing Residency","Missing",IF(X31="","","Other")))))) | AF31: =F31 -> 0 | AG31: =G31 -> 0 | AH31: =H31 -> 0 | AI31: =I31 -> 0 | AJ31: =J31 -> 0 | AK31: =K31 -> 0 | AL31: =M31 -> 0 | AN31: =N31 -> 0 | AO31: 0 | AP31: 0 | AQ31: =AN31 -> 0
N32: 0 | AA32: =IF(E32="NO-OOS","N/A",IF(X32="Driver's License",IF(Y32>$Y$2,"SOS",IF(Z32>=$Y$3,"Valid",IF(AND(Z32<$Y$3,$Y$4>$Y$3,Z32>43831),"Covid","Expired"))),IF(X32="I9",IF(Z32>=$Y$3,"Valid",IF(AND(Z32<$Y$3,$Y$4>$Y$3,Z32>43831),"Covid","Expired")),IF(X32="Work Permit",IF(AND(Z32<=$Y$2,(Z32+365)>=$Y$3),"Valid","Expired"),IF(X32="Missing Residency","Missing",IF(X32="","","Other")))))) | AF32: =F32 -> 0 | AG32: =G32 -> 0 | AH32: =H32 -> 0 | AI32: =I32 -> 0 | AJ32: =J32 -> 0 | AK32: =K32 -> 0 | AL32: =M32 -> 0 | AN32: =N32 -> 0 | AO32: 0 | AP32: 0 | AQ32: =AN32 -> 0
N33: 0 | AA33: =IF(E33="NO-OOS","N/A",IF(X33="Driver's License",IF(Y33>$Y$2,"SOS",IF(Z33>=$Y$3,"Valid",IF(AND(Z33<$Y$3,$Y$4>$Y$3,Z33>43831),"Covid","Expired"))),IF(X33="I9",IF(Z33>=$Y$3,"Valid",IF(AND(Z33<$Y$3,$Y$4>$Y$3,Z33>43831),"Covid","Expired")),IF(X33="Work Permit",IF(AND(Z33<=$Y$2,(Z33+365)>=$Y$3),"Valid","Expired"),IF(X33="Missing Residency","Missing",IF(X33="","","Other")))))) | AF33: =F33 -> 0 | AG33: =G33 -> 0 | AH33: =H33 -> 0 | AI33: =I33 -> 0 | AJ33: =J33 -> 0 | AK33: =K33 -> 0 | AL33: =M33 -> 0 | AN33: =N33 -> 0 | AO33: 0 | AP33: 0 | AQ33: =AN33 -> 0
N34: 0 | AA34: =IF(E34="NO-OOS","N/A",IF(X34="Driver's License",IF(Y34>$Y$2,"SOS",IF(Z34>=$Y$3,"Valid",IF(AND(Z34<$Y$3,$Y$4>$Y$3,Z34>43831),"Covid","Expired"))),IF(X34="I9",IF(Z34>=$Y$3,"Valid",IF(AND(Z34<$Y$3,$Y$4>$Y$3,Z34>43831),"Covid","Expired")),IF(X34="Work Permit",IF(AND(Z34<=$Y$2,(Z34+365)>=$Y$3),"Valid","Expired"),IF(X34="Missing Residency","Missing",IF(X34="","","Other")))))) | AF34: =F34 -> 0 | AG34: =G34 -> 0 | AH34: =H34 -> 0 | AI34: =I34 -> 0 | AJ34: =J34 -> 0 | AK34: =K34 -> 0 | AL34: =M34 -> 0 | AN34: =N34 -> 0 | AO34: 0 | AP34: 0 | AQ34: =AN34 -> 0
N35: =SUM(N9:N34) -> 0 | O35: =SUM(O9:O34) -> 0
H41: Retainer Billings | O41: Normal Hours TOTALS
G42: Invoice_Number | H42: POP | I42: Qualify | J42: Total Amount | K42: Qualified Amount | O42: PENDING | P42: NO-OOS | Q42: NO-IL | R42: YES-OOS | S42: YES
H43: =_xlfn.XLOOKUP($G43,$B$9:$B$34,$V$9:$V$34) -> 0 | I43: =_xlfn.XLOOKUP($G43,$B$9:$B$34,$E$9:$E$34) -> 0 | J43: =SUMIFS($O$9:$O$34,$B$9:$B$34,$G43) -> 0 | K43: =SUMIFS($O$9:$O$34,$B$9:$B$34,$G43,$E$9:$E$34,"YES") -> 0 | O43: =SUMIFS($N$9:$N$34, $E$9:$E$34, O$42, $R$9:$R$34, "<>Production") -> 0 | P43: =SUMIFS($N$9:$N$34, $E$9:$E$34, P$42, $R$9:$R$34, "<>Production") -> 0 | Q43: =SUMIFS($N$9:$N$34, $E$9:$E$34, Q$42, $R$9:$R$34, "<>Production") -> 0 | R43: =SUMIFS($N$9:$N$34, $E$9:$E$34, R$42, $R$9:$R$34, "<>Production") -> 0 | S43: =SUMIFS($N$9:$N$34, $E$9:$E$34, S$42, $R$9:$R$34, "<>Production") -> 0 | T43: =SUM(O43:S43) -> 0
H44: =_xlfn.XLOOKUP($G44,$B$9:$B$34,$V$9:$V$34) -> 0 | I44: =_xlfn.XLOOKUP($G44,$B$9:$B$34,$E$9:$E$34) -> 0 | J44: =SUMIFS($O$9:$O$34,$B$9:$B$34,$G44) -> 0 | K44: =SUMIFS($O$9:$O$34,$B$9:$B$34,$G44,$E$9:$E$34,"YES") -> 0 | T44: =T43-Q62 -> 0
H45: =_xlfn.XLOOKUP($G45,$B$9:$B$34,$V$9:$V$34) -> 0 | I45: =_xlfn.XLOOKUP($G45,$B$9:$B$34,$E$9:$E$34) -> 0 | J45: =SUMIFS($O$9:$O$34,$B$9:$B$34,$G45) -> 0 | K45: =SUMIFS($O$9:$O$34,$B$9:$B$34,$G45,$E$9:$E$34,"YES") -> 0
H46: =_xlfn.XLOOKUP($G46,$B$9:$B$34,$V$9:$V$34) -> 0 | I46: =_xlfn.XLOOKUP($G46,$B$9:$B$34,$E$9:$E$34) -> 0 | J46: =SUMIFS($O$9:$O$34,$B$9:$B$34,$G46) -> 0 | K46: =SUMIFS($O$9:$O$34,$B$9:$B$34,$G46,$E$9:$E$34,"YES") -> 0
H47: =_xlfn.XLOOKUP($G47,$B$9:$B$34,$V$9:$V$34) -> 0 | I47: =_xlfn.XLOOKUP($G47,$B$9:$B$34,$E$9:$E$34) -> 0 | J47: =SUMIFS($O$9:$O$34,$B$9:$B$34,$G47) -> 0 | K47: =SUMIFS($O$9:$O$34,$B$9:$B$34,$G47,$E$9:$E$34,"YES") -> 0 | O47: Retainer Billings TOTALS
H48: =_xlfn.XLOOKUP($G48,$B$9:$B$34,$V$9:$V$34) -> 0 | I48: =_xlfn.XLOOKUP($G48,$B$9:$B$34,$E$9:$E$34) -> 0 | J48: =SUMIFS($O$9:$O$34,$B$9:$B$34,$G48) -> 0 | K48: =SUMIFS($O$9:$O$34,$B$9:$B$34,$G48,$E$9:$E$34,"YES") -> 0 | O48: PENDING | P48: NO-OOS | Q48: NO-IL | R48: YES-OOS | S48: YES
G49: Total Retainer Billings | J49: =SUM(J43:J48) -> 0 | K49: =SUM(K43:K48) -> 0 | O49: =SUMIFS($O$9:$O$34, $E$9:$E$34, O$42, $R$9:$R$34, "<>Production") -> 0 | P49: =SUMIFS($O$9:$O$34, $E$9:$E$34, P$42, $R$9:$R$34, "<>Production") -> 0 | Q49: =SUMIFS($O$9:$O$34, $E$9:$E$34, Q$42, $R$9:$R$34, "<>Production") -> 0 | R49: =SUMIFS($O$9:$O$34, $E$9:$E$34, R$42, $R$9:$R$34, "<>Production") -> 0 | S49: =SUMIFS($O$9:$O$34, $E$9:$E$34, S$42, $R$9:$R$34, "<>Production") -> 0 | T49: =SUM(O49:S49) -> 0
G50: Total Agency Hours $ | J50: =S43+R43 -> 0 | K50: =Q58+R43 -> 0 | T50: =T49-J49 -> 0
G51: Difference | J51: =SUM(J43:J44)-J50 -> 0 | K51: =SUM(K43:K44)-K50 -> 0 | L51: <-- Notify If Red
O53: Production Hours TOTALS
O54: PENDING | P54: NO-OOS | Q54: NO-IL | R54: YES-OOS | S54: YES
O55: =SUMIFS($N$9:$N$34,$E$9:$E$34,O$42,$R$9:$R$34,"Production") -> 0 | P55: =SUMIFS($N$9:$N$34,$E$9:$E$34,P$42,$R$9:$R$34,"Production") -> 0 | Q55: =SUMIFS($N$9:$N$34,$E$9:$E$34,Q$42,$R$9:$R$34,"Production") -> 0 | R55: =SUMIFS($N$9:$N$34,$E$9:$E$34,R$42,$R$9:$R$34,"Production") -> 0 | S55: =SUMIFS($N$9:$N$34,$E$9:$E$34,S$42,$R$9:$R$34,"Production") -> 0 | T55: =SUM(O55:S55) -> 0
T56: =T55-Q68 -> 0
P58: Normal Eligible | Q58: =S43 -> 0
P59: Normal OOS Eligible | Q59: =R43 -> 0
P60: Normal Pending | Q60: =O43 -> 0
P61: Normal Ineligible | Q61: =P43+Q43 -> 0
Q62: =SUM(Q58:Q61) -> 0 | R62: =Q62-T43 -> 0
P64: Production Hours Eligible | Q64: =S55 -> 0
P65: Production Hours OOS Eligible | Q65: =R55 -> 0
P66: Production Hours Pending | Q66: =O55 -> 0
P67: Production Hours Ineligible | Q67: =P55+Q55 -> 0
Q68: =SUM(Q64:Q67) -> 0 | R68: =Q68-T55 -> 0
P70: Total Eligible | Q70: =S43+S55 -> 0
P71: Total OOS Eligible | Q71: =R43+R55 -> 0
P72: Total Pending | Q72: =O43+O55 -> 0
P73: Total Ineligible | Q73: =P43+Q43+P55+Q55 -> 0
P74: Total Expenses | Q74: =SUM(Q70:Q73) -> 0 | R74: =Q74-(T43+T55) -> 0

Sheet Agency Job Description
B2: Award Date
B3: Pre Pro Date
B4: Shoot Date
B5: Production Wrap Date
B6: Post Production Date
B8: Employee | C8: Employee Title | D8: Job Description | E8: Pre-Production (Insert Date Range) | F8: Production (Insert Date Range) | G8: Post-Production (Insert Date Range) | H8: Total Hours
D9: Pre-production: Describe the specific work done during this hase of production. | H9: 0
D10: Production: Describe the specific work done during this hase of production. | H10: 0
D11: Post-production: Describe the specific work done during this hase of production. | H11: 0
D12: Pre-production: Describe the specific work done during this hase of production. | H12: 0
D13: Production: Describe the specific work done during this hase of production. | H13: 0
D14: Post-production: Describe the specific work done during this hase of production. | H14: 0
D15: Pre-production: Describe the specific work done during this hase of production. | H15: 0
D16: Production: Describe the specific work done during this hase of production. | H16: 0
D17: Post-production: Describe the specific work done during this hase of production. | H17: 0
D18: Pre-production: Describe the specific work done during this hase of production. | H18: 0
D19: Production: Describe the specific work done during this hase of production. | H19: 0
D20: Post-production: Describe the specific work done during this hase of production. | H20: 0
... D26: Post-production: Describe the specific work done during this hase of production. | H26: 0
A29: employee_title | B29: time | C29: single_description | D29: Approved | E29: case_analysis | F29: ending_analysis | G29: 0.3915 | H29: 3182 | I29: 8127 | K29: 4945 | M29: Take the following input sentence, remove any specific names and locations, and rewrite it in the past tense. If the sentence mentions multiple people, start the output with "Part of the team that" and focus on condensing the core action described. Ensure the output does not contain any names, specific locations, or mention who the action was done with. Input Sentence Starts Here: | O29: Take the following input sentence, remove any specific names and locations, and rewrite it in the past tense. If the sentence mentions multiple people, start the output with "Part of the team that" and focus on condensing the core action described. Ensure the output does not contain any names, specific locations, or mention who the action was done with. Input Sentence Starts Here:
A30: Acct Dir | B30: post_production | C30: Attended all internal agency reviews | D30: x | E30: Capital | F30: Neither
A31: Acct Dir | B31: post_production | C31: Attended all internal agency reviews with Producer & Creative Team | D31: x | E31: Capital | F31: Neither
A32: Acct Dir | B32: post_production | C32: Attended all internal reviews with Producers and Creative Team | D32: x | E32: Capital | F32: Neither
A33: Acct Dir | B33: post_production | C33: Captured all client feedback and relayed to internal agency teams | D33: x | E33: Capital | F33: Neither
A34: Acct Dir | B34: post_production | C34: Captured client feedback and relayed to internal agency teams | D34: x | E34: Capital | F34: Neither
A35: Acct Dir | B35: post_production | C35: Coordinated & attended all client meetings for rough cut reviews/approvals | D35: x | E35: Capital | F35: Neither
A36: Acct Dir | B36: post_production | C36: Coordinated all client meetings for rough cut review/approvals | D36: x | E36: Capital | F36: Neither
A37: Acct Dir | B37: post_production | C37: Coordinated all client meetings for updates on production | D37: x | E37: Capital | F37: Neither
A38: Acct Dir | B38: post_production | C38: Coordinated client meetings for rough cut review/approvals | D38: x | E38: Capital | F38: Neither
A39: Acct Dir | B39: post_production | C39: Coordinated client meetings for updates on production | D39: x | E39: Capital | F39: Neither
A40: Acct Dir | B40: post_production | C40: Ensured all invoices/payments had been made on the project | D40: x | E40: Capital | F40: Neither
A41: Acct Dir | B41: post_production | C41: Ensured invoices/payments had been made on the project | D41: x | E41: Capital | F41: Neither
... A297: Art Director | B297: production | C297: Yi was part of Creative Team that worked with Chloe Micek (Acct Supervisor), director & line producer on set direction, lighting & props | D297: x | E297: Capital | F297: Neither
A298: Assistant Program Mgr | B298: post_production | C298: Assisted in the organization and management of post-production schedules, ensuring timely completion of editing and revisions. | D298: x
A299: Assistant Program Mgr | B299: post_production | C299: Collaborated with the editing team to gather and catalog raw footage, ensuring all necessary clips were available for review. | D299: x
A300: Assistant Program Mgr | B300: post_production | C300: Facilitated communication between the creative team and clients to gather feedback on the initial cut of the commercial. | D300: x
A301: Assistant Program Mgr | B301: post_production | C301: Maintained a project tracking system to monitor the status of edits, visual effects, and sound design, ensuring deadlines were met. | D301: x
A302: Assistant Program Mgr | B302: post_production | C302: Prepared final project deliverables for client review and distribution, ensuring all materials were formatted according to specifications. | D302: x
A303: Assistant Program Mgr | B303: pre_production | C303: Assisted in coordinating project timelines and schedules, ensuring that all pre-production activities were completed on time. | D303: x
A304: Assistant Program Mgr | B304: pre_production | C304: Collaborated with the program manager to prepare and distribute project briefs that outlined objectives and deliverables to the creative team. | D304: x
A305: Assistant Program Mgr | B305: pre_production | C305: Conducted research to identify potential production vendors and facilitated initial outreach for quotes and availability. | D305: x
A306: Assistant Program Mgr | B306: pre_production | C306: Organized and maintained project documentation, including contracts, scripts, and meeting notes, to ensure all stakeholders had access to relevant information. | D306: x
A307: Assistant Program Mgr | B307: pre_production | C307: Participated in brainstorming sessions with the creative team to contribute ideas and feedback on concepts and strategies for the commercial. | D307: x
A308: Assistant Program Mgr | B308: production | C308: Assisted in coordinating logistics for the shoot, including location scouting, transportation arrangements, and catering services. | D308: x
A309: Assistant Program Mgr | B309: production | C309: Communicated with crew members to relay important updates and ensure that everyone was aligned on the production goals. | D309: x
... A342: Assoc Bus Affairs Mgr | B342: production | C342: Reviewed call sheets and daily production reports to verify that all contractual terms were being upheld by involved parties. | D342: x
A343: Assoc Creative Dir | B343: post_production | C343: Attended all client reviews along with Account Team | D343: x | E343: Capital | F343: Neither
A344: Assoc Creative Dir | B344: post_production | C344: Attended all internal agency reviews | D344: x | E344: Capital | F344: Neither
A345: Assoc Creative Dir | B345: post_production | C345: Managed internal agency on design, layout and creation of graphic supers on all versions of cinemagraphs/spots | D345: x | E345: Capital | F345: Neither
A346: Assoc Creative Dir | B346: post_production | C346: Part of Creative Team that ensured edit specifications were met | D346: x | E346: Capital | F346: Neither
A347: Assoc Creative Dir | B347: post_production | C347: Part of Creative Team that worked with internal agency to ensure timing of visual & graphic supers were aligned in all versions of cinemagraphs/spots | D347: x | E347: Capital | F347: Neither
A348: Assoc Creative Dir | B348: post_production | C348: Presented client with rough cut of spots, noted client revisions & communicated revisions to internal agency team | D348: x | E348: Capital | F348: Neither
A349: Assoc Creative Dir | B349: post_production | C349: Supervised internal agency on all editorial services including edits of graphics/titles/end cards & finishing of cinemagraphs/spots | D349: x | E349: Capital | F349: Neither
A350: Assoc Creative Dir | B350: post_production | C350: Supervised assembly of final spots, and all versioning of spots for client review | D350: x | E350: Capital | F350: Neither
A351: Assoc Creative Dir | B351: post_production | C351: Supervised designers on all post production | D351: x | E351: Capital | F351: post
A352: Assoc Creative Dir | B352: pre_production | C352: Along with client, has final approval on all setups and shot completion. | D352: x | E352: Capital | F352: Neither
A353: Assoc Creative Dir | B353: pre_production | C353: Attended preproduction meetings with internal agency teams | D353: x | E353: Capital | F353: Neither
A354: Assoc Creative Dir | B354: pre_production | C354: Ensured client, agency and vendors are aligned with the production decisions. | D354: x | E354: Capital | F354: Neither
... A491: Assoc Dir/Rights Mgr | B491: production | C491: Manage production workflow to ensure creative is captured | D491: x | E491: Capital | F491: Neither
A492: Assoc Motion Designer | B492: post_production | C492: Assisted in preparing the final project files for archiving and documentation. | D492: x
A493: Assoc Motion Designer | B493: post_production | C493: Compiled a portfolio piece showcasing the work completed on the commercial for future reference. | D493: x
A494: Assoc Motion Designer | B494: post_production | C494: Created promotional graphics and social media assets derived from the commercial animations. | D494: x
A495: Assoc Motion Designer | B495: post_production | C495: Made necessary adjustments to animations based on director feedback after the initial screening. | D495: x
A496: Assoc Motion Designer | B496: post_production | C496: Reviewed the final cut of the commercial to ensure all animations were correctly implemented. | D496: x
A497: Assoc Motion Designer | B497: pre_production | C497: Assisted in creating mood boards to visualize the desired aesthetic and tone of the commercial. | D497: x
A498: Assoc Motion Designer | B498: pre_production | C498: Collaborated with the creative team to conceptualize and develop storyboards for the commercial. | D498: x
A499: Assoc Motion Designer | B499: pre_production | C499: Participated in team meetings to discuss project timelines and deliverables. | D499: x
A500: Assoc Motion Designer | B500: pre_production | C500: Prepared asset lists based on the storyboard for the animation production phase. | D500: x
A501: Assoc Motion Designer | B501: pre_production | C501: Researched design trends and gathered reference materials to inform the animation style. | D501: x
A502: Assoc Motion Designer | B502: production | C502: Assisted in setting up and managing project files within the animation software. | D502: x
A503: Assoc Motion Designer | B503: production | C503: Collaborated with other designers and animators to refine animations and ensure consistency. | D503: x
... A521: Assoc Program Dir, Content & Packaging | B521: production | C521: Worked closely with the director and cinematographer to provide guidance on content alignment and adherence to the creative vision during filming. | D521: x
A522: Associate Creative Director | B522: post_production | C522: Addresses client revisions. | D522: x | E522: Capital | F522: Neither
A523: Associate Creative Director | B523: post_production | C523: Approves music search with audio engineer. | D523: x | E523: Capital | F523: Neither
A524: Associate Creative Director | B524: post_production | C524: Oversees all post production edits and additional asset creation. | D524: x | E524: Capital | F524: Neither
A525: Associate Creative Director | B525: post_production | C525: Reviews clean up of film and additional fixes to final picture. | D525: x | E525: Capital | F525: Neither
A526: Associate Creative Director | B526: post_production | C526: Supervises creative team and audio engineer, records rough scratch tracks. | D526: x | E526: Capital | F526: Neither
A527: Associate Creative Director | B527: post_production | C527: Supervises creative team with edits and versions. | D527: x | E527: Capital | F527: Neither
A528: Associate Creative Director | B528: post_production | C528: Works on sounds design with creative team and audio engineer. | D528: x | E528: Capital | F528: Neither
A529: Associate Creative Director | B529: pre_production | C529: Presents examples of art direction for locations. | D529: x | E529: Capital | F529: Neither
A530: Associate Creative Director | B530: production | C530: Attends shoot and communicates on set with agency team, and with clients. | D530: x | E530: Capital | F530: Neither
A531: Associate Creative Director | B531: production | C531: Ensures client, agency and vendors are aligned with the production decisions. | D531: x | E531: Capital | F531: Neither
A532: Associate Creative Director | B532: production | C532: Manages shoot/production to ensure creative follows storyboards. | D532: x | E532: Capital | F532: Neither
A533: Associate Creative Director, Art Director | B533: post_production | C533: Addresses client revisions. | D533: x | E533: Capital | F533: Neither
... A646: BBA Coordinator | B646: post_production | C646: Managed usage payments for talent | D646: x | E646: Capital | F646: Neither
A647: Brand Designer | B647: post_production | C647: Collaborated with the sound and editing teams to ensure that brand guidelines were adhered to in all final assets. | D647: x
A648: Brand Designer | B648: post_production | C648: Delivered final branded assets, including logos and design elements, for inclusion in the finished commercial. | D648: x
A649: Brand Designer | B649: post_production | C649: Provided feedback on font choices, graphics, and other design elements added during the editing process. | D649: x
A650: Brand Designer | B650: post_production | C650: Reviewed the final edit to ensure that the overall design and branding were consistent throughout the commercial. | D650: x
A651: Brand Designer | B651: post_production | C651: Worked with the post-production team to ensure that color grading and visual effects remained true to the brand's visual identity. | D651: x
A652: Brand Designer | B652: pre_production | C652: Collaborated with the creative team to develop visual concepts and brand guidelines for the commercial. | D652: x
A653: Brand Designer | B653: pre_production | C653: Designed initial mockups, storyboards, and mood boards to guide the creative direction of the production. | D653: x
A654: Brand Designer | B654: pre_production | C654: Presented design ideas and brand concepts to the client for approval, ensuring alignment with their vision and brand identity. | D654: x
A655: Brand Designer | B655: pre_production | C655: Provided detailed design briefs to vendors and external teams, ensuring consistency across all pre-production assets. | D655: x
A656: Brand Designer | B656: pre_production | C656: Worked closely with the production team to ensure that set designs, props, and wardrobe choices reflected the brand’s aesthetics. | D656: x
A657: Brand Designer | B657: production | C657: Collaborated with the director and production designer to ensure that every scene captured the intended brand look and feel. | D657: x
A658: Brand Designer | B658: production | C658: Communicated any necessary changes to the design or visual style to the production team during filming. | D658: x
... A661: Brand Designer | B661: production | C661: Provided on-set art direction, offering adjustments to visual elements as needed to maintain brand consistency. | D661: x
A662: Broadcast Support | B662: post_production | C662: Attended all internal and client reviews and coordinated final client approval of spots | D662: x | E662: Capital | F662: Neither
A663: Broadcast Support | B663: post_production | C663: Ensured all job files were complete with all the necessary production paperwork | D663: x | E663: Capital | F663: Neither
...

Sheet Agency Sub-Vendors
B1: Production Tax Incentives Agency Sub-Vendors
D3: Project Title: | E3: =#REF! -> #REF!
D4: Shoot Date: | E4: =#REF! -> #REF!
D5: Work State: | E5: =#REF! -> #REF! | Y5: Don't edit this part; with formulas
O6: INVOICE/ W9 | Q6: PROOF OF PAYMENT
B7: ITEM # | C7: Qualify? | D7: Vendor Name | E7: Description | F7: Address | G7: City | H7: Zip | I7: State | J7: Invoice Date | K7: Invoice # | L7: Invoice $ | M7: Non-Eligible $ | N7: Eligible Total $ | O7: Received Invoice? | P7: W9 and Valid Date | Q7: Proof of Payment? | R7: Pymt Method | S7: Pymt # | T7: Payment Entity | U7: Job No. | V7: Client Billing No. | W7: Notes: | Y7: VENDOR NAME | Z7: DESCRIPTION | AA7: ADDRESS | AB7: CITY | AC7: ZIP | AD7: INVOICE DATE | AE7: INVOICE NUMBER | AF7: AMOUNT
Y8: Agency Sub-Vendors
B9: 1 | L9: 0 | M9: 0 | N9: =L9-M9 -> 0 | Y9: =D9 -> 0 | Z9: =E9 -> 0 | AA9: =F9 -> 0 | AB9: =G9 -> 0 | AC9: =H9 -> 0 | AD9: =J9 -> 0 | AE9: =K9 -> 0 | AF9: =N9 -> 0
B10: 2 | L10: 0 | M10: 0 | N10: =L10-M10 -> 0 | Y10: =D10 -> 0 | Z10: =E10 -> 0 | AA10: =F10 -> 0 | AB10: =G10 -> 0 | AC10: =H10 -> 0 | AD10: =J10 -> 0 | AE10: =K10 -> 0 | AF10: =N10 -> 0
B11: 3 | L11: 0 | M11: 0 | N11: =L11-M11 -> 0 | Y11: =D11 -> 0 | Z11: =E11 -> 0 | AA11: =F11 -> 0 | AB11: =G11 -> 0 | AC11: =H11 -> 0 | AD11: =J11 -> 0 | AE11: =K11 -> 0 | AF11: =N11 -> 0
B12: 4 | L12: 0 | M12: 0 | N12: =L12-M12 -> 0 | Y12: =D12 -> 0 | Z12: =E12 -> 0 | AA12: =F12 -> 0 | AB12: =G12 -> 0 | AC12: =H12 -> 0 | AD12: =J12 -> 0 | AE12: =K12 -> 0 | AF12: =N12 -> 0
B13: 5 | L13: 0 | M13: 0 | N13: =L13-M13 -> 0 | Y13: =D13 -> 0 | Z13: =E13 -> 0 | AA13: =F13 -> 0 | AB13: =G13 -> 0 | AC13: =H13 -> 0 | AD13: =J13 -> 0 | AE13: =K13 -> 0 | AF13: =N13 -> 0
B14: 6 | L14: 0 | M14: 0 | N14: =L14-M14 -> 0 | Y14: =D14 -> 0 | Z14: =E14 -> 0 | AA14: =F14 -> 0 | AB14: =G14 -> 0 | AC14: =H14 -> 0 | AD14: =J14 -> 0 | AE14: =K14 -> 0 | AF14: =N14 -> 0
B15: 7 | L15: 0 | M15: 0 | N15: =L15-M15 -> 0 | Y15: =D15 -> 0 | Z15: =E15 -> 0 | AA15: =F15 -> 0 | AB15: =G15 -> 0 | AC15: =H15 -> 0 | AD15: =J15 -> 0 | AE15: =K15 -> 0 | AF15: =N15 -> 0
B16: 8 | L16: 0 | M16: 0 | N16: =L16-M16 -> 0 | Y16: =D16 -> 0 | Z16: =E16 -> 0 | AA16: =F16 -> 0 | AB16: =G16 -> 0 | AC16: =H16 -> 0 | AD16: =J16 -> 0 | AE16: =K16 -> 0 | AF16: =N16 -> 0
B17: 9 | L17: 0 | M17: 0 | N17: =L17-M17 -> 0 | Y17: =D17 -> 0 | Z17: =E17 -> 0 | AA17: =F17 -> 0 | AB17: =G17 -> 0 | AC17: =H17 -> 0 | AD17: =J17 -> 0 | AE17: =K17 -> 0 | AF17: =N17 -> 0
B18: 10 | L18: 0 | M18: 0 | N18: =L18-M18 -> 0 | Y18: =D18 -> 0 | Z18: =E18 -> 0 | AA18: =F18 -> 0 | AB18: =G18 -> 0 | AC18: =H18 -> 0 | AD18: =J18 -> 0 | AE18: =K18 -> 0 | AF18: =N18 -> 0
B19: 11 | L19: 0 | M19: 0 | N19: =L19-M19 -> 0 | Y19: =D19 -> 0 | Z19: =E19 -> 0 | AA19: =F19 -> 0 | AB19: =G19 -> 0 | AC19: =H19 -> 0 | AD19: =J19 -> 0 | AE19: =K19 -> 0 | AF19: =N19 -> 0
B20: 12 | L20: 0 | M20: 0 | N20: =L20-M20 -> 0 | Y20: =D20 -> 0 | Z20: =E20 -> 0 | AA20: =F20 -> 0 | AB20: =G20 -> 0 | AC20: =H20 -> 0 | AD20: =J20 -> 0 | AE20: =K20 -> 0 | AF20: =N20 -> 0
... B38: 30 | L38: 0 | M38: 0 | N38: =L38-M38 -> 0 | Y38: =D38 -> 0 | Z38: =E38 -> 0 | AA38: =F38 -> 0 | AB38: =G38 -> 0 | AC38: =H38 -> 0 | AD38: =J38 -> 0 | AE38: =K38 -> 0 | AF38: =N38 -> 0
L39: 0 | M39: 0 | N39: =L39-M39 -> 0 | Y39: =D39 -> 0 | Z39: =E39 -> 0 | AA39: =F39 -> 0 | AB39: =G39 -> 0 | AC39: =H39 -> 0 | AD39: =J39 -> 0 | AE39: =K39 -> 0 | AF39: =N39 -> 0
Y40: =D40 -> 0 | Z40: =E40 -> 0 | AA40: =F40 -> 0 | AB40: =G40 -> 0 | AC40: =H40 -> 0 | AD40: =J40 -> 0 | AE40: =K40 -> 0 | AF40: =N40 -> 0
L41: =SUBTOTAL(9,L8:L40) -> 0 | M41: =SUBTOTAL(9,M8:M40) -> 0 | N41: =SUBTOTAL(9,N8:N40) -> 0 | S41: =SUBTOTAL(2,S8:S40) -> 0
L44: =SUM(L8:L40) -> 0 | M44: =SUM(M8:M40) -> 0 | N44: =SUM(N8:N40) -> 0
K48: ELIGIBLE TOTAL
K49: PENDING | L49: NO-OOS | M49: NO-IL | N49: YES
K50: =SUMIF($C$8:$C$40,K49,$N$8:$N$40) -> 0 | L50: =SUMIF($C$8:$C$40,L49,$N$8:$N$40) -> 0 | M50: =SUMIF($C$8:$C$40,M49,$N$8:$N$40) -> 0 | N50: =SUMIF($C$8:$C$39,N49,$N$8:$N$40) -> 0 | O50: =SUM(K50:N50) -> 0
O51: =N44-O50 -> 0
K53: INELIGIBLE TOTAL
K54: PENDING | L54: NO-OOS | M54: NO-IL | N54: YES
K55: =SUMIF($C$8:$C$40,K54,$M$8:$M$40) -> 0 | L55: =SUMIF($C$8:$C$40,L54,$M$8:$M$40) -> 0 | M55: =SUMIF($C$8:$C$40,M54,$M$8:$M$40) -> 0 | N55: =SUMIF($C$8:$C$40,N54,$M$8:$M$40) -> 0 | O55: =SUM(K55:N55) -> 0
O56: =M44-O55 -> 0
L60: Total Eligible | M60: =N50 -> 0
L61: Total Pending | M61: =K50 -> 0
L62: Total Ineligible | M62: =L50+M50+L55+M55+N55+K55 -> 0
L63: Total Expenses | M63: =SUM(M60:M62) -> 0 | N63: =L44-M63 -> 0
L67: Total Eligible | M67: =M60 -> 0
L68: Agency Fees | M68: ='Talent & Extras'!N84 -> 0
L69: Handling Fees | M69: ='Talent & Extras'!O85 -> 0
L70: Revised Qualified Total | M70: =SUM(M67:M69) -> 0

Sheet Loan Out Withholding
A1: LOAN OUT WITHHOLDING
A3: Job Code | B3: GM 006
A4: Shoot Date | B4: 46155 | C4: GENERAL MILLS REESES PUFFS
A6: JOB CODE | B6: WTH REMITTED? | C6: Crew / Employee Name (Last, First) | D6: POSITION / TITLE | E6: LOAN OUT NAME | F6: Federal Tax Classification | G6: SSN | H6: FEIN | I6: INVOICE/ GROSS AMOUNT | J6: AMOUNT WITHELD | K6: CREW POSITION | L6: PAYROLL COMPANY | M6: ADDRESS | N6: HOME STATE | O6: WORK STATE | P6: INVOICE DATE | Q6: Invoice # | R6: PAYMENT DATE | S6: NOTES
A7: GM 006 | B7: FALSE | C7: Jones, Hunter | D7: Prop Master | E7: HUNTER JONES | F7: Individual | H7: 67-0902390 | I7: 850 | J7: =I7*0.0499 -> 42.415 | K7: PRODUCTION ASSISTANT | L7: WRAPBOOK | M7: 123 Main Street, El Segundo, CA | N7: CA | O7: IL | P7: 46155 | Q7: 1807 | R7: 46162
A8: GM 006 | B8: FALSE | C8: Doe, John | D8: Director of Photography | E8: AISLE 35 STUDIOS LLC | F8: LLC | H8: 67-0902391 | I8: 1725 | J8: =I8*0.0499 -> 86.0775 | K8: SWING G&E | L8: WRAPBOOK | M8: 124 Main Street, El Segundo, CA | N8: IL | O8: IL | P8: 46156 | Q8: 240065 | R8: 46162
A9: GM 006 | B9: FALSE | C9: Knobloch, Jason | D9: BB Electric | E9: JASON KNOBLOCH | F9: S-Corp | H9: 67-0902392 | I9: 6150.76 | J9: =I9*0.0499 -> 306.92292 | K9: CAMERA OPERATOR | L9: WRAPBOOK | M9: 125 Main Street, El Segundo, CA | N9: GA | O9: IL | P9: 46157 | Q9: 101-34 | R9: 46162
A10: GM 006 | B10: FALSE | C10: Miller, Elaine | D10: Director | E10: ELAINE SUZANNE MILLER | F10: C-Corp | H10: 67-0902393 | I10: 1518.75 | J10: =I10*0.0499 -> 75.785625 | K10: DIGITAL TECH | L10: WRAPBOOK | M10: 126 Main Street, El Segundo, CA | N10: GA | O10: IL | P10: 46158 | Q10: 1qw123 | R10: 46162
A11: GM 006 | B11: FALSE | C11: Reed, Don | D11: Swing | E11: DON REED JR. | F11: LLC | H11: 67-0902394 | I11: 1400 | J11: =I11*0.0499 -> 69.86 | K11: DIT/VTR | L11: WRAPBOOK | M11: 127 Main Street, El Segundo, CA | N11: GA | O11: IL | P11: 46159 | Q11: 2025-34 | R11: 46162
A12: GM 006 | B12: FALSE | C12: Smith, Joe | D12: Digitech | E12: MAD SWORDSMAN PRODUCTIONS LLC | F12: LLC | H12: 67-0902395 | I12: 18000 | J12: =I12*0.0499 -> 898.2 | K12: PRODUCTION DESIGNER | L12: INVOICE - 1099 | M12: 128 Main Street, El Segundo, CA | N12: GA | O12: IL | P12: 46160 | Q12: 2025-00001 | R12: 46162
